Workbook

Sheet Model Countries
A1: Government health spending as % of government spending, model countries (71), 2000-2023 (WHO GHED, GGHE-D % GGE)
A2: Abuja target | B2: 0.15 | C2: Grey cell = same value as the year before (likely carried forward by WHO, not a new figure). Blank = no WHO estimate. See Notes.
A4: Country | B4: ISO3 | C4: MOU 15 | D4: 2000 | E4: 2001 | F4: 2002 | G4: 2003 | H4: 2004 | I4: 2005 | J4: 2006 | K4: 2007 | L4: 2008 | M4: 2009 | N4: 2010 | O4: 2011 | P4: 2012 | Q4: 2013 | R4: 2014 | S4: 2015 | T4: 2016 | U4: 2017 | V4: 2018 | W4: 2019 | X4: 2020 | Y4: 2021 | Z4: 2022 | AA4: 2023 | AB4: 2024 | AC4: Latest | AD4: Latest Year | AE4: Avg 2019-2023 | AF4: Room to Abuja target
A5: Angola | B5: AGO | D5: 0.027385826 | E5: 0.059682546 | F5: 0.041912308 | G5: 0.04260468 | H5: 0.056592388 | I5: 0.048206377 | J5: 0.047187376 | K5: 0.045162711 | L5: 0.040603714 | M5: 0.057778893 | N5: 0.04249568 | O5: 0.045805688 | P5: 0.042015133 | Q5: 0.045754008 | R5: 0.036156802 | S5: 0.045626254 | T5: 0.054326968 | U5: 0.053643193 | V5: 0.053643193 | W5: 0.055068841 | X5: 0.073050218 | Y5: 0.087773657 | Z5: 0.06699635 | AA5: 0.058957567 | AC5: =LOOKUP(9.99E+307,D5:AB5) -> 0.058957567 | AD5: =LOOKUP(9.99E+307,D5:AB5,D$4:AB$4) -> 2023 | AE5: =IFERROR(AVERAGE(W5:AB5),"") -> 0.068369327 | AF5: =MAX(0,$B$2-AC5) -> 0.091042433
A6: Azerbaijan | B6: AZE | D6: 0.047502904 | E6: 0.047982063 | F6: 0.031931574 | G6: 0.035723515 | H6: 0.035575993 | I6: 0.039594917 | J6: 0.0342998 | K6: 0.034903398 | L6: 0.027519121 | M6: 0.032848394 | N6: 0.031712611 | O6: 0.028160138 | P6: 0.030453246 | Q6: 0.028222861 | R6: 0.031070068 | S6: 0.033728263 | T6: 0.03289871 | U6: 0.028237727 | V6: 0.026780353 | W6: 0.032879271 | X6: 0.057977181 | Y6: 0.046051784 | Z6: 0.036410747 | AA6: 0.042580843 | AC6: =LOOKUP(9.99E+307,D6:AB6) -> 0.042580843 | AD6: =LOOKUP(9.99E+307,D6:AB6,D$4:AB$4) -> 2023 | AE6: =IFERROR(AVERAGE(W6:AB6),"") -> 0.043179965 | AF6: =MAX(0,$B$2-AC6) -> 0.10741916
A7: Bangladesh | B7: BGD | D7: 0.052114644 | E7: 0.035785534 | F7: 0.045399313 | G7: 0.047553134 | H7: 0.048652663 | I7: 0.043888373 | J7: 0.047282033 | K7: 0.050751882 | L7: 0.038409143 | M7: 0.041153383 | N7: 0.044394164 | O7: 0.04181591 | P7: 0.040162044 | Q7: 0.036174552 | R7: 0.035924532 | S7: 0.033768887 | T7: 0.040993581 | U7: 0.041070523 | V7: 0.037503543 | W7: 0.026642132 | X7: 0.026732917 | Y7: 0.030042543 | Z7: 0.02623276 | AA7: 0.024716196 | AC7: =LOOKUP(9.99E+307,D7:AB7) -> 0.024716196 | AD7: =LOOKUP(9.99E+307,D7:AB7,D$4:AB$4) -> 2023 | AE7: =IFERROR(AVERAGE(W7:AB7),"") -> 0.02687331 | AF7: =MAX(0,$B$2-AC7) -> 0.1252838
A8: Belize | B8: BLZ | D8: 0.05847578 | E8: 0.068270483 | F8: 0.075145411 | G8: 0.071356831 | H8: 0.078819284 | I8: 0.083321724 | J8: 0.093324451 | K8: 0.10768107 | L8: 0.13384028 | M8: 0.12482731 | N8: 0.12763881 | O8: 0.12696217 | P8: 0.12936385 | Q8: 0.12273203 | R8: 0.12234224 | S8: 0.11345565 | T8: 0.12114573 | U8: 0.11624961 | V8: 0.12209848 | W8: 0.12076534 | X8: 0.11438439 | Y8: 0.13614674 | Z8: 0.11447968 | AA8: 0.1087746 | AC8: =LOOKUP(9.99E+307,D8:AB8) -> 0.1087746 | AD8: =LOOKUP(9.99E+307,D8:AB8,D$4:AB$4) -> 2023 | AE8: =IFERROR(AVERAGE(W8:AB8),"") -> 0.11891015 | AF8: =MAX(0,$B$2-AC8) -> 0.041225395
A9: Benin | B9: BEN | D9: 0.072511077 | E9: 0.077723508 | F9: 0.061315412 | G9: 0.076892033 | H9: 0.086366129 | I9: 0.074113364 | J9: 0.081737995 | K9: 0.060395412 | L9: 0.051033645 | M9: 0.051059413 | N9: 0.05344604 | O9: 0.044236145 | P9: 0.052463355 | Q9: 0.051338048 | R9: 0.040445924 | S9: 0.032547801 | T9: 0.046273146 | U9: 0.039717438 | V9: 0.040243492 | W9: 0.03124814 | X9: 0.026806235 | Y9: 0.01680898 | Z9: 0.025534043 | AA9: 0.025534043 | AC9: =LOOKUP(9.99E+307,D9:AB9) -> 0.025534043 | AD9: =LOOKUP(9.99E+307,D9:AB9,D$4:AB$4) -> 2023 | AE9: =IFERROR(AVERAGE(W9:AB9),"") -> 0.025186288 | AF9: =MAX(0,$B$2-AC9) -> 0.12446596
A10: Bolivia (Plurinational State of) | B10: BOL | D10: 0.082959833 | E10: 0.081801205 | F10: 0.078159523 | G10: 0.086116819 | H10: 0.078391628 | I10: 0.082987986 | J10: 0.087520018 | K10: 0.085002489 | L10: 0.076468911 | M10: 0.095118818 | N10: 0.097059021 | O10: 0.085434141 | P10: 0.083143749 | Q10: 0.092054644 | R10: 0.089520187 | S10: 0.096743507 | T10: 0.11075057 | U10: 0.11510429 | V10: 0.12721485 | W10: 0.13546631 | X10: 0.15777554 | Y10: 0.169198 | Z10: 0.12820347 | AA10: 0.12029774 | AC10: =LOOKUP(9.99E+307,D10:AB10) -> 0.12029774 | AD10: =LOOKUP(9.99E+307,D10:AB10,D$4:AB$4) -> 2023 | AE10: =IFERROR(AVERAGE(W10:AB10),"") -> 0.14218821 | AF10: =MAX(0,$B$2-AC10) -> 0.029702263
A11: Botswana | B11: BWA | C11: yes | D11: 0.08178297 | E11: 0.08178297 | F11: 0.08178297 | G11: 0.08178297 | H11: 0.08178297 | I11: 0.08178297 | J11: 0.08178297 | K11: 0.08178297 | L11: 0.076448069 | M11: 0.062520623 | N11: 0.08060935 | O11: 0.096322517 | P11: 0.10684479 | Q11: 0.11934482 | R11: 0.10958582 | S11: 0.10415888 | T11: 0.11211295 | U11: 0.14315475 | V11: 0.11542103 | W11: 0.12006065 | X11: 0.11661525 | Y11: 0.14610139 | Z11: 0.14610139 | AA11: 0.14610139 | AC11: =LOOKUP(9.99E+307,D11:AB11) -> 0.14610139 | AD11: =LOOKUP(9.99E+307,D11:AB11,D$4:AB$4) -> 2023 | AE11: =IFERROR(AVERAGE(W11:AB11),"") -> 0.13499601 | AF11: =MAX(0,$B$2-AC11) -> 0.0038986111
A12: Burkina Faso | B12: BFA | D12: 0.048483686 | E12: 0.049421768 | F12: 0.054349313 | G12: 0.055697293 | H12: 0.083909988 | I12: 0.060486403 | J12: 0.065406885 | K12: 0.062706828 | L12: 0.073215261 | M12: 0.07629394 | N12: 0.060323525 | O12: 0.065873938 | P12: 0.046960587 | Q12: 0.063829322 | R12: 0.077736711 | S12: 0.071526418 | T12: 0.11033994 | U12: 0.10235205 | V12: 0.087850237 | W12: 0.09576911 | X12: 0.116475 | Y12: 0.098384151 | Z12: 0.083968487 | AA12: 0.08775362 | AC12: =LOOKUP(9.99E+307,D12:AB12) -> 0.08775362 | AD12: =LOOKUP(9.99E+307,D12:AB12,D$4:AB$4) -> 2023 | AE12: =IFERROR(AVERAGE(W12:AB12),"") -> 0.096470074 | AF12: =MAX(0,$B$2-AC12) -> 0.06224638
A13: Burundi | B13: BDI | C13: yes | D13: 0.0594454 | E13: 0.066626387 | F13: 0.063795781 | G13: 0.037158155 | H13: 0.05803843 | I13: 0.06223104 | J13: 0.064814196 | K13: 0.063231559 | L13: 0.037877474 | M13: 0.054775238 | N13: 0.048606639 | O13: 0.082279139 | P13: 0.071102819 | Q13: 0.044317017 | R13: 0.097924833 | S13: 0.10443518 | T13: 0.099044924 | U13: 0.083575859 | V13: 0.079078622 | W13: 0.079078622 | X13: 0.073328781 | Y13: 0.073328781 | Z13: 0.047289734 | AA13: 0.047289734 | AC13: =LOOKUP(9.99E+307,D13:AB13) -> 0.047289734 | AD13: =LOOKUP(9.99E+307,D13:AB13,D$4:AB$4) -> 2023 | AE13: =IFERROR(AVERAGE(W13:AB13),"") -> 0.06406313 | AF13: =MAX(0,$B$2-AC13) -> 0.10271027
A14: Cambodia | B14: KHM | D14: 0.085917358 | E14: 0.07830318 | F14: 0.082978315 | G14: 0.094304419 | H14: 0.099010906 | I14: 0.098973665 | J14: 0.074111047 | K14: 0.067482748 | L14: 0.066590457 | M14: 0.059676833 | N14: 0.065196424 | O14: 0.062146068 | P14: 0.063306508 | Q14: 0.067916837 | R14: 0.061677031 | S14: 0.069401135 | T14: 0.068482499 | U14: 0.069959145 | V14: 0.075233431 | W14: 0.069910355 | X14: 0.068979673 | Y14: 0.14310493 | Z14: 0.064150882 | AA14: 0.066474256 | AC14: =LOOKUP(9.99E+307,D14:AB14) -> 0.066474256 | AD14: =LOOKUP(9.99E+307,D14:AB14,D$4:AB$4) -> 2023 | AE14: =IFERROR(AVERAGE(W14:AB14),"") -> 0.082524018 | AF14: =MAX(0,$B$2-AC14) -> 0.083525743
A15: Cameroon | B15: CMR | C15: yes | D15: 0.044262691 | E15: 0.053437476 | F15: 0.064329853 | G15: 0.06515377 | H15: 0.052618337 | I15: 0.05247488 | J15: 0.051831469 | K15: 0.042260818 | L15: 0.034610515 | M15: 0.030473874 | N15: 0.026757979 | O15: 0.032104812 | P15: 0.037318034 | Q15: 0.025009561 | R15: 0.029397316 | S15: 0.018129396 | T15: 0.018129396 | U15: 0.0073440903 | V15: 0.019570337 | W15: 0.021798592 | X15: 0.036595056 | Y15: 0.028629239 | Z15: 0.039128006 | AA15: 0.039128006 | AC15: =LOOKUP(9.99E+307,D15:AB15) -> 0.039128006 | AD15: =LOOKUP(9.99E+307,D15:AB15,D$4:AB$4) -> 2023 | AE15: =IFERROR(AVERAGE(W15:AB15),"") -> 0.033055779 | AF15: =MAX(0,$B$2-AC15) -> 0.11087199
A16: Central African Republic | B16: CAF | D16: 0.10021617 | E16: 0.10725758 | F16: 0.086075211 | G16: 0.1254863 | H16: 0.11276064 | I16: 0.064003949 | J16: 0.091779222 | K16: 0.098746586 | L16: 0.05283493 | M16: 0.04575438 | N16: 0.033414733 | O16: 0.029325564 | P16: 0.042233172 | Q16: 0.073451528 | R16: 0.039467859 | S16: 0.032645256 | T16: 0.049471331 | U16: 0.052599773 | V16: 0.039108746 | W16: 0.048423176 | X16: 0.048644204 | Y16: 0.064207349 | Z16: 0.084761972 | AA16: 0.084761972 | AC16: =LOOKUP(9.99E+307,D16:AB16) -> 0.084761972 | AD16: =LOOKUP(9.99E+307,D16:AB16,D$4:AB$4) -> 2023 | AE16: =IFERROR(AVERAGE(W16:AB16),"") -> 0.066159735 | AF16: =MAX(0,$B$2-AC16) -> 0.065238028
A17: Côte d'Ivoire | B17: CIV | D17: 0.045575986 | E17: 0.044565473 | F17: 0.041479588 | G17: 0.040670872 | H17: 0.041451526 | I17: 0.038913488 | J17: 0.038571844 | K17: 0.045792217 | L17: 0.046578813 | M17: 0.058213243 | N17: 0.058067884 | O17: 0.043936925 | P17: 0.046220031 | Q17: 0.045898829 | R17: 0.051112542 | S17: 0.048747077 | T17: 0.048519926 | U17: 0.051502876 | V17: 0.051172767 | W17: 0.056012759 | X17: 0.06538353 | Y17: 0.077738953 | Z17: 0.068222361 | AA17: 0.065832048 | AC17: =LOOKUP(9.99E+307,D17:AB17) -> 0.065832048 | AD17: =LOOKUP(9.99E+307,D17:AB17,D$4:AB$4) -> 2023 | AE17: =IFERROR(AVERAGE(W17:AB17),"") -> 0.06663793 | AF17: =MAX(0,$B$2-AC17) -> 0.084167952
A18: Democratic Republic of the Congo | B18: COD | D18: 0.024989526 | E18: 0.024989526 | F18: 0.024989526 | G18: 0.024989526 | H18: 0.024989526 | I18: 0.024989526 | J18: 0.024989526 | K18: 0.024989526 | L18: 0.024989526 | M18: 0.024989526 | N18: 0.024989526 | O18: 0.025320144 | P18: 0.038775921 | Q18: 0.039094405 | R18: 0.039867942 | S18: 0.041041536 | T18: 0.03807735 | U18: 0.038418849 | V18: 0.041669412 | W18: 0.041286588 | X18: 0.050872474 | Y18: 0.045126462 | Z18: 0.039843409 | AA18: 0.040007191 | AC18: =LOOKUP(9.99E+307,D18:AB18) -> 0.040007191 | AD18: =LOOKUP(9.99E+307,D18:AB18,D$4:AB$4) -> 2023 | AE18: =IFERROR(AVERAGE(W18:AB18),"") -> 0.043427225 | AF18: =MAX(0,$B$2-AC18) -> 0.10999281
A19: Djibouti | B19: DJI | D19: 0.060754762 | E19: 0.059684048 | F19: 0.05495636 | G19: 0.058153071 | H19: 0.053861504 | I19: 0.053278184 | J19: 0.072324629 | K19: 0.065265923 | L19: 0.063488808 | M19: 0.061399169 | N19: 0.069704871 | O19: 0.084744921 | P19: 0.071332936 | Q19: 0.067350478 | R19: 0.060729909 | S19: 0.040695095 | T19: 0.051373649 | U19: 0.048029952 | V19: 0.051697979 | W19: 0.051610975 | X19: 0.041593022 | Y19: 0.033152716 | Z19: 0.050955634 | AA19: 0.048918228 | AC19: =LOOKUP(9.99E+307,D19:AB19) -> 0.048918228 | AD19: =LOOKUP(9.99E+307,D19:AB19,D$4:AB$4) -> 2023 | AE19: =IFERROR(AVERAGE(W19:AB19),"") -> 0.045246115 | AF19: =MAX(0,$B$2-AC19) -> 0.10108177
A20: Dominican Republic | B20: DOM | D20: 0.12137587 | E20: 0.11438853 | F20: 0.10194515 | G20: 0.067342434 | H20: 0.06621449 | I20: 0.089872961 | J20: 0.082697029 | K20: 0.10323029 | L20: 0.11476502 | M20: 0.14433601 | N20: 0.15678899 | O20: 0.170697 | P20: 0.13968768 | Q20: 0.1503564 | R20: 0.14475961 | S20: 0.14195518 | T20: 0.15698118 | U20: 0.15108495 | V20: 0.15667871 | W20: 0.14952268 | X20: 0.14678337 | Y20: 0.18260876 | Z20: 0.15200764 | AA20: 0.15411339 | AC20: =LOOKUP(9.99E+307,D20:AB20) -> 0.15411339 | AD20: =LOOKUP(9.99E+307,D20:AB20,D$4:AB$4) -> 2023 | AE20: =IFERROR(AVERAGE(W20:AB20),"") -> 0.15700717 | AF20: =MAX(0,$B$2-AC20) -> 0
A21: Egypt | B21: EGY | D21: 0.066637259 | E21: 0.066326628 | F21: 0.061411839 | G21: 0.054432034 | H21: 0.052430897 | I21: 0.052435308 | J21: 0.050499468 | K21: 0.050176458 | L21: 0.046992469 | M21: 0.047180848 | N21: 0.043615632 | O21: 0.048270822 | P21: 0.043854094 | Q21: 0.041566329 | R21: 0.041614847 | S21: 0.050579767 | T21: 0.050579767 | U21: 0.054199476 | V21: 0.047215853 | W21: 0.048228469 | X21: 0.051611223 | Y21: 0.067994494 | Z21: 0.067607384 | AA21: 0.069267306 | AC21: =LOOKUP(9.99E+307,D21:AB21) -> 0.069267306 | AD21: =LOOKUP(9.99E+307,D21:AB21,D$4:AB$4) -> 2023 | AE21: =IFERROR(AVERAGE(W21:AB21),"") -> 0.060941775 | AF21: =MAX(0,$B$2-AC21) -> 0.080732694
A22: El Salvador | B22: SLV | D22: 0.18813766 | E22: 0.1768816 | F22: 0.1778229 | G22: 0.17186676 | H22: 0.18680647 | I22: 0.18938656 | J22: 0.19308365 | K22: 0.17984247 | L22: 0.16658825 | M22: 0.15814736 | N22: 0.17085518 | O22: 0.18986029 | P22: 0.162677 | Q22: 0.16716999 | R22: 0.16978041 | S22: 0.17738533 | T22: 0.17652054 | U22: 0.16314199 | V22: 0.16460562 | W22: 0.16971138 | X22: 0.1772464 | Y22: 0.2065045 | Z22: 0.21437885 | AA22: 0.1850918 | AC22: =LOOKUP(9.99E+307,D22:AB22) -> 0.1850918 | AD22: =LOOKUP(9.99E+307,D22:AB22,D$4:AB$4) -> 2023 | AE22: =IFERROR(AVERAGE(W22:AB22),"") -> 0.19058659 | AF22: =MAX(0,$B$2-AC22) -> 0
A23: Eswatini | B23: SWZ | C23: yes | D23: 0.097942724 | E23: 0.092848577 | F23: 0.091893816 | G23: 0.11396682 | H23: 0.097426119 | I23: 0.12612316 | J23: 0.12620983 | K23: 0.12373458 | L23: 0.13342635 | M23: 0.1333174 | N23: 0.13756534 | O23: 0.14277364 | P23: 0.12654774 | Q23: 0.11660085 | R23: 0.085009337 | S23: 0.085870171 | T23: 0.082180529 | U23: 0.099716406 | V23: 0.096976748 | W23: 0.1293036 | X23: 0.10393844 | Y23: 0.12300969 | Z23: 0.10635378 | AA23: 0.10635378 | AC23: =LOOKUP(9.99E+307,D23:AB23) -> 0.10635378 | AD23: =LOOKUP(9.99E+307,D23:AB23,D$4:AB$4) -> 2023 | AE23: =IFERROR(AVERAGE(W23:AB23),"") -> 0.11379186 | AF23: =MAX(0,$B$2-AC23) -> 0.043646221
A24: Ethiopia | B24: ETH | C24: yes | D24: 0.070295844 | E24: 0.089823351 | F24: 0.083686762 | G24: 0.084177933 | H24: 0.05726654 | I24: 0.07550024 | J24: 0.050760446 | K24: 0.064959817 | L24: 0.027417819 | M24: 0.053002 | N24: 0.051071138 | O24: 0.020911443 | P24: 0.064068546 | Q24: 0.061933026 | R24: 0.040883422 | S24: 0.055721168 | T24: 0.050244527 | U24: 0.047883601 | V24: 0.047606049 | W24: 0.047606049 | X24: 0.067922325 | Y24: 0.07096745 | Z24: 0.05676702 | AA24: 0.05676702 | AC24: =LOOKUP(9.99E+307,D24:AB24) -> 0.05676702 | AD24: =LOOKUP(9.99E+307,D24:AB24,D$4:AB$4) -> 2023 | AE24: =IFERROR(AVERAGE(W24:AB24),"") -> 0.060005973 | AF24: =MAX(0,$B$2-AC24) -> 0.09323298
A25: Fiji | B25: FJI | D25: 0.10588044 | E25: 0.079022274 | F25: 0.080357571 | G25: 0.086106272 | H25: 0.092540503 | I25: 0.10359533 | J25: 0.099688578 | K25: 0.10593208 | L25: 0.097818184 | M25: 0.083703699 | N25: 0.087944441 | O25: 0.074741101 | P25: 0.075050917 | Q25: 0.07466826 | R25: 0.071042762 | S25: 0.070441751 | T25: 0.066678991 | U25: 0.077232141 | V25: 0.077550287 | W25: 0.087279425 | X25: 0.086814642 | Y25: 0.10310143 | Z25: 0.10329376 | AA25: 0.09322113 | AC25: =LOOKUP(9.99E+307,D25:AB25) -> 0.09322113 | AD25: =LOOKUP(9.99E+307,D25:AB25,D$4:AB$4) -> 2023 | AE25: =IFERROR(AVERAGE(W25:AB25),"") -> 0.094742077 | AF25: =MAX(0,$B$2-AC25) -> 0.05677887
A26: Gambia | B26: GMB | D26: 0.063089752 | E26: 0.063089752 | F26: 0.063089752 | G26: 0.063089752 | H26: 0.063089752 | I26: 0.063089752 | J26: 0.063089752 | K26: 0.063089752 | L26: 0.063089752 | M26: 0.063089752 | N26: 0.063089752 | O26: 0.063089752 | P26: 0.063089752 | Q26: 0.063089752 | R26: 0.057540197 | S26: 0.050990448 | T26: 0.066577015 | U26: 0.044914708 | V26: 0.055134363 | W26: 0.053790603 | X26: 0.076984744 | Y26: 0.059844098 | Z26: 0.068301234 | AA26: 0.054587293 | AC26: =LOOKUP(9.99E+307,D26:AB26) -> 0.054587293 | AD26: =LOOKUP(9.99E+307,D26:AB26,D$4:AB$4) -> 2023 | AE26: =IFERROR(AVERAGE(W26:AB26),"") -> 0.062701594 | AF26: =MAX(0,$B$2-AC26) -> 0.095412707
A27: Ghana | B27: GHA | D27: 0.061019425 | E27: 0.061019425 | F27: 0.061019425 | G27: 0.077802806 | H27: 0.069171963 | I27: 0.13634508 | J27: 0.11497241 | K27: 0.097394896 | L27: 0.098777552 | M27: 0.12356558 | N27: 0.11915574 | O27: 0.12074167 | P27: 0.089727478 | Q27: 0.086166973 | R27: 0.067195373 | S27: 0.085578575 | T27: 0.065376787 | U27: 0.09274003 | V27: 0.065605044 | W27: 0.087683659 | X27: 0.080232305 | Y27: 0.077142072 | Z27: 0.074095879 | AA27: 0.10051485 | AC27: =LOOKUP(9.99E+307,D27:AB27) -> 0.10051485 | AD27: =LOOKUP(9.99E+307,D27:AB27,D$4:AB$4) -> 2023 | AE27: =IFERROR(AVERAGE(W27:AB27),"") -> 0.083933753 | AF27: =MAX(0,$B$2-AC27) -> 0.049485149
A28: Guatemala | B28: GTM | D28: 0.14082759 | E28: 0.144004 | F28: 0.14791301 | G28: 0.14208874 | H28: 0.15732374 | I28: 0.1420313 | J28: 0.14587105 | K28: 0.1423033 | L28: 0.15491264 | M28: 0.16026173 | N28: 0.14248166 | O28: 0.13759575 | P28: 0.14318863 | Q28: 0.15827068 | R28: 0.164603 | S28: 0.18107498 | T28: 0.18205315 | U28: 0.17212185 | V28: 0.16674454 | W28: 0.17651402 | X28: 0.15862992 | Y28: 0.19772802 | Z28: 0.1733054 | AA28: 0.1775436 | AC28: =LOOKUP(9.99E+307,D28:AB28) -> 0.1775436 | AD28: =LOOKUP(9.99E+307,D28:AB28,D$4:AB$4) -> 2023 | AE28: =IFERROR(AVERAGE(W28:AB28),"") -> 0.17674419 | AF28: =MAX(0,$B$2-AC28) -> 0
A29: Guinea | B29: GIN | D29: 0.023868253 | E29: 0.024863112 | F29: 0.044430332 | G29: 0.028638539 | H29: 0.01861527 | I29: 0.023775997 | J29: 0.018866088 | K29: 0.027802451 | L29: 0.026759889 | M29: 0.016039821 | N29: 0.017697701 | O29: 0.031844747 | P29: 0.02630034 | Q29: 0.026236229 | R29: 0.030479202 | S29: 0.019800686 | T29: 0.041296558 | U29: 0.034782426 | V29: 0.038791776 | W29: 0.061876755 | X29: 0.045516515 | Y29: 0.04510335 | Z29: 0.051174025 | AA29: 0.051174025 | AC29: =LOOKUP(9.99E+307,D29:AB29) -> 0.051174025 | AD29: =LOOKUP(9.99E+307,D29:AB29,D$4:AB$4) -> 2023 | AE29: =IFERROR(AVERAGE(W29:AB29),"") -> 0.050968934 | AF29: =MAX(0,$B$2-AC29) -> 0.098825974
A30: Guyana | B30: GUY | D30: 0.078165045 | E30: 0.067953935 | F30: 0.075090137 | G30: 0.073576484 | H30: 0.073529549 | I30: 0.062754049 | J30: 0.05696579 | K30: 0.066087761 | L30: 0.070215044 | M30: 0.074141932 | N30: 0.076051526 | O30: 0.086206064 | P30: 0.082260752 | Q30: 0.088188906 | R30: 0.094168501 | S30: 0.10840705 | T30: 0.10054208 | U30: 0.10613539 | V30: 0.10711576 | W30: 0.1032425 | X30: 0.13011635 | Y30: 0.12894853 | Z30: 0.085649328 | AA30: 0.073120976 | AC30: =LOOKUP(9.99E+307,D30:AB30) -> 0.073120976 | AD30: =LOOKUP(9.99E+307,D30:AB30,D$4:AB$4) -> 2023 | AE30: =IFERROR(AVERAGE(W30:AB30),"") -> 0.10421554 | AF30: =MAX(0,$B$2-AC30) -> 0.076879024
A31: Haiti | B31: HTI | D31: 0.13943684 | E31: 0.11909204 | F31: 0.073620429 | G31: 0.066061697 | H31: 0.079492502 | I31: 0.066687546 | J31: 0.02994277 | K31: 0.07113584 | L31: 0.074259653 | M31: 0.067716474 | N31: 0.064308343 | O31: 0.029842613 | P31: 0.027839146 | Q31: 0.029984677 | R31: 0.032014871 | S31: 0.044000373 | T31: 0.050224214 | U31: 0.045437198 | V31: 0.046750169 | W31: 0.042496586 | X31: 0.048419085 | Y31: 0.043947258 | Z31: 0.041084309 | AA31: 0.045637708 | AC31: =LOOKUP(9.99E+307,D31:AB31) -> 0.045637708 | AD31: =LOOKUP(9.99E+307,D31:AB31,D$4:AB$4) -> 2023 | AE31: =IFERROR(AVERAGE(W31:AB31),"") -> 0.044316989 | AF31: =MAX(0,$B$2-AC31) -> 0.10436229
A32: Honduras | B32: HND | D32: 0.13678985 | E32: 0.099386835 | F32: 0.094749918 | G32: 0.098826895 | H32: 0.095964127 | I32: 0.1236688 | J32: 0.13421832 | K32: 0.13636523 | L32: 0.12566714 | M32: 0.13993237 | N32: 0.13966723 | O32: 0.15026725 | P32: 0.12835978 | Q32: 0.11812871 | R32: 0.11553196 | S32: 0.11328797 | T32: 0.11295919 | U32: 0.10626307 | V32: 0.10892013 | W32: 0.11167437 | X32: 0.12344063 | Y32: 0.12092145 | Z32: 0.13315739 | AA32: 0.09428587 | AC32: =LOOKUP(9.99E+307,D32:AB32) -> 0.09428587 | AD32: =LOOKUP(9.99E+307,D32:AB32,D$4:AB$4) -> 2023 | AE32: =IFERROR(AVERAGE(W32:AB32),"") -> 0.11669594 | AF32: =MAX(0,$B$2-AC32) -> 0.05571413
A33: India | B33: IND | D33: 0.0305056 | E33: 0.029032168 | F33: 0.027712765 | G33: 0.026768761 | H33: 0.026527741 | I33: 0.029360442 | J33: 0.028859975 | K33: 0.027873428 | L33: 0.027989826 | M33: 0.031219337 | N33: 0.0311163 | O33: 0.033813007 | P33: 0.03438494 | Q33: 0.032388325 | R33: 0.032507055 | S33: 0.0337624 | T33: 0.033933346 | U33: 0.036608045 | V33: 0.036753218 | W33: 0.038472986 | X33: 0.036866047 | Y33: 0.044556293 | Z33: 0.047143903 | AA33: 0.045867086 | AC33: =LOOKUP(9.99E+307,D33:AB33) -> 0.045867086 | AD33: =LOOKUP(9.99E+307,D33:AB33,D$4:AB$4) -> 2023 | AE33: =IFERROR(AVERAGE(W33:AB33),"") -> 0.042581263 | AF33: =MAX(0,$B$2-AC33) -> 0.10413291
A34: Indonesia | B34: IDN | D34: 0.03592418 | E34: 0.039583151 | F34: 0.039828384 | G34: 0.044996161 | H34: 0.042014952 | I34: 0.042081809 | J34: 0.045113745 | K34: 0.054374208 | L34: 0.046298518 | M34: 0.054129438 | N34: 0.039148963 | O34: 0.039625185 | P34: 0.040733542 | Q34: 0.043404298 | R34: 0.054055018 | S34: 0.065787244 | T34: 0.081296864 | U34: 0.082089262 | V34: 0.084031391 | W34: 0.085453539 | X34: 0.10241962 | Y34: 0.12149899 | Z34: 0.080798512 | AA34: 0.08520731 | AC34: =LOOKUP(9.99E+307,D34:AB34) -> 0.08520731 | AD34: =LOOKUP(9.99E+307,D34:AB34,D$4:AB$4) -> 2023 | AE34: =IFERROR(AVERAGE(W34:AB34),"") -> 0.095075594 | AF34: =MAX(0,$B$2-AC34) -> 0.06479269
A35: Iraq | B35: IRQ | G35: 0.03131005 | H35: 0.029806504 | I35: 0.031964197 | J35: 0.030470798 | K35: 0.046332202 | L35: 0.041442576 | M35: 0.04733726 | N35: 0.048027453 | O35: 0.04798624 | P35: 0.023523643 | Q35: 0.023758931 | R35: 0.023695984 | S35: 0.016812644 | T35: 0.059849253 | U35: 0.047749205 | V35: 0.064310226 | W35: 0.059936714 | X35: 0.061605988 | Y35: 0.069839292 | Z35: 0.05841526 | AA35: 0.06184782 | AC35: =LOOKUP(9.99E+307,D35:AB35) -> 0.06184782 | AD35: =LOOKUP(9.99E+307,D35:AB35,D$4:AB$4) -> 2023 | AE35: =IFERROR(AVERAGE(W35:AB35),"") -> 0.062329015 | AF35: =MAX(0,$B$2-AC35) -> 0.08815218
A36: Jamaica | B36: JAM | D36: 0.11841487 | E36: 0.082009611 | F36: 0.086676102 | G36: 0.06137599 | H36: 0.076452746 | I36: 0.074342041 | J36: 0.062574463 | K36: 0.082274962 | L36: 0.083576364 | M36: 0.074510446 | N36: 0.090329323 | O36: 0.095287666 | P36: 0.091577921 | Q36: 0.10769291 | R36: 0.11251961 | S36: 0.1282022 | T36: 0.12683866 | U36: 0.13954786 | V36: 0.13039397 | W36: 0.13320455 | X36: 0.13988929 | Y36: 0.16177647 | Z36: 0.1896324 | AA36: 0.15855964 | AC36: =LOOKUP(9.99E+307,D36:AB36) -> 0.15855964 | AD36: =LOOKUP(9.99E+307,D36:AB36,D$4:AB$4) -> 2023 | AE36: =IFERROR(AVERAGE(W36:AB36),"") -> 0.15661247 | AF36: =MAX(0,$B$2-AC36) -> 0
A37: Jordan | B37: JOR | D37: 0.12689116 | E37: 0.136148 | F37: 0.133821 | G37: 0.1137037 | H37: 0.094005899 | I37: 0.11786743 | J37: 0.11360124 | K37: 0.12519184 | L37: 0.15125435 | M37: 0.17915905 | N37: 0.17020586 | O37: 0.15417559 | P37: 0.13670978 | Q37: 0.13126521 | R37: 0.13064031 | S37: 0.12219738 | T37: 0.1123799 | U37: 0.1109924 | V37: 0.099767199 | W37: 0.10080314 | X37: 0.10765898 | Y37: 0.10347293 | Z37: 0.10466299 | AA37: 0.10501314 | AC37: =LOOKUP(9.99E+307,D37:AB37) -> 0.10501314 | AD37: =LOOKUP(9.99E+307,D37:AB37,D$4:AB$4) -> 2023 | AE37: =IFERROR(AVERAGE(W37:AB37),"") -> 0.10432224 | AF37: =MAX(0,$B$2-AC37) -> 0.044986858
A38: Kenya | B38: KEN | C38: yes | D38: 0.070889826 | E38: 0.070889826 | F38: 0.070889826 | G38: 0.070224299 | H38: 0.069893775 | I38: 0.068923879 | J38: 0.068128095 | K38: 0.070393863 | L38: 0.07170805 | M38: 0.072007761 | N38: 0.072441263 | O38: 0.07981091 | P38: 0.073592792 | Q38: 0.071497207 | R38: 0.078450079 | S38: 0.080744801 | T38: 0.080254345 | U38: 0.067924047 | V38: 0.072187452 | W38: 0.082272358 | X38: 0.089104605 | Y38: 0.092824087 | Z38: 0.086511555 | AA38: 0.086511555 | AC38: =LOOKUP(9.99E+307,D38:AB38) -> 0.086511555 | AD38: =LOOKUP(9.99E+307,D38:AB38,D$4:AB$4) -> 2023 | AE38: =IFERROR(AVERAGE(W38:AB38),"") -> 0.087444832 | AF38: =MAX(0,$B$2-AC38) -> 0.063488445
A39: Kyrgyzstan | B39: KGZ | D39: 0.070640063 | E39: 0.071314993 | F39: 0.075632911 | G39: 0.080725298 | H39: 0.082125959 | I39: 0.13069867 | J39: 0.14458958 | K39: 0.10425051 | L39: 0.10385349 | M39: 0.10696233 | N39: 0.09203639 | O39: 0.098833132 | P39: 0.10400711 | Q39: 0.10346405 | R39: 0.071389055 | S39: 0.071201859 | T39: 0.064158077 | U39: 0.063416133 | V39: 0.073343763 | W39: 0.07093936 | X39: 0.069168787 | Y39: 0.09223444 | Z39: 0.075484381 | AA39: 0.073012633 | AC39: =LOOKUP(9.99E+307,D39:AB39) -> 0.073012633 | AD39: =LOOKUP(9.99E+307,D39:AB39,D$4:AB$4) -> 2023 | AE39: =IFERROR(AVERAGE(W39:AB39),"") -> 0.07616792 | AF39: =MAX(0,$B$2-AC39) -> 0.076987367
A40: Lao People's Democratic Republic | B40: LAO | D40: 0.061991444 | E40: 0.070550289 | F40: 0.061298442 | G40: 0.06834805 | H40: 0.05853271 | I40: 0.059141712 | J40: 0.043634644 | K40: 0.039029949 | L40: 0.031974592 | M40: 0.057037659 | N40: 0.026945555 | O40: 0.018174868 | P40: 0.017665906 | Q40: 0.029400711 | R40: 0.027363534 | S40: 0.033508019 | T40: 0.036279941 | U40: 0.040769591 | V40: 0.041973305 | W40: 0.05163249 | X40: 0.043148298 | Y40: 0.045797653 | Z40: 0.042535505 | AA40: 0.032051065 | AC40: =LOOKUP(9.99E+307,D40:AB40) -> 0.032051065 | AD40: =LOOKUP(9.99E+307,D40:AB40,D$4:AB$4) -> 2023 | AE40: =IFERROR(AVERAGE(W40:AB40),"") -> 0.043033002 | AF40: =MAX(0,$B$2-AC40) -> 0.11794893
A41: Lesotho | B41: LSO | C41: yes | D41: 0.074074073 | E41: 0.087013416 | F41: 0.077236958 | G41: 0.079082699 | H41: 0.082549896 | I41: 0.059969253 | J41: 0.070538449 | K41: 0.096424684 | L41: 0.080810175 | M41: 0.073227449 | N41: 0.071979928 | O41: 0.081988745 | P41: 0.096743116 | Q41: 0.10487746 | R41: 0.11592402 | S41: 0.10860278 | T41: 0.10336077 | U41: 0.11972834 | V41: 0.1077791 | W41: 0.12610546 | X41: 0.089495935 | Y41: 0.081524248 | Z41: 0.12883148 | AA41: 0.11833222 | AC41: =LOOKUP(9.99E+307,D41:AB41) -> 0.11833222 | AD41: =LOOKUP(9.99E+307,D41:AB41,D$4:AB$4) -> 2023 | AE41: =IFERROR(AVERAGE(W41:AB41),"") -> 0.10885787 | AF41: =MAX(0,$B$2-AC41) -> 0.031667776
A42: Liberia | B42: LBR | C42: yes | D42: 0.042549176 | E42: 0.042549176 | F42: 0.042549176 | G42: 0.042549176 | H42: 0.042549176 | I42: 0.042549176 | J42: 0.042549176 | K42: 0.042549176 | L42: 0.042549176 | M42: 0.050466022 | N42: 0.050466022 | O42: 0.050466022 | P42: 0.050466022 | Q42: 0.011572529 | R42: 0.024611893 | S42: 0.032433903 | T42: 0.038970165 | U42: 0.039551458 | V42: 0.051662292 | W42: 0.041983461 | X42: 0.037481868 | Y42: 0.037302012 | Z42: 0.047911715 | AA42: 0.047911715 | AC42: =LOOKUP(9.99E+307,D42:AB42) -> 0.047911715 | AD42: =LOOKUP(9.99E+307,D42:AB42,D$4:AB$4) -> 2023 | AE42: =IFERROR(AVERAGE(W42:AB42),"") -> 0.042518155 | AF42: =MAX(0,$B$2-AC42) -> 0.10208828
A43: Libya | B43: LBY | D43: 0.060398207 | E43: 0.057829866 | F43: 0.077564321 | G43: 0.063085999 | H43: 0.054211988 | I43: 0.057806249 | J43: 0.05275487 | K43: 0.048129821 | L43: 0.037007906 | M43: 0.040890393 | N43: 0.043341274 | O43: 0.064195838 | P43: 0.074125748 | Q43: 0.04971242 | R43: 0.057134776 | S43: 0.075143166 | T43: 0.09908102 | U43: 0.088626747 | V43: 0.092703323 | W43: 0.083604937 | X43: 0.097431974 | Y43: 0.069114699 | Z43: 0.050627132 | AA43: 0.095714731 | AC43: =LOOKUP(9.99E+307,D43:AB43) -> 0.095714731 | AD43: =LOOKUP(9.99E+307,D43:AB43,D$4:AB$4) -> 2023 | AE43: =IFERROR(AVERAGE(W43:AB43),"") -> 0.079298695 | AF43: =MAX(0,$B$2-AC43) -> 0.054285269
A44: Madagascar | B44: MDG | C44: yes | D44: 0.12027845 | E44: 0.11971967 | F44: 0.14041333 | G44: 0.13117822 | H44: 0.10014785 | I44: 0.10540405 | J44: 0.10247689 | K44: 0.11838323 | L44: 0.089767837 | M44: 0.10439493 | N44: 0.15209797 | O44: 0.13936786 | P44: 0.12936996 | Q44: 0.10268065 | R44: 0.1392415 | S44: 0.1527428 | T44: 0.17510868 | U44: 0.15032087 | V44: 0.10429566 | W44: 0.044441509 | X44: 0.042181768 | Y44: 0.053777943 | Z44: 0.055134177 | AA44: 0.055134177 | AC44: =LOOKUP(9.99E+307,D44:AB44) -> 0.055134177 | AD44: =LOOKUP(9.99E+307,D44:AB44,D$4:AB$4) -> 2023 | AE44: =IFERROR(AVERAGE(W44:AB44),"") -> 0.050133915 | AF44: =MAX(0,$B$2-AC44) -> 0.094865823
A45: Malawi | B45: MWI | C45: yes | D45: 0.070426035 | E45: 0.070426035 | F45: 0.070426035 | G45: 0.076335125 | H45: 0.04995151 | I45: 0.060378303 | J45: 0.052927179 | K45: 0.035445971 | L45: 0.066249685 | M45: 0.052324381 | N45: 0.057746429 | O45: 0.067799969 | P45: 0.050962386 | Q45: 0.071556726 | R45: 0.08580905 | S45: 0.0972892 | T45: 0.096779671 | U45: 0.081896133 | V45: 0.087133112 | W45: 0.079386005 | X45: 0.068733201 | Y45: 0.05756381 | Z45: 0.032871101 | AA45: 0.032871101 | AC45: =LOOKUP(9.99E+307,D45:AB45) -> 0.032871101 | AD45: =LOOKUP(9.99E+307,D45:AB45,D$4:AB$4) -> 2023 | AE45: =IFERROR(AVERAGE(W45:AB45),"") -> 0.054285044 | AF45: =MAX(0,$B$2-AC45) -> 0.1171289
A46: Mali | B46: MLI | D46: 0.066688929 | E46: 0.057465625 | F46: 0.055660768 | G46: 0.06785975 | H46: 0.073005457 | I46: 0.064582086 | J46: 0.055458898 | K46: 0.046381097 | L46: 0.03794112 | M46: 0.029260635 | N46: 0.033015409 | O46: 0.029412172 | P46: 0.026625431 | Q46: 0.04128911 | R46: 0.044547329 | S46: 0.043903341 | T46: 0.054306331 | U46: 0.051372628 | V46: 0.056687856 | W46: 0.048350143 | X46: 0.053712625 | Y46: 0.050374312 | Z46: 0.056016617 | AA46: 0.054313564 | AC46: =LOOKUP(9.99E+307,D46:AB46) -> 0.054313564 | AD46: =LOOKUP(9.99E+307,D46:AB46,D$4:AB$4) -> 2023 | AE46: =IFERROR(AVERAGE(W46:AB46),"") -> 0.052553452 | AF46: =MAX(0,$B$2-AC46) -> 0.095686436
A47: Mauritius | B47: MUS | D47: 0.06879271 | E47: 0.07015892 | F47: 0.072455525 | G47: 0.071191735 | H47: 0.079944196 | I47: 0.073627076 | J47: 0.07302484 | K47: 0.068428731 | L47: 0.061225448 | M47: 0.062817368 | N47: 0.082958803 | O47: 0.073622041 | P47: 0.083190432 | Q47: 0.08007184 | R47: 0.10528387 | S47: 0.094584189 | T47: 0.10202269 | U47: 0.10204333 | V47: 0.1020625 | W47: 0.090032053 | X47: 0.089929619 | Y47: 0.10898217 | Z47: 0.086092091 | AA47: 0.082431126 | AC47: =LOOKUP(9.99E+307,D47:AB47) -> 0.082431126 | AD47: =LOOKUP(9.99E+307,D47:AB47,D$4:AB$4) -> 2023 | AE47: =IFERROR(AVERAGE(W47:AB47),"") -> 0.091493412 | AF47: =MAX(0,$B$2-AC47) -> 0.067568874
A48: Mongolia | B48: MNG | D48: 0.13354764 | E48: 0.11051221 | F48: 0.10904332 | G48: 0.088584766 | H48: 0.088026466 | I48: 0.094847002 | J48: 0.095116034 | K48: 0.081638727 | L48: 0.085525045 | M48: 0.087487116 | N48: 0.077428665 | O48: 0.0562043 | P48: 0.06503387 | Q48: 0.071063871 | R48: 0.074850249 | S48: 0.077266617 | T48: 0.064619765 | U48: 0.070231714 | V48: 0.073763604 | W48: 0.068780842 | X48: 0.06920671 | Y48: 0.1173573 | Z48: 0.092518873 | AA48: 0.085609341 | AC48: =LOOKUP(9.99E+307,D48:AB48) -> 0.085609341 | AD48: =LOOKUP(9.99E+307,D48:AB48,D$4:AB$4) -> 2023 | AE48: =IFERROR(AVERAGE(W48:AB48),"") -> 0.086694613 | AF48: =MAX(0,$B$2-AC48) -> 0.064390659
A49: Mozambique | B49: MOZ | C49: yes | D49: 0.063166494 | E49: 0.063166494 | F49: 0.063166494 | G49: 0.063166494 | H49: 0.063166494 | I49: 0.083970003 | J49: 0.056725707 | K49: 0.056029038 | L49: 0.056681066 | M49: 0.049652133 | N49: 0.046724148 | O49: 0.043442202 | P49: 0.043945961 | Q49: 0.047261586 | R49: 0.043172817 | S49: 0.055544376 | T49: 0.059959621 | U49: 0.060745649 | V49: 0.05731606 | W49: 0.065206022 | X49: 0.070641246 | Y49: 0.071126351 | Z49: 0.069572682 | AA49: 0.067625647 | AC49: =LOOKUP(9.99E+307,D49:AB49) -> 0.067625647 | AD49: =LOOKUP(9.99E+307,D49:AB49,D$4:AB$4) -> 2023 | AE49: =IFERROR(AVERAGE(W49:AB49),"") -> 0.06883439 | AF49: =MAX(0,$B$2-AC49) -> 0.082374353
A50: Namibia | B50: NAM | D50: 0.18655966 | E50: 0.18655966 | F50: 0.1985425 | G50: 0.19498096 | H50: 0.20066647 | I50: 0.18941818 | J50: 0.18427374 | K50: 0.20653 | L50: 0.17223892 | M50: 0.13492179 | N50: 0.1458856 | O50: 0.13310722 | P50: 0.13719824 | Q50: 0.13588655 | R50: 0.11966694 | S50: 0.12350636 | T50: 0.13802707 | U50: 0.14021177 | V50: 0.14208248 | W50: 0.14082218 | X50: 0.15705352 | Y50: 0.16603724 | Z50: 0.15882202 | AA50: 0.14992521 | AC50: =LOOKUP(9.99E+307,D50:AB50) -> 0.14992521 | AD50: =LOOKUP(9.99E+307,D50:AB50,D$4:AB$4) -> 2023 | AE50: =IFERROR(AVERAGE(W50:AB50),"") -> 0.15453203 | AF50: =MAX(0,$B$2-AC50) -> 7.47871e-05
A51: Nepal | B51: NPL | D51: 0.042507415 | E51: 0.045276132 | F51: 0.06101347 | G51: 0.055215454 | H51: 0.054828486 | I51: 0.06251473 | J51: 0.075840302 | K51: 0.051758842 | L51: 0.05311276 | M51: 0.046907816 | N51: 0.048050637 | O51: 0.048736372 | P51: 0.046918612 | Q51: 0.048838277 | R51: 0.052682366 | S51: 0.051459527 | T51: 0.053145595 | U51: 0.045078778 | V51: 0.038115978 | W51: 0.040338621 | X51: 0.056691947 | Y51: 0.064860811 | Z51: 0.080067015 | AA51: 0.076604295 | AC51: =LOOKUP(9.99E+307,D51:AB51) -> 0.076604295 | AD51: =LOOKUP(9.99E+307,D51:AB51,D$4:AB$4) -> 2023 | AE51: =IFERROR(AVERAGE(W51:AB51),"") -> 0.063712538 | AF51: =MAX(0,$B$2-AC51) -> 0.073395705
A52: Nicaragua | B52: NIC | D52: 0.12483802 | E52: 0.12790487 | F52: 0.13145116 | G52: 0.12244049 | H52: 0.10920973 | I52: 0.11793169 | J52: 0.13405313 | K52: 0.14678522 | L52: 0.14583184 | M52: 0.16769718 | N52: 0.15736391 | O52: 0.15000977 | P52: 0.1556665 | Q52: 0.1598526 | R52: 0.16911612 | S52: 0.17550644 | T52: 0.17329458 | U52: 0.17787367 | V52: 0.18703579 | W52: 0.18925169 | X52: 0.18296871 | Y52: 0.20180525 | Z52: 0.18097803 | AA52: 0.18289673 | AC52: =LOOKUP(9.99E+307,D52:AB52) -> 0.18289673 | AD52: =LOOKUP(9.99E+307,D52:AB52,D$4:AB$4) -> 2023 | AE52: =IFERROR(AVERAGE(W52:AB52),"") -> 0.18758008 | AF52: =MAX(0,$B$2-AC52) -> 0
A53: Niger | B53: NER | D53: 0.083682642 | E53: 0.083435249 | F53: 0.08355998 | G53: 0.076298943 | H53: 0.073486261 | I53: 0.12347425 | J53: 0.13544619 | K53: 0.086317816 | L53: 0.091883316 | M53: 0.086941404 | N53: 0.09177887 | O53: 0.082997389 | P53: 0.062491212 | Q53: 0.065553365 | R53: 0.054026942 | S53: 0.045863447 | T53: 0.056858091 | U53: 0.096628141 | V53: 0.083492775 | W53: 0.093794031 | X53: 0.10344369 | Y53: 0.087473574 | Z53: 0.071149826 | AA53: 0.061501756 | AC53: =LOOKUP(9.99E+307,D53:AB53) -> 0.061501756 | AD53: =LOOKUP(9.99E+307,D53:AB53,D$4:AB$4) -> 2023 | AE53: =IFERROR(AVERAGE(W53:AB53),"") -> 0.083472575 | AF53: =MAX(0,$B$2-AC53) -> 0.088498244
A54: Nigeria | B54: NGA | C54: yes | D54: 0.023668199 | E54: 0.027795591 | F54: 0.027414963 | G54: 0.040068517 | H54: 0.065542889 | I54: 0.064077029 | J54: 0.073223448 | K54: 0.042935777 | L54: 0.045940452 | M54: 0.036939576 | N54: 0.027029309 | O54: 0.027714133 | P54: 0.036679838 | Q54: 0.034590383 | R54: 0.0333638 | S54: 0.053312464 | T54: 0.048661375 | U54: 0.044423523 | V54: 0.038811214 | W54: 0.037617121 | X54: 0.041839042 | Y54: 0.043079586 | Z54: 0.043079586 | AA54: 0.043079586 | AC54: =LOOKUP(9.99E+307,D54:AB54) -> 0.043079586 | AD54: =LOOKUP(9.99E+307,D54:AB54,D$4:AB$4) -> 2023 | AE54: =IFERROR(AVERAGE(W54:AB54),"") -> 0.041738984 | AF54: =MAX(0,$B$2-AC54) -> 0.10692041
A55: Pakistan | B55: PAK | D55: 0.062598591 | E55: 0.06306684 | F55: 0.062668557 | G55: 0.039821603 | H55: 0.045119391 | I55: 0.039787476 | J55: 0.032093623 | K55: 0.028208477 | L55: 0.022233431 | M55: 0.029631405 | N55: 0.028897414 | O55: 0.025431917 | P55: 0.031706104 | Q55: 0.03249306 | R55: 0.033424859 | S55: 0.038504207 | T55: 0.039600825 | U55: 0.047719541 | V55: 0.048994937 | W55: 0.049508824 | X55: 0.051228571 | Y55: 0.060219402 | Z55: 0.055511613 | AA55: 0.046826034 | AC55: =LOOKUP(9.99E+307,D55:AB55) -> 0.046826034 | AD55: =LOOKUP(9.99E+307,D55:AB55,D$4:AB$4) -> 2023 | AE55: =IFERROR(AVERAGE(W55:AB55),"") -> 0.052658889 | AF55: =MAX(0,$B$2-AC55) -> 0.10317397
A56: Panama | B56: PAN | D56: 0.19781748 | E56: 0.18728844 | F56: 0.18844736 | G56: 0.17181688 | H56: 0.192215 | I56: 0.16471035 | J56: 0.18558369 | K56: 0.22247358 | L56: 0.20069345 | M56: 0.20486574 | N56: 0.19226313 | O56: 0.1798856 | P56: 0.17106688 | Q56: 0.17400517 | R56: 0.18434895 | S56: 0.1971187 | T56: 0.20341421 | U56: 0.20797066 | V56: 0.20192026 | W56: 0.22348572 | X56: 0.20134941 | Y56: 0.21347996 | Z56: 0.22304193 | AA56: 0.1984911 | AC56: =LOOKUP(9.99E+307,D56:AB56) -> 0.1984911 | AD56: =LOOKUP(9.99E+307,D56:AB56,D$4:AB$4) -> 2023 | AE56: =IFERROR(AVERAGE(W56:AB56),"") -> 0.21196962 | AF56: =MAX(0,$B$2-AC56) -> 0
A57: Papua New Guinea | B57: PNG | D57: 0.083166676 | E57: 0.07733428 | F57: 0.084760389 | G57: 0.076346121 | H57: 0.087462501 | I57: 0.078258791 | J57: 0.083770504 | K57: 0.09068861 | L57: 0.076645341 | M57: 0.063151846 | N57: 0.070693121 | O57: 0.076042318 | P57: 0.081286125 | Q57: 0.071877017 | R57: 0.074700818 | S57: 0.060310936 | T57: 0.080409183 | U57: 0.091549807 | V57: 0.079493136 | W57: 0.063698492 | X57: 0.067297945 | Y57: 0.053251205 | Z57: 0.069878235 | AA57: 0.094504452 | AC57: =LOOKUP(9.99E+307,D57:AB57) -> 0.094504452 | AD57: =LOOKUP(9.99E+307,D57:AB57,D$4:AB$4) -> 2023 | AE57: =IFERROR(AVERAGE(W57:AB57),"") -> 0.069726066 | AF57: =MAX(0,$B$2-AC57) -> 0.055495548
A58: Philippines | B58: PHL | D58: 0.065183859 | E58: 0.055015583 | F58: 0.047528081 | G58: 0.054588623 | H58: 0.056192007 | I58: 0.066097803 | J58: 0.066309614 | K58: 0.064638405 | L58: 0.065101442 | M58: 0.066447358 | N58: 0.071827903 | O58: 0.061674323 | P58: 0.062014275 | Q58: 0.064671025 | R58: 0.075054045 | S58: 0.08256876 | T58: 0.077519669 | U58: 0.076203294 | V58: 0.073461299 | W58: 0.077887635 | X58: 0.090017347 | Y58: 0.09820035 | Z58: 0.089760952 | AA58: 0.087699451 | AC58: =LOOKUP(9.99E+307,D58:AB58) -> 0.087699451 | AD58: =LOOKUP(9.99E+307,D58:AB58,D$4:AB$4) -> 2023 | AE58: =IFERROR(AVERAGE(W58:AB58),"") -> 0.088713147 | AF58: =MAX(0,$B$2-AC58) -> 0.062300549
A59: Republic of Moldova | B59: MDA | D59: 0.085279446 | E59: 0.097118463 | F59: 0.11537353 | G59: 0.095935364 | H59: 0.15250319 | I59: 0.1357666 | J59: 0.12890509 | K59: 0.13181109 | L59: 0.12721593 | M59: 0.12875923 | N59: 0.1362692 | O59: 0.1303699 | P59: 0.1317397 | Q59: 0.12499175 | R59: 0.12757282 | S59: 0.12214735 | T59: 0.12208034 | U59: 0.11645921 | V59: 0.12025702 | W59: 0.12120483 | X59: 0.12376142 | Y59: 0.14621915 | Z59: 0.12347353 | AA59: 0.12068118 | AC59: =LOOKUP(9.99E+307,D59:AB59) -> 0.12068118 | AD59: =LOOKUP(9.99E+307,D59:AB59,D$4:AB$4) -> 2023 | AE59: =IFERROR(AVERAGE(W59:AB59),"") -> 0.12706802 | AF59: =MAX(0,$B$2-AC59) -> 0.029318819
A60: Rwanda | B60: RWA | C60: yes | D60: 0.035436115 | E60: 0.036613052 | F60: 0.037057266 | G60: 0.12454895 | H60: 0.10788955 | I60: 0.080927191 | J60: 0.072027006 | K60: 0.077929072 | L60: 0.080763216 | M60: 0.084302445 | N60: 0.085564241 | O60: 0.089006796 | P60: 0.08363018 | Q60: 0.083041182 | R60: 0.079819064 | S60: 0.079149456 | T60: 0.062302461 | U60: 0.062302461 | V60: 0.062302461 | W60: 0.062761536 | X60: 0.063912997 | Y60: 0.083519449 | Z60: 0.082025328 | AA60: 0.089230986 | AC60: =LOOKUP(9.99E+307,D60:AB60) -> 0.089230986 | AD60: =LOOKUP(9.99E+307,D60:AB60,D$4:AB$4) -> 2023 | AE60: =IFERROR(AVERAGE(W60:AB60),"") -> 0.076290059 | AF60: =MAX(0,$B$2-AC60) -> 0.060769014
A61: Sao Tome and Principe | B61: STP | D61: 0.32571323 | E61: 0.07026926 | F61: 0.085408087 | G61: 0.11678334 | H61: 0.085635901 | I61: 0.11518961 | J61: 0.01691655 | K61: 0.042763843 | L61: 0.040179758 | M61: 0.032723732 | N61: 0.041002846 | O61: 0.043093619 | P61: 0.045668697 | Q61: 0.084400892 | R61: 0.077758141 | S61: 0.04936841 | T61: 0.080021572 | U61: 0.10762633 | V61: 0.093856688 | W61: 0.097778044 | X61: 0.12803995 | Y61: 0.13142622 | Z61: 0.083445749 | AA61: 0.087735281 | AC61: =LOOKUP(9.99E+307,D61:AB61) -> 0.087735281 | AD61: =LOOKUP(9.99E+307,D61:AB61,D$4:AB$4) -> 2023 | AE61: =IFERROR(AVERAGE(W61:AB61),"") -> 0.10568505 | AF61: =MAX(0,$B$2-AC61) -> 0.062264719
A62: Senegal | B62: SEN | D62: 0.089599495 | E62: 0.090105324 | F62: 0.086363592 | G62: 0.09047883 | H62: 0.089669704 | I62: 0.085441351 | J62: 0.082667284 | K62: 0.059480786 | L62: 0.06624815 | M62: 0.06660274 | N62: 0.053533254 | O62: 0.056281166 | P62: 0.05307559 | Q62: 0.05299932 | R62: 0.046755114 | S62: 0.046987033 | T62: 0.04456933 | U62: 0.044990048 | V62: 0.049615188 | W62: 0.035002797 | X62: 0.058475819 | Y62: 0.03877243 | Z62: 0.033444905 | AA62: 0.035745463 | AC62: =LOOKUP(9.99E+307,D62:AB62) -> 0.035745463 | AD62: =LOOKUP(9.99E+307,D62:AB62,D$4:AB$4) -> 2023 | AE62: =IFERROR(AVERAGE(W62:AB62),"") -> 0.040288283 | AF62: =MAX(0,$B$2-AC62) -> 0.11425454
A63: Sierra Leone | B63: SLE | C63: yes | D63: 0.054509754 | E63: 0.054509754 | F63: 0.054509754 | G63: 0.054509754 | H63: 0.054509754 | I63: 0.054509754 | J63: 0.054509754 | K63: 0.054509754 | L63: 0.044130363 | M63: 0.056055417 | N63: 0.065142417 | O63: 0.053543301 | P63: 0.04753211 | Q63: 0.051501288 | R63: 0.075798845 | S63: 0.062052178 | T63: 0.044451132 | U63: 0.03632112 | V63: 0.035992189 | W63: 0.05841722 | X63: 0.053023968 | Y63: 0.056669006 | Z63: 0.044684482 | AA63: 0.044684482 | AC63: =LOOKUP(9.99E+307,D63:AB63) -> 0.044684482 | AD63: =LOOKUP(9.99E+307,D63:AB63,D$4:AB$4) -> 2023 | AE63: =IFERROR(AVERAGE(W63:AB63),"") -> 0.051495831 | AF63: =MAX(0,$B$2-AC63) -> 0.10531552
A64: Somalia | B64: SOM | Q64: 0.057628288 | R64: 0.041115642 | S64: 0.052517319 | T64: 0.057761183 | U64: 0.047264438 | V64: 0.040835619 | W64: 0.041364956 | X64: 0.042128167 | Y64: 0.071242857 | Z64: 0.04420074 | AA64: 0.0790447 | AC64: =LOOKUP(9.99E+307,D64:AB64) -> 0.0790447 | AD64: =LOOKUP(9.99E+307,D64:AB64,D$4:AB$4) -> 2023 | AE64: =IFERROR(AVERAGE(W64:AB64),"") -> 0.055596284 | AF64: =MAX(0,$B$2-AC64) -> 0.0709553
A65: South Africa | B65: ZAF | D65: 0.11855308 | E65: 0.10622846 | F65: 0.10379812 | G65: 0.12338238 | H65: 0.12029251 | I65: 0.10918806 | J65: 0.13095092 | K65: 0.13509318 | L65: 0.13014714 | M65: 0.13369973 | N65: 0.14115259 | O65: 0.14674422 | P65: 0.14467314 | Q65: 0.14337916 | R65: 0.14916127 | S65: 0.15237736 | T65: 0.1528984 | U65: 0.1528984 | V65: 0.1528984 | W65: 0.1528984 | X65: 0.16885675 | Y65: 0.16885675 | Z65: 0.16885675 | AA65: 0.16885675 | AC65: =LOOKUP(9.99E+307,D65:AB65) -> 0.16885675 | AD65: =LOOKUP(9.99E+307,D65:AB65,D$4:AB$4) -> 2023 | AE65: =IFERROR(AVERAGE(W65:AB65),"") -> 0.16566508 | AF65: =MAX(0,$B$2-AC65) -> 0
A66: South Sudan | B66: SSD | U66: 0.021062052 | V66: 0.021062052 | W66: 0.021062052 | X66: 0.021062052 | Y66: 0.021062052 | Z66: 0.021062052 | AA66: 0.021358619 | AC66: =LOOKUP(9.99E+307,D66:AB66) -> 0.021358619 | AD66: =LOOKUP(9.99E+307,D66:AB66,D$4:AB$4) -> 2023 | AE66: =IFERROR(AVERAGE(W66:AB66),"") -> 0.021121365 | AF66: =MAX(0,$B$2-AC66) -> 0.12864138
A67: Tajikistan | B67: TJK | D67: 0.048929663 | E67: 0.050574713 | F67: 0.0421875 | G67: 0.040352812 | H67: 0.044186048 | I67: 0.043151517 | J67: 0.043291769 | K67: 0.05300231 | L67: 0.067886295 | M67: 0.045913758 | N67: 0.045633802 | O67: 0.053759761 | P67: 0.065030193 | Q67: 0.068673086 | R67: 0.075624552 | S67: 0.064093766 | T67: 0.060942478 | U67: 0.058856773 | V67: 0.061445789 | W67: 0.065859361 | X67: 0.073759446 | Y67: 0.070209379 | Z67: 0.063917909 | AA67: 0.061385097 | AC67: =LOOKUP(9.99E+307,D67:AB67) -> 0.061385097 | AD67: =LOOKUP(9.99E+307,D67:AB67,D$4:AB$4) -> 2023 | AE67: =IFERROR(AVERAGE(W67:AB67),"") -> 0.067026238 | AF67: =MAX(0,$B$2-AC67) -> 0.088614903
A68: Timor-Leste | B68: TLS | G68: 0.016249464 | H68: 0.022540574 | I68: 0.036345334 | J68: 0.040001564 | K68: 0.012737614 | L68: 0.027769404 | M68: 0.026631961 | N68: 0.027104998 | O68: 0.026768098 | P68: 0.032064052 | Q68: 0.046244412 | R68: 0.037185555 | S68: 0.045054522 | T68: 0.030717392 | U68: 0.051460443 | V68: 0.046211515 | W68: 0.041934099 | X68: 0.065902076 | Y68: 0.069707313 | Z68: 0.089028816 | AA68: 0.091623793 | AC68: =LOOKUP(9.99E+307,D68:AB68) -> 0.091623793 | AD68: =LOOKUP(9.99E+307,D68:AB68,D$4:AB$4) -> 2023 | AE68: =IFERROR(AVERAGE(W68:AB68),"") -> 0.071639219 | AF68: =MAX(0,$B$2-AC68) -> 0.058376207
A69: Togo | B69: TGO | D69: 0.024448416 | E69: 0.029947822 | F69: 0.040513344 | G69: 0.042420878 | H69: 0.042055535 | I69: 0.038008156 | J69: 0.038319192 | K69: 0.043449535 | L69: 0.048437166 | M69: 0.047768583 | N69: 0.074458599 | O69: 0.056692529 | P69: 0.061090674 | Q69: 0.046896563 | R69: 0.045581021 | S69: 0.040382533 | T69: 0.04258637 | U69: 0.064504061 | V69: 0.054890213 | W69: 0.053817401 | X69: 0.038512247 | Y69: 0.025608845 | Z69: 0.025608845 | AA69: 0.025608845 | AC69: =LOOKUP(9.99E+307,D69:AB69) -> 0.025608845 | AD69: =LOOKUP(9.99E+307,D69:AB69,D$4:AB$4) -> 2023 | AE69: =IFERROR(AVERAGE(W69:AB69),"") -> 0.033831236 | AF69: =MAX(0,$B$2-AC69) -> 0.12439116
A70: Uganda | B70: UGA | C70: yes | D70: 0.083307648 | E70: 0.083307648 | F70: 0.087481051 | G70: 0.089497604 | H70: 0.087673616 | I70: 0.07135263 | J70: 0.071609378 | K70: 0.07792912 | L70: 0.072511458 | M70: 0.070329056 | N70: 0.071137476 | O70: 0.068970098 | P70: 0.070504432 | Q70: 0.073242755 | R70: 0.070089807 | S70: 0.050845342 | T70: 0.051781931 | U70: 0.039216382 | V70: 0.041681151 | W70: 0.0313883 | X70: 0.055540357 | Y70: 0.0535358 | Z70: 0.048603988 | AA70: 0.048603988 | AC70: =LOOKUP(9.99E+307,D70:AB70) -> 0.048603988 | AD70: =LOOKUP(9.99E+307,D70:AB70,D$4:AB$4) -> 2023 | AE70: =IFERROR(AVERAGE(W70:AB70),"") -> 0.047534486 | AF70: =MAX(0,$B$2-AC70) -> 0.10139601
A71: United Republic of Tanzania | B71: TZA | D71: 0.060520005 | E71: 0.087993107 | F71: 0.097884245 | G71: 0.097085171 | H71: 0.11553483 | I71: 0.12619913 | J71: 0.13508828 | K71: 0.10886572 | L71: 0.124855 | M71: 0.075839615 | N71: 0.073213797 | O71: 0.067621193 | P71: 0.060057139 | Q71: 0.063068624 | R71: 0.069378467 | S71: 0.073306294 | T71: 0.095214338 | U71: 0.095214338 | V71: 0.09414732 | W71: 0.094380102 | X71: 0.049400015 | Y71: 0.0513517 | Z71: 0.0513517 | AA71: 0.0513517 | AC71: =LOOKUP(9.99E+307,D71:AB71) -> 0.0513517 | AD71: =LOOKUP(9.99E+307,D71:AB71,D$4:AB$4) -> 2023 | AE71: =IFERROR(AVERAGE(W71:AB71),"") -> 0.059567043 | AF71: =MAX(0,$B$2-AC71) -> 0.0986483
A72: Venezuela (Bolivarian Republic of) | B72: VEN | V72: 0.01697551 | W72: 0.016100203 | X72: 0.058499622 | Y72: 0.044399552 | Z72: 0.058742647 | AA72: 0.036269651 | AC72: =LOOKUP(9.99E+307,D72:AB72) -> 0.036269651 | AD72: =LOOKUP(9.99E+307,D72:AB72,D$4:AB$4) -> 2023 | AE72: =IFERROR(AVERAGE(W72:AB72),"") -> 0.042802335 | AF72: =MAX(0,$B$2-AC72) -> 0.11373035
A73: Viet Nam | B73: VNM | D73: 0.094822588 | E73: 0.082020779 | F73: 0.086199598 | G73: 0.071603308 | H73: 0.086892519 | I73: 0.08669239 | J73: 0.087669868 | K73: 0.079369111 | L73: 0.081204872 | M73: 0.068530107 | N73: 0.086057291 | O73: 0.091072073 | P73: 0.095150404 | Q73: 0.081612139 | R73: 0.091232414 | S73: 0.084938517 | T73: 0.095965862 | U73: 0.10093239 | V73: 0.10217708 | W73: 0.10198591 | X73: 0.084261189 | Y73: 0.09740695 | Z73: 0.10829385 | AA73: 0.10451711 | AC73: =LOOKUP(9.99E+307,D73:AB73) -> 0.10451711 | AD73: =LOOKUP(9.99E+307,D73:AB73,D$4:AB$4) -> 2023 | AE73: =IFERROR(AVERAGE(W73:AB73),"") -> 0.099293001 | AF73: =MAX(0,$B$2-AC73) -> 0.045482893
A74: Zambia | B74: ZMB | D74: 0.068847504 | E74: 0.068847504 | F74: 0.068847504 | G74: 0.053227615 | H74: 0.056522694 | I74: 0.05537641 | J74: 0.067470403 | K74: 0.074681029 | L74: 0.081471176 | M74: 0.093657865 | N74: 0.086339178 | O74: 0.080581131 | P74: 0.070576959 | Q74: 0.054523168 | R74: 0.077846622 | S74: 0.075614514 | T74: 0.071645694 | U74: 0.10052179 | V74: 0.075291042 | W74: 0.075730639 | X74: 0.10560055 | Y74: 0.092548494 | Z74: 0.088887758 | AA74: 0.088887758 | AC74: =LOOKUP(9.99E+307,D74:AB74) -> 0.088887758 | AD74: =LOOKUP(9.99E+307,D74:AB74,D$4:AB$4) -> 2023 | AE74: =IFERROR(AVERAGE(W74:AB74),"") -> 0.090331039 | AF74: =MAX(0,$B$2-AC74) -> 0.061112242
A75: Zimbabwe | B75: ZWE | N75: 0.13766672 | O75: 0.12717875 | P75: 0.13991549 | Q75: 0.080723658 | R75: 0.1092625 | S75: 0.06205451 | T75: 0.054890156 | U75: 0.069794187 | V75: 0.079763265 | W75: 0.032664912 | X75: 0.047405839 | Y75: 0.047405839 | Z75: 0.047405839 | AA75: 0.047405839 | AC75: =LOOKUP(9.99E+307,D75:AB75) -> 0.047405839 | AD75: =LOOKUP(9.99E+307,D75:AB75,D$4:AB$4) -> 2023 | AE75: =IFERROR(AVERAGE(W75:AB75),"") -> 0.044457654 | AF75: =MAX(0,$B$2-AC75) -> 0.10259416

Sheet All GHED Countries
A1: Government health spending as % of government spending, all WHO GHED countries (195), 2000-2023
A2: Abuja target | B2: ='Model Countries'!$B$2 -> 0.15 | C2: Grey cell = same value as the year before (likely carried forward by WHO, not a new figure). Blank = no WHO estimate. See Notes.
A4: Country | B4: ISO3 | C4: MOU 15 | D4: 2000 | E4: 2001 | F4: 2002 | G4: 2003 | H4: 2004 | I4: 2005 | J4: 2006 | K4: 2007 | L4: 2008 | M4: 2009 | N4: 2010 | O4: 2011 | P4: 2012 | Q4: 2013 | R4: 2014 | S4: 2015 | T4: 2016 | U4: 2017 | V4: 2018 | W4: 2019 | X4: 2020 | Y4: 2021 | Z4: 2022 | AA4: 2023 | AB4: 2024 | AC4: Latest | AD4: Latest Year | AE4: Avg 2019-2023 | AF4: Room to Abuja target
A5: Afghanistan | B5: AFG | F5: 0.01212456 | G5: 0.054576788 | H5: 0.036029682 | I5: 0.033812206 | J5: 0.027260592 | K5: 0.026107819 | L5: 0.030039206 | M5: 0.025147831 | N5: 0.022567358 | O5: 0.021881192 | P5: 0.013700027 | Q5: 0.017750696 | R5: 0.01860674 | S5: 0.02014406 | T5: 0.021411054 | U5: 0.023191156 | V5: 0.019090469 | W5: 0.017752601 | X5: 0.04246028 | Y5: 0.039610109 | Z5: 0.011260573 | AA5: 0.014601837 | AC5: =LOOKUP(9.99E+307,D5:AB5) -> 0.014601837 | AD5: =LOOKUP(9.99E+307,D5:AB5,D$4:AB$4) -> 2023 | AE5: =IFERROR(AVERAGE(W5:AB5),"") -> 0.02513708 | AF5: =MAX(0,$B$2-AC5) -> 0.13539816
A6: Albania | B6: ALB | D6: 0.08173727 | E6: 0.084236832 | F6: 0.082089748 | G6: 0.089971762 | H6: 0.09354475 | I6: 0.093009472 | J6: 0.090339222 | K6: 0.093771095 | L6: 0.072510648 | M6: 0.07217092 | N6: 0.080945129 | O6: 0.082909117 | P6: 0.086973457 | Q6: 0.088300629 | R6: 0.081742783 | S6: 0.08803566 | T6: 0.098886671 | U6: 0.095141821 | V6: 0.09886014 | W6: 0.10046225 | X6: 0.091851702 | Y6: 0.091411314 | Z6: 0.1230901 | AA6: 0.12282823 | AC6: =LOOKUP(9.99E+307,D6:AB6) -> 0.12282823 | AD6: =LOOKUP(9.99E+307,D6:AB6,D$4:AB$4) -> 2023 | AE6: =IFERROR(AVERAGE(W6:AB6),"") -> 0.10592872 | AF6: =MAX(0,$B$2-AC6) -> 0.027171774
A7: Algeria | B7: DZA | D7: 0.087792378 | E7: 0.092666121 | F7: 0.079734383 | G7: 0.09437788 | H7: 0.086691694 | I7: 0.077615991 | J7: 0.0784513 | K7: 0.076307364 | L7: 0.076872091 | M7: 0.086446848 | N7: 0.091878758 | O7: 0.090342512 | P7: 0.10061447 | Q7: 0.11701066 | R7: 0.11418038 | S7: 0.10604811 | T7: 0.10605941 | U7: 0.1060604 | V7: 0.10606169 | W7: 0.088303614 | X7: 0.088303061 | Y7: 0.088285294 | Z7: 0.05251564 | AA7: 0.061683345 | AC7: =LOOKUP(9.99E+307,D7:AB7) -> 0.061683345 | AD7: =LOOKUP(9.99E+307,D7:AB7,D$4:AB$4) -> 2023 | AE7: =IFERROR(AVERAGE(W7:AB7),"") -> 0.075818191 | AF7: =MAX(0,$B$2-AC7) -> 0.088316655
A8: Andorra | B8: AND | D8: 0.30418488 | E8: 0.18425966 | F8: 0.30313049 | G8: 0.30215126 | H8: 0.2770529 | I8: 0.18778881 | J8: 0.23288269 | K8: 0.21894827 | L8: 0.24805691 | M8: 0.16870777 | N8: 0.24528812 | O8: 0.2376627 | P8: 0.15370749 | Q8: 0.11189083 | R8: 0.2167169 | S8: 0.15752106 | T8: 0.11595967 | U8: 0.14120295 | V8: 0.14528497 | W8: 0.14574258 | X8: 0.1505597 | Y8: 0.15790538 | Z8: 0.15870918 | AA8: 0.15194997 | AC8: =LOOKUP(9.99E+307,D8:AB8) -> 0.15194997 | AD8: =LOOKUP(9.99E+307,D8:AB8,D$4:AB$4) -> 2023 | AE8: =IFERROR(AVERAGE(W8:AB8),"") -> 0.15297336 | AF8: =MAX(0,$B$2-AC8) -> 0
A9: Angola | B9: AGO | D9: 0.027385826 | E9: 0.059682546 | F9: 0.041912308 | G9: 0.04260468 | H9: 0.056592388 | I9: 0.048206377 | J9: 0.047187376 | K9: 0.045162711 | L9: 0.040603714 | M9: 0.057778893 | N9: 0.04249568 | O9: 0.045805688 | P9: 0.042015133 | Q9: 0.045754008 | R9: 0.036156802 | S9: 0.045626254 | T9: 0.054326968 | U9: 0.053643193 | V9: 0.053643193 | W9: 0.055068841 | X9: 0.073050218 | Y9: 0.087773657 | Z9: 0.06699635 | AA9: 0.058957567 | AC9: =LOOKUP(9.99E+307,D9:AB9) -> 0.058957567 | AD9: =LOOKUP(9.99E+307,D9:AB9,D$4:AB$4) -> 2023 | AE9: =IFERROR(AVERAGE(W9:AB9),"") -> 0.068369327 | AF9: =MAX(0,$B$2-AC9) -> 0.091042433
A10: Antigua and Barbuda | B10: ATG | D10: 0.11862532 | E10: 0.12117159 | F10: 0.10650884 | G10: 0.12448911 | H10: 0.12126567 | I10: 0.11530172 | J10: 0.08368083 | K10: 0.084518461 | L10: 0.080810614 | M10: 0.063313918 | N10: 0.13896391 | O10: 0.12989786 | P10: 0.14632363 | Q10: 0.13300732 | R10: 0.1510594 | S10: 0.11817538 | T10: 0.11606883 | U10: 0.11607389 | V10: 0.13074534 | W10: 0.11299994 | X10: 0.13783793 | Y10: 0.13094046 | Z10: 0.13773719 | AA10: 0.12279952 | AC10: =LOOKUP(9.99E+307,D10:AB10) -> 0.12279952 | AD10: =LOOKUP(9.99E+307,D10:AB10,D$4:AB$4) -> 2023 | AE10: =IFERROR(AVERAGE(W10:AB10),"") -> 0.12846301 | AF10: =MAX(0,$B$2-AC10) -> 0.027200479
A11: Argentina | B11: ARG | D11: 0.17819662 | E11: 0.16936325 | F11: 0.17747658 | G11: 0.1708437 | H11: 0.1493299 | I11: 0.16097414 | J11: 0.15193391 | K11: 0.14366702 | L11: 0.14556316 | M11: 0.16644169 | N11: 0.16697248 | O11: 0.16387676 | P11: 0.16684788 | Q11: 0.16740732 | R11: 0.1648708 | S11: 0.16445961 | T11: 0.15841621 | U11: 0.16251633 | V11: 0.15689699 | W11: 0.16311375 | X11: 0.16456453 | Y11: 0.16756962 | Z11: 0.15795045 | AA11: 0.16347298 | AC11: =LOOKUP(9.99E+307,D11:AB11) -> 0.16347298 | AD11: =LOOKUP(9.99E+307,D11:AB11,D$4:AB$4) -> 2023 | AE11: =IFERROR(AVERAGE(W11:AB11),"") -> 0.16333426 | AF11: =MAX(0,$B$2-AC11) -> 0
A12: Armenia | B12: ARM | D12: 0.038698921 | E12: 0.056626477 | F12: 0.053255291 | G12: 0.053752279 | H12: 0.06275475 | I12: 0.074400082 | J12: 0.07931859 | K12: 0.071985488 | L12: 0.06692462 | M12: 0.063449011 | N12: 0.064360886 | O12: 0.067010198 | P12: 0.070407543 | Q12: 0.0578088 | R12: 0.062752604 | S12: 0.06115303 | T12: 0.060535474 | U12: 0.052734718 | V12: 0.051338592 | W12: 0.056688504 | X12: 0.076896224 | Y12: 0.076349659 | Z12: 0.065027537 | AA12: 0.054564252 | AC12: =LOOKUP(9.99E+307,D12:AB12) -> 0.054564252 | AD12: =LOOKUP(9.99E+307,D12:AB12,D$4:AB$4) -> 2023 | AE12: =IFERROR(AVERAGE(W12:AB12),"") -> 0.065905235 | AF12: =MAX(0,$B$2-AC12) -> 0.095435748
A13: Australia | B13: AUS | D13: 0.14601329 | E13: 0.14708553 | F13: 0.15514163 | G13: 0.15481012 | H13: 0.15947051 | I13: 0.15902768 | J13: 0.15939968 | K13: 0.16490223 | L13: 0.15612955 | M13: 0.1588237 | N13: 0.16114603 | O13: 0.16322504 | P13: 0.16186937 | Q13: 0.15400936 | R13: 0.17636618 | S13: 0.18289017 | T13: 0.18542912 | U13: 0.18582108 | V13: 0.1852639 | W13: 0.17126518 | X13: 0.17063093 | Y13: 0.19292011 | Z13: 0.20248672 | AA13: 0.210086 | AC13: =LOOKUP(9.99E+307,D13:AB13) -> 0.210086 | AD13: =LOOKUP(9.99E+307,D13:AB13,D$4:AB$4) -> 2023 | AE13: =IFERROR(AVERAGE(W13:AB13),"") -> 0.18947779 | AF13: =MAX(0,$B$2-AC13) -> 0
A14: Austria | B14: AUT | D14: 0.13347214 | E14: 0.13241023 | F14: 0.13480156 | G14: 0.1356053 | H14: 0.12996217 | I14: 0.13645687 | J14: 0.13770193 | K14: 0.14055029 | L14: 0.14361295 | M14: 0.13751563 | N14: 0.13962966 | O14: 0.14304615 | P14: 0.1447297 | Q14: 0.14292957 | R14: 0.14502279 | S14: 0.14787659 | T14: 0.14904736 | U14: 0.15486373 | V14: 0.15766131 | W14: 0.16071058 | X14: 0.15197711 | Y14: 0.16888676 | Z14: 0.1632947 | AA14: 0.16192835 | AC14: =LOOKUP(9.99E+307,D14:AB14) -> 0.16192835 | AD14: =LOOKUP(9.99E+307,D14:AB14,D$4:AB$4) -> 2023 | AE14: =IFERROR(AVERAGE(W14:AB14),"") -> 0.1613595 | AF14: =MAX(0,$B$2-AC14) -> 0
A15: Azerbaijan | B15: AZE | D15: 0.047502904 | E15: 0.047982063 | F15: 0.031931574 | G15: 0.035723515 | H15: 0.035575993 | I15: 0.039594917 | J15: 0.0342998 | K15: 0.034903398 | L15: 0.027519121 | M15: 0.032848394 | N15: 0.031712611 | O15: 0.028160138 | P15: 0.030453246 | Q15: 0.028222861 | R15: 0.031070068 | S15: 0.033728263 | T15: 0.03289871 | U15: 0.028237727 | V15: 0.026780353 | W15: 0.032879271 | X15: 0.057977181 | Y15: 0.046051784 | Z15: 0.036410747 | AA15: 0.042580843 | AC15: =LOOKUP(9.99E+307,D15:AB15) -> 0.042580843 | AD15: =LOOKUP(9.99E+307,D15:AB15,D$4:AB$4) -> 2023 | AE15: =IFERROR(AVERAGE(W15:AB15),"") -> 0.043179965 | AF15: =MAX(0,$B$2-AC15) -> 0.10741916
A16: Bahamas | B16: BHS | D16: 0.13349923 | E16: 0.13963019 | F16: 0.13405273 | G16: 0.13809264 | H16: 0.13041773 | I16: 0.1286341 | J16: 0.12726217 | K16: 0.13499355 | L16: 0.1447345 | M16: 0.15009686 | N16: 0.15442394 | O16: 0.138966 | P16: 0.14060425 | Q16: 0.14021345 | R16: 0.1421291 | S16: 0.12836961 | T16: 0.13885354 | U16: 0.15596427 | V16: 0.143479 | W16: 0.14137413 | X16: 0.1491028 | Y16: 0.1232062 | Z16: 0.157634 | AA16: 0.13481312 | AC16: =LOOKUP(9.99E+307,D16:AB16) -> 0.13481312 | AD16: =LOOKUP(9.99E+307,D16:AB16,D$4:AB$4) -> 2023 | AE16: =IFERROR(AVERAGE(W16:AB16),"") -> 0.14122605 | AF16: =MAX(0,$B$2-AC16) -> 0.015186882
A17: Bahrain | B17: BHR | D17: 0.10268106 | E17: 0.090306454 | F17: 0.082211571 | G17: 0.087581797 | H17: 0.090417614 | I17: 0.091384249 | J17: 0.08944663 | K17: 0.090665274 | L17: 0.088342657 | M17: 0.11165728 | N17: 0.082303419 | O17: 0.080526104 | P17: 0.082980499 | Q17: 0.084568834 | R17: 0.10091253 | S17: 0.088659935 | T17: 0.085259905 | U17: 0.079766583 | V17: 0.072344513 | W17: 0.070605116 | X17: 0.082946186 | Y17: 0.090074635 | Z17: 0.086438742 | AA17: 0.084886742 | AC17: =LOOKUP(9.99E+307,D17:AB17) -> 0.084886742 | AD17: =LOOKUP(9.99E+307,D17:AB17,D$4:AB$4) -> 2023 | AE17: =IFERROR(AVERAGE(W17:AB17),"") -> 0.082990284 | AF17: =MAX(0,$B$2-AC17) -> 0.065113258
... A26: Bosnia and Herzegovina | B26: BIH | D26: 0.072539926 | E26: 0.086007443 | F26: 0.093225574 | G26: 0.11586452 | H26: 0.11320334 | I26: 0.10810091 | J26: 0.10958023 | K26: 0.1132833 | L26: 0.10918696 | M26: 0.12523983 | N26: 0.12600886 | O26: 0.13380139 | P26: 0.13883348 | Q26: 0.14794703 | R26: 0.14431893 | S26: 0.14984101 | T26: 0.15629663 | U26: 0.15466545 | V26: 0.151429 | W26: 0.15367926 | X26: 0.14880352 | Y26: 0.16057568 | Z26: 0.14565588 | AA26: 0.1442121 | AC26: =LOOKUP(9.99E+307,D26:AB26) -> 0.1442121 | AD26: =LOOKUP(9.99E+307,D26:AB26,D$4:AB$4) -> 2023 | AE26: =IFERROR(AVERAGE(W26:AB26),"") -> 0.15058529 | AF26: =MAX(0,$B$2-AC26) -> 0.0057878971
A27: Botswana | B27: BWA | C27: yes | D27: 0.08178297 | E27: 0.08178297 | F27: 0.08178297 | G27: 0.08178297 | H27: 0.08178297 | I27: 0.08178297 | J27: 0.08178297 | K27: 0.08178297 | L27: 0.076448069 | M27: 0.062520623 | N27: 0.08060935 | O27: 0.096322517 | P27: 0.10684479 | Q27: 0.11934482 | R27: 0.10958582 | S27: 0.10415888 | T27: 0.11211295 | U27: 0.14315475 | V27: 0.11542103 | W27: 0.12006065 | X27: 0.11661525 | Y27: 0.14610139 | Z27: 0.14610139 | AA27: 0.14610139 | AC27: =LOOKUP(9.99E+307,D27:AB27) -> 0.14610139 | AD27: =LOOKUP(9.99E+307,D27:AB27,D$4:AB$4) -> 2023 | AE27: =IFERROR(AVERAGE(W27:AB27),"") -> 0.13499601 | AF27: =MAX(0,$B$2-AC27) -> 0.0038986111
A28: Brazil | B28: BRA | D28: 0.096767397 | E28: 0.08826087 | F28: 0.082849064 | G28: 0.085001154 | H28: 0.087370558 | I28: 0.079895639 | J28: 0.083201942 | K28: 0.086356258 | L28: 0.087795753 | M28: 0.091458635 | N28: 0.090520887 | O28: 0.088034592 | P28: 0.085338993 | Q28: 0.089269133 | R28: 0.08928752 | S28: 0.083435726 | T28: 0.086763544 | U28: 0.089241323 | V28: 0.088030415 | W28: 0.091002769 | X28: 0.09034318 | Y28: 0.10667907 | Z28: 0.098047161 | AA28: 0.094769115 | AC28: =LOOKUP(9.99E+307,D28:AB28) -> 0.094769115 | AD28: =LOOKUP(9.99E+307,D28:AB28,D$4:AB$4) -> 2023 | AE28: =IFERROR(AVERAGE(W28:AB28),"") -> 0.096168259 | AF28: =MAX(0,$B$2-AC28) -> 0.055230885
A29: Brunei Darussalam | B29: BRN | D29: 0.057201023 | E29: 0.059716096 | F29: 0.051140027 | G29: 0.06989408 | H29: 0.063955154 | I29: 0.064329338 | J29: 0.058137608 | K29: 0.057738957 | L29: 0.062070947 | M29: 0.062168865 | N29: 0.05776835 | O29: 0.057430243 | P29: 0.054435349 | Q29: 0.051207418 | R29: 0.05203927 | S29: 0.058648925 | T29: 0.061532998 | U29: 0.05870759 | V29: 0.071402106 | W29: 0.06489933 | X29: 0.069482288 | Y29: 0.068214803 | Z29: 0.061809793 | AA29: 0.070233498 | AC29: =LOOKUP(9.99E+307,D29:AB29) -> 0.070233498 | AD29: =LOOKUP(9.99E+307,D29:AB29,D$4:AB$4) -> 2023 | AE29: =IFERROR(AVERAGE(W29:AB29),"") -> 0.066927942 | AF29: =MAX(0,$B$2-AC29) -> 0.079766502
A30: Bulgaria | B30: BGR | D30: 0.080766668 | E30: 0.094655161 | F30: 0.10744461 | G30: 0.11333193 | H30: 0.10827431 | I30: 0.11169881 | J30: 0.1079414 | K30: 0.091050682 | L30: 0.093931027 | M30: 0.090361624 | N30: 0.10849959 | O30: 0.11410629 | P30: 0.11179397 | Q30: 0.1069858 | R30: 0.10364101 | S30: 0.10233752 | T30: 0.11827792 | U30: 0.1183658 | V30: 0.11434177 | W30: 0.11553802 | X30: 0.12217266 | Y30: 0.13311139 | Z30: 0.11571726 | AA30: 0.12826755 | AC30: =LOOKUP(9.99E+307,D30:AB30) -> 0.12826755 | AD30: =LOOKUP(9.99E+307,D30:AB30,D$4:AB$4) -> 2023 | AE30: =IFERROR(AVERAGE(W30:AB30),"") -> 0.12296138 | AF30: =MAX(0,$B$2-AC30) -> 0.021732454
A31: Burkina Faso | B31: BFA | D31: 0.048483686 | E31: 0.049421768 | F31: 0.054349313 | G31: 0.055697293 | H31: 0.083909988 | I31: 0.060486403 | J31: 0.065406885 | K31: 0.062706828 | L31: 0.073215261 | M31: 0.07629394 | N31: 0.060323525 | O31: 0.065873938 | P31: 0.046960587 | Q31: 0.063829322 | R31: 0.077736711 | S31: 0.071526418 | T31: 0.11033994 | U31: 0.10235205 | V31: 0.087850237 | W31: 0.09576911 | X31: 0.116475 | Y31: 0.098384151 | Z31: 0.083968487 | AA31: 0.08775362 | AC31: =LOOKUP(9.99E+307,D31:AB31) -> 0.08775362 | AD31: =LOOKUP(9.99E+307,D31:AB31,D$4:AB$4) -> 2023 | AE31: =IFERROR(AVERAGE(W31:AB31),"") -> 0.096470074 | AF31: =MAX(0,$B$2-AC31) -> 0.06224638
A32: Burundi | B32: BDI | C32: yes | D32: 0.0594454 | E32: 0.066626387 | F32: 0.063795781 | G32: 0.037158155 | H32: 0.05803843 | I32: 0.06223104 | J32: 0.064814196 | K32: 0.063231559 | L32: 0.037877474 | M32: 0.054775238 | N32: 0.048606639 | O32: 0.082279139 | P32: 0.071102819 | Q32: 0.044317017 | R32: 0.097924833 | S32: 0.10443518 | T32: 0.099044924 | U32: 0.083575859 | V32: 0.079078622 | W32: 0.079078622 | X32: 0.073328781 | Y32: 0.073328781 | Z32: 0.047289734 | AA32: 0.047289734 | AC32: =LOOKUP(9.99E+307,D32:AB32) -> 0.047289734 | AD32: =LOOKUP(9.99E+307,D32:AB32,D$4:AB$4) -> 2023 | AE32: =IFERROR(AVERAGE(W32:AB32),"") -> 0.06406313 | AF32: =MAX(0,$B$2-AC32) -> 0.10271027
A33: Cabo Verde | B33: CPV | D33: 0.075015879 | E33: 0.11173052 | F33: 0.095042782 | G33: 0.11367002 | H33: 0.096314259 | I33: 0.088029909 | J33: 0.089211149 | K33: 0.10090197 | L33: 0.081084881 | M33: 0.08311655 | N33: 0.072267523 | O33: 0.086077766 | P33: 0.088649693 | Q33: 0.090295563 | R33: 0.099830713 | S33: 0.10093954 | T33: 0.10392425 | U33: 0.091237488 | V33: 0.11265527 | W33: 0.11783461 | X33: 0.13447078 | Y33: 0.14889709 | Z33: 0.1606422 | AA33: 0.1378945 | AC33: =LOOKUP(9.99E+307,D33:AB33) -> 0.1378945 | AD33: =LOOKUP(9.99E+307,D33:AB33,D$4:AB$4) -> 2023 | AE33: =IFERROR(AVERAGE(W33:AB33),"") -> 0.13994784 | AF33: =MAX(0,$B$2-AC33) -> 0.012105503
A34: Cambodia | B34: KHM | D34: 0.085917358 | E34: 0.07830318 | F34: 0.082978315 | G34: 0.094304419 | H34: 0.099010906 | I34: 0.098973665 | J34: 0.074111047 | K34: 0.067482748 | L34: 0.066590457 | M34: 0.059676833 | N34: 0.065196424 | O34: 0.062146068 | P34: 0.063306508 | Q34: 0.067916837 | R34: 0.061677031 | S34: 0.069401135 | T34: 0.068482499 | U34: 0.069959145 | V34: 0.075233431 | W34: 0.069910355 | X34: 0.068979673 | Y34: 0.14310493 | Z34: 0.064150882 | AA34: 0.066474256 | AC34: =LOOKUP(9.99E+307,D34:AB34) -> 0.066474256 | AD34: =LOOKUP(9.99E+307,D34:AB34,D$4:AB$4) -> 2023 | AE34: =IFERROR(AVERAGE(W34:AB34),"") -> 0.082524018 | AF34: =MAX(0,$B$2-AC34) -> 0.083525743
A35: Cameroon | B35: CMR | C35: yes | D35: 0.044262691 | E35: 0.053437476 | F35: 0.064329853 | G35: 0.06515377 | H35: 0.052618337 | I35: 0.05247488 | J35: 0.051831469 | K35: 0.042260818 | L35: 0.034610515 | M35: 0.030473874 | N35: 0.026757979 | O35: 0.032104812 | P35: 0.037318034 | Q35: 0.025009561 | R35: 0.029397316 | S35: 0.018129396 | T35: 0.018129396 | U35: 0.0073440903 | V35: 0.019570337 | W35: 0.021798592 | X35: 0.036595056 | Y35: 0.028629239 | Z35: 0.039128006 | AA35: 0.039128006 | AC35: =LOOKUP(9.99E+307,D35:AB35) -> 0.039128006 | AD35: =LOOKUP(9.99E+307,D35:AB35,D$4:AB$4) -> 2023 | AE35: =IFERROR(AVERAGE(W35:AB35),"") -> 0.033055779 | AF35: =MAX(0,$B$2-AC35) -> 0.11087199
A36: Canada | B36: CAN | D36: 0.14815627 | E36: 0.1527648 | F36: 0.15882566 | G36: 0.16363544 | H36: 0.16926079 | I36: 0.17131039 | J36: 0.16781704 | K36: 0.17068182 | L36: 0.1728191 | M36: 0.17325489 | N36: 0.17377098 | O36: 0.17589609 | P36: 0.18173801 | Q36: 0.18530561 | R36: 0.18969894 | S36: 0.19068136 | T36: 0.18961018 | U36: 0.18809015 | V36: 0.18701818 | W36: 0.18927599 | X36: 0.18363117 | Y36: 0.19796778 | Z36: 0.19361433 | AA36: 0.18684921 | AB36: 0.17756598 | AC36: =LOOKUP(9.99E+307,D36:AB36) -> 0.17756598 | AD36: =LOOKUP(9.99E+307,D36:AB36,D$4:AB$4) -> 2024 | AE36: =IFERROR(AVERAGE(W36:AB36),"") -> 0.18815074 | AF36: =MAX(0,$B$2-AC36) -> 0
A37: Central African Republic | B37: CAF | D37: 0.10021617 | E37: 0.10725758 | F37: 0.086075211 | G37: 0.1254863 | H37: 0.11276064 | I37: 0.064003949 | J37: 0.091779222 | K37: 0.098746586 | L37: 0.05283493 | M37: 0.04575438 | N37: 0.033414733 | O37: 0.029325564 | P37: 0.042233172 | Q37: 0.073451528 | R37: 0.039467859 | S37: 0.032645256 | T37: 0.049471331 | U37: 0.052599773 | V37: 0.039108746 | W37: 0.048423176 | X37: 0.048644204 | Y37: 0.064207349 | Z37: 0.084761972 | AA37: 0.084761972 | AC37: =LOOKUP(9.99E+307,D37:AB37) -> 0.084761972 | AD37: =LOOKUP(9.99E+307,D37:AB37,D$4:AB$4) -> 2023 | AE37: =IFERROR(AVERAGE(W37:AB37),"") -> 0.066159735 | AF37: =MAX(0,$B$2-AC37) -> 0.065238028
A38: Chad | B38: TCD | D38: 0.11398789 | E38: 0.11868776 | F38: 0.11724425 | G38: 0.089815569 | H38: 0.1503138 | I38: 0.12423414 | J38: 0.07144639 | K38: 0.059949446 | L38: 0.042314992 | M38: 0.035498657 | N38: 0.034979272 | O38: 0.036880267 | P38: 0.039646971 | Q38: 0.050367928 | R38: 0.055486155 | S38: 0.052452025 | T38: 0.057250209 | U38: 0.046783958 | V38: 0.048614955 | W38: 0.048614955 | X38: 0.039544351 | Y38: 0.05641912 | Z38: 0.072637334 | AA38: 0.072637334 | AC38: =LOOKUP(9.99E+307,D38:AB38) -> 0.072637334 | AD38: =LOOKUP(9.99E+307,D38:AB38,D$4:AB$4) -> 2023 | AE38: =IFERROR(AVERAGE(W38:AB38),"") -> 0.057970619 | AF38: =MAX(0,$B$2-AC38) -> 0.077362666
A39: Chile | B39: CHL | D39: 0.10956289 | E39: 0.11133472 | F39: 0.1166363 | G39: 0.12481333 | H39: 0.13101777 | I39: 0.12869405 | J39: 0.13405399 | K39: 0.1359831 | L39: 0.13461457 | M39: 0.13603492 | N39: 0.13689023 | O39: 0.14010506 | P39: 0.14573092 | Q39: 0.15411278 | R39: 0.15693084 | S39: 0.1602235 | T39: 0.16750845 | U39: 0.17972158 | V39: 0.18303989 | W39: 0.18011597 | X39: 0.18839195 | Y39: 0.15523948 | Z39: 0.19047033 | AA39: 0.1916633 | AB39: 0.19296413 | AC39: =LOOKUP(9.99E+307,D39:AB39) -> 0.19296413 | AD39: =LOOKUP(9.99E+307,D39:AB39,D$4:AB$4) -> 2024 | AE39: =IFERROR(AVERAGE(W39:AB39),"") -> 0.18314086 | AF39: =MAX(0,$B$2-AC39) -> 0
A40: China | B40: CHN | D40: 0.060898409 | E40: 0.05589242 | F40: 0.060258031 | G40: 0.068765297 | H40: 0.072660584 | I40: 0.074888291 | J40: 0.075638208 | K40: 0.079013572 | L40: 0.077085824 | M40: 0.083752317 | N40: 0.087509222 | O40: 0.0860285 | P40: 0.090372934 | Q40: 0.094168425 | R40: 0.096608858 | S40: 0.094190235 | T40: 0.089527655 | U40: 0.087973442 | V40: 0.087614632 | W40: 0.087695618 | X40: 0.086463261 | Y40: 0.089053545 | Z40: 0.10394173 | AA40: 0.10367977 | AC40: =LOOKUP(9.99E+307,D40:AB40) -> 0.10367977 | AD40: =LOOKUP(9.99E+307,D40:AB40,D$4:AB$4) -> 2023 | AE40: =IFERROR(AVERAGE(W40:AB40),"") -> 0.094166784 | AF40: =MAX(0,$B$2-AC40) -> 0.046320229
A41: Colombia | B41: COL | D41: 0.14881617 | E41: 0.15377504 | F41: 0.1486478 | G41: 0.15598855 | H41: 0.15737347 | I41: 0.16830919 | J41: 0.16057571 | K41: 0.16284443 | L41: 0.16693029 | M41: 0.17040621 | N41: 0.1682774 | O41: 0.16484554 | P41: 0.16199553 | Q41: 0.16341106 | R41: 0.16182764 | S41: 0.17037544 | T41: 0.1765918 | U41: 0.18604675 | V41: 0.15547496 | W41: 0.16659067 | X41: 0.18450232 | Y41: 0.19372189 | Z41: 0.1576685 | AA41: 0.16186947 | AB41: 0.17243502 | AC41: =LOOKUP(9.99E+307,D41:AB41) -> 0.17243502 | AD41: =LOOKUP(9.99E+307,D41:AB41,D$4:AB$4) -> 2024 | AE41: =IFERROR(AVERAGE(W41:AB41),"") -> 0.17279798 | AF41: =MAX(0,$B$2-AC41) -> 0
A42: Comoros | B42: COM | D42: 0.091551466 | E42: 0.041141682 | F42: 0.067107038 | G42: 0.066844735 | H42: 0.067557421 | I42: 0.054200544 | J42: 0.051817398 | K42: 0.043323989 | L42: 0.028645396 | M42: 0.027746561 | N42: 0.02839236 | O42: 0.072384434 | P42: 0.053522482 | Q42: 0.04449965 | R42: 0.038196549 | S42: 0.024457152 | T42: 0.030360751 | U42: 0.03585496 | V42: 0.039939125 | W42: 0.041334567 | X42: 0.068890824 | Y42: 0.047373166 | Z42: 0.047373166 | AA42: 0.047373166 | AC42: =LOOKUP(9.99E+307,D42:AB42) -> 0.047373166 | AD42: =LOOKUP(9.99E+307,D42:AB42,D$4:AB$4) -> 2023 | AE42: =IFERROR(AVERAGE(W42:AB42),"") -> 0.050468978 | AF42: =MAX(0,$B$2-AC42) -> 0.10262683
A43: Congo | B43: COG | D43: 0.022729034 | E43: 0.033190191 | F43: 0.013442719 | G43: 0.018552579 | H43: 0.017842994 | I43: 0.019531525 | J43: 0.020837886 | K43: 0.020520797 | L43: 0.045489221 | M43: 0.025281646 | N43: 0.03602102 | O43: 0.023368313 | P43: 0.026713102 | Q43: 0.022095163 | R43: 0.019499675 | S43: 0.027098103 | T43: 0.028850231 | U43: 0.034111474 | V43: 0.034871991 | W43: 0.051072521 | X43: 0.082168407 | Y43: 0.082168407 | Z43: 0.035258799 | AA43: 0.054217749 | AC43: =LOOKUP(9.99E+307,D43:AB43) -> 0.054217749 | AD43: =LOOKUP(9.99E+307,D43:AB43,D$4:AB$4) -> 2023 | AE43: =IFERROR(AVERAGE(W43:AB43),"") -> 0.060977177 | AF43: =MAX(0,$B$2-AC43) -> 0.095782251
A44: Cook Islands | B44: COK | D44: 0.096333189 | E44: 0.09633318 | F44: 0.10124437 | G44: 0.09633317 | H44: 0.09633316 | I44: 0.09633316 | J44: 0.096311035 | K44: 0.096309767 | L44: 0.096322861 | M44: 0.10858501 | N44: 0.095378628 | O44: 0.088194342 | P44: 0.083177214 | Q44: 0.080714674 | R44: 0.091433182 | S44: 0.072444553 | T44: 0.081484423 | U44: 0.072633815 | V44: 0.076654878 | W44: 0.093362999 | X44: 0.11665719 | Y44: 0.082263794 | Z44: 0.10750381 | AA44: 0.1027783 | AC44: =LOOKUP(9.99E+307,D44:AB44) -> 0.1027783 | AD44: =LOOKUP(9.99E+307,D44:AB44,D$4:AB$4) -> 2023 | AE44: =IFERROR(AVERAGE(W44:AB44),"") -> 0.10051322 | AF44: =MAX(0,$B$2-AC44) -> 0.047221699
A45: Costa Rica | B45: CRI | D45: 0.25264774 | E45: 0.24561287 | F45: 0.24758076 | G45: 0.26331982 | H45: 0.25737473 | I45: 0.26825884 | J45: 0.30262608 | K45: 0.31738693 | L45: 0.33367374 | M45: 0.33472801 | N45: 0.32182404 | O45: 0.33184631 | P45: 0.31732821 | Q45: 0.29452593 | R45: 0.2958095 | S45: 0.29424847 | T45: 0.28605955 | U45: 0.27034313 | V45: 0.27914709 | W45: 0.24153326 | X45: 0.25207146 | Y45: 0.257729 | Z45: 0.25816147 | AA45: 0.24907295 | AC45: =LOOKUP(9.99E+307,D45:AB45) -> 0.24907295 | AD45: =LOOKUP(9.99E+307,D45:AB45,D$4:AB$4) -> 2023 | AE45: =IFERROR(AVERAGE(W45:AB45),"") -> 0.25171363 | AF45: =MAX(0,$B$2-AC45) -> 0
A46: Croatia | B46: HRV | D46: 0.11923579 | E46: 0.1164405 | F46: 0.098688946 | G46: 0.10316412 | H46: 0.10597341 | I46: 0.12509827 | J46: 0.13114732 | K46: 0.13788143 | L46: 0.13838007 | M46: 0.13517841 | N46: 0.13775545 | O46: 0.12867774 | P46: 0.13348791 | Q46: 0.11375049 | R46: 0.11334707 | S46: 0.11636552 | T46: 0.12088621 | U46: 0.12407314 | V46: 0.12274974 | W46: 0.1195514 | X46: 0.1170918 | Y46: 0.14128839 | Z46: 0.13709288 | AA46: 0.12840257 | AC46: =LOOKUP(9.99E+307,D46:AB46) -> 0.12840257 | AD46: =LOOKUP(9.99E+307,D46:AB46,D$4:AB$4) -> 2023 | AE46: =IFERROR(AVERAGE(W46:AB46),"") -> 0.12868541 | AF46: =MAX(0,$B$2-AC46) -> 0.021597433
A47: Cuba | B47: CUB | D47: 0.10802315 | E47: 0.11391795 | F47: 0.11190471 | G47: 0.10890823 | H47: 0.10320927 | I47: 0.11667609 | J47: 0.11205644 | K47: 0.1448143 | L47: 0.13177696 | M47: 0.14932304 | N47: 0.13865822 | O47: 0.15093541 | P47: 0.11494596 | Q47: 0.14140575 | R47: 0.18024471 | S47: 0.18245586 | T47: 0.17302824 | U47: 0.15512218 | V47: 0.14935592 | W47: 0.15516299 | X47: 0.16431042 | Y47: 0.21482759 | Z47: 0.21039637 | AA47: 0.1997772 | AC47: =LOOKUP(9.99E+307,D47:AB47) -> 0.1997772 | AD47: =LOOKUP(9.99E+307,D47:AB47,D$4:AB$4) -> 2023 | AE47: =IFERROR(AVERAGE(W47:AB47),"") -> 0.18889491 | AF47: =MAX(0,$B$2-AC47) -> 0
A48: Cyprus | B48: CYP | D48: 0.059856963 | E48: 0.060168471 | F48: 0.06400969 | G48: 0.057754579 | H48: 0.054583502 | I48: 0.054313054 | J48: 0.057055769 | K48: 0.057653775 | L48: 0.061328058 | M48: 0.061237974 | N48: 0.066829467 | O48: 0.067843671 | P48: 0.055008144 | Q48: 0.068120861 | R48: 0.056516542 | S48: 0.066295128 | T48: 0.07054956 | U48: 0.071307569 | V48: 0.064431195 | W48: 0.094155998 | X48: 0.13524846 | Y48: 0.16323246 | Z48: 0.1659008 | AA48: 0.14859171 | AC48: =LOOKUP(9.99E+307,D48:AB48) -> 0.14859171 | AD48: =LOOKUP(9.99E+307,D48:AB48,D$4:AB$4) -> 2023 | AE48: =IFERROR(AVERAGE(W48:AB48),"") -> 0.14142589 | AF48: =MAX(0,$B$2-AC48) -> 0.0014082909
A49: Czechia | B49: CZE | D49: 0.12388258 | E49: 0.11838051 | F49: 0.12182892 | G49: 0.1161949 | H49: 0.13144728 | I49: 0.1275457 | J49: 0.12711453 | K49: 0.12403005 | L49: 0.12545538 | M49: 0.13544696 | N49: 0.14695007 | O49: 0.14741914 | P49: 0.14378068 | Q49: 0.14843148 | R49: 0.14962428 | S49: 0.14754028 | T49: 0.15715848 | U49: 0.15912028 | V49: 0.15556313 | W49: 0.15682148 | X49: 0.17062262 | Y49: 0.17588268 | Z49: 0.16703617 | AA49: 0.16180204 | AC49: =LOOKUP(9.99E+307,D49:AB49) -> 0.16180204 | AD49: =LOOKUP(9.99E+307,D49:AB49,D$4:AB$4) -> 2023 | AE49: =IFERROR(AVERAGE(W49:AB49),"") -> 0.166433 | AF49: =MAX(0,$B$2-AC49) -> 0
A50: Côte d'Ivoire | B50: CIV | D50: 0.045575986 | E50: 0.044565473 | F50: 0.041479588 | G50: 0.040670872 | H50: 0.041451526 | I50: 0.038913488 | J50: 0.038571844 | K50: 0.045792217 | L50: 0.046578813 | M50: 0.058213243 | N50: 0.058067884 | O50: 0.043936925 | P50: 0.046220031 | Q50: 0.045898829 | R50: 0.051112542 | S50: 0.048747077 | T50: 0.048519926 | U50: 0.051502876 | V50: 0.051172767 | W50: 0.056012759 | X50: 0.06538353 | Y50: 0.077738953 | Z50: 0.068222361 | AA50: 0.065832048 | AC50: =LOOKUP(9.99E+307,D50:AB50) -> 0.065832048 | AD50: =LOOKUP(9.99E+307,D50:AB50,D$4:AB$4) -> 2023 | AE50: =IFERROR(AVERAGE(W50:AB50),"") -> 0.06663793 | AF50: =MAX(0,$B$2-AC50) -> 0.084167952
A51: Democratic Republic of the Congo | B51: COD | D51: 0.024989526 | E51: 0.024989526 | F51: 0.024989526 | G51: 0.024989526 | H51: 0.024989526 | I51: 0.024989526 | J51: 0.024989526 | K51: 0.024989526 | L51: 0.024989526 | M51: 0.024989526 | N51: 0.024989526 | O51: 0.025320144 | P51: 0.038775921 | Q51: 0.039094405 | R51: 0.039867942 | S51: 0.041041536 | T51: 0.03807735 | U51: 0.038418849 | V51: 0.041669412 | W51: 0.041286588 | X51: 0.050872474 | Y51: 0.045126462 | Z51: 0.039843409 | AA51: 0.040007191 | AC51: =LOOKUP(9.99E+307,D51:AB51) -> 0.040007191 | AD51: =LOOKUP(9.99E+307,D51:AB51,D$4:AB$4) -> 2023 | AE51: =IFERROR(AVERAGE(W51:AB51),"") -> 0.043427225 | AF51: =MAX(0,$B$2-AC51) -> 0.10999281
A52: Denmark | B52: DNK | D52: 0.12748543 | E52: 0.13288517 | F52: 0.13723657 | G52: 0.13943393 | H52: 0.14221165 | I52: 0.14872601 | J52: 0.15441875 | K52: 0.15744954 | L52: 0.15820475 | M52: 0.15936565 | N52: 0.15799385 | O52: 0.15504166 | P52: 0.15346861 | Q52: 0.1564888 | R52: 0.1580607 | S52: 0.16064283 | T52: 0.1653396 | U52: 0.16780603 | V52: 0.16734722 | W52: 0.17117033 | X52: 0.16907198 | Y52: 0.18217592 | Z52: 0.17817404 | AA52: 0.16917269 | AB52: 0.16858686 | AC52: =LOOKUP(9.99E+307,D52:AB52) -> 0.16858686 | AD52: =LOOKUP(9.99E+307,D52:AB52,D$4:AB$4) -> 2024 | AE52: =IFERROR(AVERAGE(W52:AB52),"") -> 0.17305864 | AF52: =MAX(0,$B$2-AC52) -> 0
A53: Djibouti | B53: DJI | D53: 0.060754762 | E53: 0.059684048 | F53: 0.05495636 | G53: 0.058153071 | H53: 0.053861504 | I53: 0.053278184 | J53: 0.072324629 | K53: 0.065265923 | L53: 0.063488808 | M53: 0.061399169 | N53: 0.069704871 | O53: 0.084744921 | P53: 0.071332936 | Q53: 0.067350478 | R53: 0.060729909 | S53: 0.040695095 | T53: 0.051373649 | U53: 0.048029952 | V53: 0.051697979 | W53: 0.051610975 | X53: 0.041593022 | Y53: 0.033152716 | Z53: 0.050955634 | AA53: 0.048918228 | AC53: =LOOKUP(9.99E+307,D53:AB53) -> 0.048918228 | AD53: =LOOKUP(9.99E+307,D53:AB53,D$4:AB$4) -> 2023 | AE53: =IFERROR(AVERAGE(W53:AB53),"") -> 0.045246115 | AF53: =MAX(0,$B$2-AC53) -> 0.10108177
A54: Dominica | B54: DMA | D54: 0.086406117 | E54: 0.087834692 | F54: 0.08401413 | G54: 0.086660767 | H54: 0.085275669 | I54: 0.08720129 | J54: 0.087401485 | K54: 0.070998449 | L54: 0.072852678 | M54: 0.074169898 | N54: 0.074434113 | O54: 0.090903921 | P54: 0.094937553 | Q54: 0.095945721 | R54: 0.096197996 | S54: 0.097314014 | T54: 0.072784901 | U54: 0.067698622 | V54: 0.061579714 | W54: 0.075669174 | X54: 0.05408915 | Y54: 0.057531629 | Z54: 0.062004514 | AA54: 0.050313516 | AC54: =LOOKUP(9.99E+307,D54:AB54) -> 0.050313516 | AD54: =LOOKUP(9.99E+307,D54:AB54,D$4:AB$4) -> 2023 | AE54: =IFERROR(AVERAGE(W54:AB54),"") -> 0.059921597 | AF54: =MAX(0,$B$2-AC54) -> 0.099686484
A55: Dominican Republic | B55: DOM | D55: 0.12137587 | E55: 0.11438853 | F55: 0.10194515 | G55: 0.067342434 | H55: 0.06621449 | I55: 0.089872961 | J55: 0.082697029 | K55: 0.10323029 | L55: 0.11476502 | M55: 0.14433601 | N55: 0.15678899 | O55: 0.170697 | P55: 0.13968768 | Q55: 0.1503564 | R55: 0.14475961 | S55: 0.14195518 | T55: 0.15698118 | U55: 0.15108495 | V55: 0.15667871 | W55: 0.14952268 | X55: 0.14678337 | Y55: 0.18260876 | Z55: 0.15200764 | AA55: 0.15411339 | AC55: =LOOKUP(9.99E+307,D55:AB55) -> 0.15411339 | AD55: =LOOKUP(9.99E+307,D55:AB55,D$4:AB$4) -> 2023 | AE55: =IFERROR(AVERAGE(W55:AB55),"") -> 0.15700717 | AF55: =MAX(0,$B$2-AC55) -> 0
A56: Ecuador | B56: ECU | D56: 0.04139431 | E56: 0.062078028 | F56: 0.065468268 | G56: 0.082131472 | H56: 0.084612303 | I56: 0.078655849 | J56: 0.085682659 | K56: 0.088273954 | L56: 0.061516337 | M56: 0.074589715 | N56: 0.084362812 | O56: 0.079652543 | P56: 0.08172205 | Q56: 0.082616138 | R56: 0.090497227 | S56: 0.10204524 | T56: 0.10479515 | U56: 0.11459781 | V56: 0.12205158 | W56: 0.12355843 | X56: 0.13132625 | Y56: 0.14189287 | Z56: 0.12142165 | AA56: 0.11873737 | AC56: =LOOKUP(9.99E+307,D56:AB56) -> 0.11873737 | AD56: =LOOKUP(9.99E+307,D56:AB56,D$4:AB$4) -> 2023 | AE56: =IFERROR(AVERAGE(W56:AB56),"") -> 0.12738731 | AF56: =MAX(0,$B$2-AC56) -> 0.031262627
A57: Egypt | B57: EGY | D57: 0.066637259 | E57: 0.066326628 | F57: 0.061411839 | G57: 0.054432034 | H57: 0.052430897 | I57: 0.052435308 | J57: 0.050499468 | K57: 0.050176458 | L57: 0.046992469 | M57: 0.047180848 | N57: 0.043615632 | O57: 0.048270822 | P57: 0.043854094 | Q57: 0.041566329 | R57: 0.041614847 | S57: 0.050579767 | T57: 0.050579767 | U57: 0.054199476 | V57: 0.047215853 | W57: 0.048228469 | X57: 0.051611223 | Y57: 0.067994494 | Z57: 0.067607384 | AA57: 0.069267306 | AC57: =LOOKUP(9.99E+307,D57:AB57) -> 0.069267306 | AD57: =LOOKUP(9.99E+307,D57:AB57,D$4:AB$4) -> 2023 | AE57: =IFERROR(AVERAGE(W57:AB57),"") -> 0.060941775 | AF57: =MAX(0,$B$2-AC57) -> 0.080732694
A58: El Salvador | B58: SLV | D58: 0.18813766 | E58: 0.1768816 | F58: 0.1778229 | G58: 0.17186676 | H58: 0.18680647 | I58: 0.18938656 | J58: 0.19308365 | K58: 0.17984247 | L58: 0.16658825 | M58: 0.15814736 | N58: 0.17085518 | O58: 0.18986029 | P58: 0.162677 | Q58: 0.16716999 | R58: 0.16978041 | S58: 0.17738533 | T58: 0.17652054 | U58: 0.16314199 | V58: 0.16460562 | W58: 0.16971138 | X58: 0.1772464 | Y58: 0.2065045 | Z58: 0.21437885 | AA58: 0.1850918 | AC58: =LOOKUP(9.99E+307,D58:AB58) -> 0.1850918 | AD58: =LOOKUP(9.99E+307,D58:AB58,D$4:AB$4) -> 2023 | AE58: =IFERROR(AVERAGE(W58:AB58),"") -> 0.19058659 | AF58: =MAX(0,$B$2-AC58) -> 0
A59: Equatorial Guinea | B59: GNQ | D59: 0.023096285 | E59: 0.029073269 | F59: 0.03198767 | G59: 0.028615487 | H59: 0.032743199 | I59: 0.028398647 | J59: 0.025306692 | K59: 0.02441539 | L59: 0.0243119 | M59: 0.019303828 | N59: 0.020691845 | O59: 0.021547396 | P59: 0.019963014 | Q59: 0.021107135 | R59: 0.020607238 | S59: 0.017879912 | T59: 0.031105394 | U59: 0.039362917 | V59: 0.042775426 | W59: 0.047922282 | X59: 0.063953814 | Y59: 0.089973764 | Z59: 0.058613305 | AA59: 0.058653078 | AC59: =LOOKUP(9.99E+307,D59:AB59) -> 0.058653078 | AD59: =LOOKUP(9.99E+307,D59:AB59,D$4:AB$4) -> 2023 | AE59: =IFERROR(AVERAGE(W59:AB59),"") -> 0.063823249 | AF59: =MAX(0,$B$2-AC59) -> 0.091346922
A60: Eritrea | B60: ERI | D60: 0.024220676 | E60: 0.030102041 | F60: 0.035287104 | G60: 0.028702853 | H60: 0.027329979 | I60: 0.011140076 | J60: 0.016211193 | K60: 0.023728719 | L60: 0.023728719 | M60: 0.023728719 | N60: 0.023728719 | O60: 0.023728719 | P60: 0.023728719 | Q60: 0.023728719 | R60: 0.023728719 | S60: 0.023728719 | T60: 0.023728719 | U60: 0.023728719 | V60: 0.023728719 | W60: 0.023728719 | X60: 0.023728719 | Y60: 0.023728719 | Z60: 0.023728719 | AA60: 0.023728719 | AC60: =LOOKUP(9.99E+307,D60:AB60) -> 0.023728719 | AD60: =LOOKUP(9.99E+307,D60:AB60,D$4:AB$4) -> 2023 | AE60: =IFERROR(AVERAGE(W60:AB60),"") -> 0.023728719 | AF60: =MAX(0,$B$2-AC60) -> 0.12627128
A61: Estonia | B61: EST | D61: 0.10782393 | E61: 0.1056832 | F61: 0.099725637 | G61: 0.11076973 | H61: 0.11509225 | I61: 0.11575336 | J61: 0.11036446 | K61: 0.11453437 | L61: 0.11394276 | M61: 0.11335488 | N61: 0.11892976 | O61: 0.11927606 | P61: 0.11519547 | Q61: 0.12045306 | R61: 0.12427452 | S61: 0.12364561 | T61: 0.12564738 | U61: 0.1223001 | V61: 0.12440928 | W61: 0.12637461 | X61: 0.1286363 | Y61: 0.13507273 | Z61: 0.12979257 | AA61: 0.12958453 | AC61: =LOOKUP(9.99E+307,D61:AB61) -> 0.12958453 | AD61: =LOOKUP(9.99E+307,D61:AB61,D$4:AB$4) -> 2023 | AE61: =IFERROR(AVERAGE(W61:AB61),"") -> 0.12989215 | AF61: =MAX(0,$B$2-AC61) -> 0.020415468
A62: Eswatini | B62: SWZ | C62: yes | D62: 0.097942724 | E62: 0.092848577 | F62: 0.091893816 | G62: 0.11396682 | H62: 0.097426119 | I62: 0.12612316 | J62: 0.12620983 | K62: 0.12373458 | L62: 0.13342635 | M62: 0.1333174 | N62: 0.13756534 | O62: 0.14277364 | P62: 0.12654774 | Q62: 0.11660085 | R62: 0.085009337 | S62: 0.085870171 | T62: 0.082180529 | U62: 0.099716406 | V62: 0.096976748 | W62: 0.1293036 | X62: 0.10393844 | Y62: 0.12300969 | Z62: 0.10635378 | AA62: 0.10635378 | AC62: =LOOKUP(9.99E+307,D62:AB62) -> 0.10635378 | AD62: =LOOKUP(9.99E+307,D62:AB62,D$4:AB$4) -> 2023 | AE62: =IFERROR(AVERAGE(W62:AB62),"") -> 0.11379186 | AF62: =MAX(0,$B$2-AC62) -> 0.043646221
A63: Ethiopia | B63: ETH | C63: yes | D63: 0.070295844 | E63: 0.089823351 | F63: 0.083686762 | G63: 0.084177933 | H63: 0.05726654 | I63: 0.07550024 | J63: 0.050760446 | K63: 0.064959817 | L63: 0.027417819 | M63: 0.053002 | N63: 0.051071138 | O63: 0.020911443 | P63: 0.064068546 | Q63: 0.061933026 | R63: 0.040883422 | S63: 0.055721168 | T63: 0.050244527 | U63: 0.047883601 | V63: 0.047606049 | W63: 0.047606049 | X63: 0.067922325 | Y63: 0.07096745 | Z63: 0.05676702 | AA63: 0.05676702 | AC63: =LOOKUP(9.99E+307,D63:AB63) -> 0.05676702 | AD63: =LOOKUP(9.99E+307,D63:AB63,D$4:AB$4) -> 2023 | AE63: =IFERROR(AVERAGE(W63:AB63),"") -> 0.060005973 | AF63: =MAX(0,$B$2-AC63) -> 0.09323298
A64: Fiji | B64: FJI | D64: 0.10588044 | E64: 0.079022274 | F64: 0.080357571 | G64: 0.086106272 | H64: 0.092540503 | I64: 0.10359533 | J64: 0.099688578 | K64: 0.10593208 | L64: 0.097818184 | M64: 0.083703699 | N64: 0.087944441 | O64: 0.074741101 | P64: 0.075050917 | Q64: 0.07466826 | R64: 0.071042762 | S64: 0.070441751 | T64: 0.066678991 | U64: 0.077232141 | V64: 0.077550287 | W64: 0.087279425 | X64: 0.086814642 | Y64: 0.10310143 | Z64: 0.10329376 | AA64: 0.09322113 | AC64: =LOOKUP(9.99E+307,D64:AB64) -> 0.09322113 | AD64: =LOOKUP(9.99E+307,D64:AB64,D$4:AB$4) -> 2023 | AE64: =IFERROR(AVERAGE(W64:AB64),"") -> 0.094742077 | AF64: =MAX(0,$B$2-AC64) -> 0.05677887
A65: Finland | B65: FIN | D65: 0.11210176 | E65: 0.11690111 | F65: 0.12095653 | G65: 0.12442871 | H65: 0.12771414 | I65: 0.13157266 | J65: 0.13574973 | K65: 0.1364809 | L65: 0.13737659 | M65: 0.13384903 | N65: 0.13292454 | O65: 0.13587016 | P65: 0.13779918 | Q65: 0.13699012 | R65: 0.13572024 | S65: 0.13670947 | T65: 0.13356859 | U65: 0.1356778 | V65: 0.13582366 | W65: 0.14061247 | X65: 0.13974769 | Y65: 0.14626522 | Z65: 0.151254 | AA65: 0.1519407 | AC65: =LOOKUP(9.99E+307,D65:AB65) -> 0.1519407 | AD65: =LOOKUP(9.99E+307,D65:AB65,D$4:AB$4) -> 2023 | AE65: =IFERROR(AVERAGE(W65:AB65),"") -> 0.14596401 | AF65: =MAX(0,$B$2-AC65) -> 0
A66: France | B66: FRA | D66: 0.13495421 | E66: 0.13654057 | F66: 0.13858079 | G66: 0.13748136 | H66: 0.13935871 | I66: 0.13905218 | J66: 0.13999301 | K66: 0.13952299 | L66: 0.13915397 | M66: 0.13959336 | N66: 0.13748777 | O66: 0.13818472 | P66: 0.13815845 | Q66: 0.13983721 | R66: 0.14148189 | S66: 0.14516502 | T66: 0.15174274 | U66: 0.15210646 | V66: 0.15222422 | W66: 0.15052577 | X66: 0.15004672 | Y66: 0.15557046 | Z66: 0.15254701 | AA66: 0.13696946 | AB66: 0.13806446 | AC66: =LOOKUP(9.99E+307,D66:AB66) -> 0.13806446 | AD66: =LOOKUP(9.99E+307,D66:AB66,D$4:AB$4) -> 2024 | AE66: =IFERROR(AVERAGE(W66:AB66),"") -> 0.14728731 | AF66: =MAX(0,$B$2-AC66) -> 0.011935539
A67: Gabon | B67: GAB | D67: 0.052412825 | E67: 0.045377698 | F67: 0.046636677 | G67: 0.067543745 | H67: 0.06513216 | I67: 0.050768027 | J67: 0.057600718 | K67: 0.063619065 | L67: 0.05612905 | M67: 0.06817637 | N67: 0.068133764 | O67: 0.071831636 | P67: 0.061915851 | Q67: 0.052575402 | R67: 0.063845825 | S67: 0.07034874 | T67: 0.092025576 | U67: 0.097150774 | V67: 0.094152069 | W67: 0.095915585 | X67: 0.095915585 | Y67: 0.095915585 | Z67: 0.095915585 | AA67: 0.095915585 | AC67: =LOOKUP(9.99E+307,D67:AB67) -> 0.095915585 | AD67: =LOOKUP(9.99E+307,D67:AB67,D$4:AB$4) -> 2023 | AE67: =IFERROR(AVERAGE(W67:AB67),"") -> 0.095915585 | AF67: =MAX(0,$B$2-AC67) -> 0.054084415
A68: Gambia | B68: GMB | D68: 0.063089752 | E68: 0.063089752 | F68: 0.063089752 | G68: 0.063089752 | H68: 0.063089752 | I68: 0.063089752 | J68: 0.063089752 | K68: 0.063089752 | L68: 0.063089752 | M68: 0.063089752 | N68: 0.063089752 | O68: 0.063089752 | P68: 0.063089752 | Q68: 0.063089752 | R68: 0.057540197 | S68: 0.050990448 | T68: 0.066577015 | U68: 0.044914708 | V68: 0.055134363 | W68: 0.053790603 | X68: 0.076984744 | Y68: 0.059844098 | Z68: 0.068301234 | AA68: 0.054587293 | AC68: =LOOKUP(9.99E+307,D68:AB68) -> 0.054587293 | AD68: =LOOKUP(9.99E+307,D68:AB68,D$4:AB$4) -> 2023 | AE68: =IFERROR(AVERAGE(W68:AB68),"") -> 0.062701594 | AF68: =MAX(0,$B$2-AC68) -> 0.095412707
A69: Georgia | B69: GEO | D69: 0.048525214 | E69: 0.067504334 | F69: 0.070204082 | G69: 0.071327682 | H69: 0.0625 | I69: 0.055770721 | J69: 0.052303863 | K69: 0.039536328 | L69: 0.048306851 | M69: 0.058841796 | N69: 0.061533976 | O69: 0.050416608 | P69: 0.055060101 | Q69: 0.06851613 | R69: 0.077795601 | S69: 0.096085787 | T69: 0.10326514 | U69: 0.095190258 | V69: 0.10324947 | W69: 0.093872232 | X69: 0.10733172 | Y69: 0.14229896 | Z69: 0.10735195 | AA69: 0.077799106 | AC69: =LOOKUP(9.99E+307,D69:AB69) -> 0.077799106 | AD69: =LOOKUP(9.99E+307,D69:AB69,D$4:AB$4) -> 2023 | AE69: =IFERROR(AVERAGE(W69:AB69),"") -> 0.10573079 | AF69: =MAX(0,$B$2-AC69) -> 0.072200894
A70: Germany | B70: DEU | D70: 0.15938912 | E70: 0.16107563 | F70: 0.16244158 | G70: 0.16385138 | H70: 0.16179857 | I70: 0.1638726 | J70: 0.16623154 | K70: 0.17067087 | L70: 0.17089405 | M70: 0.17266411 | N70: 0.17120506 | O70: 0.17610683 | P70: 0.17815664 | Q70: 0.18264946 | R70: 0.18727848 | S70: 0.18995073 | T70: 0.19077759 | U70: 0.19377295 | V70: 0.1949172 | W70: 0.19526081 | X70: 0.19310244 | Y70: 0.19961626 | Z70: 0.20441454 | AA70: 0.19205816 | AC70: =LOOKUP(9.99E+307,D70:AB70) -> 0.19205816 | AD70: =LOOKUP(9.99E+307,D70:AB70,D$4:AB$4) -> 2023 | AE70: =IFERROR(AVERAGE(W70:AB70),"") -> 0.19689044 | AF70: =MAX(0,$B$2-AC70) -> 0
A71: Ghana | B71: GHA | D71: 0.061019425 | E71: 0.061019425 | F71: 0.061019425 | G71: 0.077802806 | H71: 0.069171963 | I71: 0.13634508 | J71: 0.11497241 | K71: 0.097394896 | L71: 0.098777552 | M71: 0.12356558 | N71: 0.11915574 | O71: 0.12074167 | P71: 0.089727478 | Q71: 0.086166973 | R71: 0.067195373 | S71: 0.085578575 | T71: 0.065376787 | U71: 0.09274003 | V71: 0.065605044 | W71: 0.087683659 | X71: 0.080232305 | Y71: 0.077142072 | Z71: 0.074095879 | AA71: 0.10051485 | AC71: =LOOKUP(9.99E+307,D71:AB71) -> 0.10051485 | AD71: =LOOKUP(9.99E+307,D71:AB71,D$4:AB$4) -> 2023 | AE71: =IFERROR(AVERAGE(W71:AB71),"") -> 0.083933753 | AF71: =MAX(0,$B$2-AC71) -> 0.049485149
A72: Greece | B72: GRC | D72: 0.096134195 | E72: 0.10979025 | F72: 0.10869623 | G72: 0.10855977 | H72: 0.099656324 | I72: 0.1143559 | J72: 0.11277622 | K72: 0.11300306 | L72: 0.11343373 | M72: 0.11883022 | N72: 0.12486731 | O72: 0.10958381 | P72: 0.099293327 | Q72: 0.081927519 | R72: 0.087723589 | S72: 0.087053814 | T72: 0.088089218 | U72: 0.088421993 | V72: 0.085910072 | W72: 0.083047123 | X72: 0.085408401 | Y72: 0.094931603 | Z72: 0.086528807 | AA72: 0.085835247 | AC72: =LOOKUP(9.99E+307,D72:AB72) -> 0.085835247 | AD72: =LOOKUP(9.99E+307,D72:AB72,D$4:AB$4) -> 2023 | AE72: =IFERROR(AVERAGE(W72:AB72),"") -> 0.087150236 | AF72: =MAX(0,$B$2-AC72) -> 0.064164753
A73: Grenada | B73: GRD | D73: 0.072555533 | E73: 0.07277 | F73: 0.075790844 | G73: 0.075316281 | H73: 0.10495727 | I73: 0.091110783 | J73: 0.063096952 | K73: 0.072554202 | L73: 0.070374537 | M73: 0.079825726 | N73: 0.07357501 | O73: 0.085355778 | P73: 0.091091919 | Q73: 0.080983715 | R73: 0.072963576 | S73: 0.076600747 | T73: 0.075082064 | U73: 0.083515596 | V73: 0.083340673 | W73: 0.094322023 | X73: 0.069983287 | Y73: 0.069414787 | Z73: 0.062845306 | AA73: 0.072720375 | AC73: =LOOKUP(9.99E+307,D73:AB73) -> 0.072720375 | AD73: =LOOKUP(9.99E+307,D73:AB73,D$4:AB$4) -> 2023 | AE73: =IFERROR(AVERAGE(W73:AB73),"") -> 0.073857156 | AF73: =MAX(0,$B$2-AC73) -> 0.077279625
A74: Guatemala | B74: GTM | D74: 0.14082759 | E74: 0.144004 | F74: 0.14791301 | G74: 0.14208874 | H74: 0.15732374 | I74: 0.1420313 | J74: 0.14587105 | K74: 0.1423033 | L74: 0.15491264 | M74: 0.16026173 | N74: 0.14248166 | O74: 0.13759575 | P74: 0.14318863 | Q74: 0.15827068 | R74: 0.164603 | S74: 0.18107498 | T74: 0.18205315 | U74: 0.17212185 | V74: 0.16674454 | W74: 0.17651402 | X74: 0.15862992 | Y74: 0.19772802 | Z74: 0.1733054 | AA74: 0.1775436 | AC74: =LOOKUP(9.99E+307,D74:AB74) -> 0.1775436 | AD74: =LOOKUP(9.99E+307,D74:AB74,D$4:AB$4) -> 2023 | AE74: =IFERROR(AVERAGE(W74:AB74),"") -> 0.17674419 | AF74: =MAX(0,$B$2-AC74) -> 0
A75: Guinea | B75: GIN | D75: 0.023868253 | E75: 0.024863112 | F75: 0.044430332 | G75: 0.028638539 | H75: 0.01861527 | I75: 0.023775997 | J75: 0.018866088 | K75: 0.027802451 | L75: 0.026759889 | M75: 0.016039821 | N75: 0.017697701 | O75: 0.031844747 | P75: 0.02630034 | Q75: 0.026236229 | R75: 0.030479202 | S75: 0.019800686 | T75: 0.041296558 | U75: 0.034782426 | V75: 0.038791776 | W75: 0.061876755 | X75: 0.045516515 | Y75: 0.04510335 | Z75: 0.051174025 | AA75: 0.051174025 | AC75: =LOOKUP(9.99E+307,D75:AB75) -> 0.051174025 | AD75: =LOOKUP(9.99E+307,D75:AB75,D$4:AB$4) -> 2023 | AE75: =IFERROR(AVERAGE(W75:AB75),"") -> 0.050968934 | AF75: =MAX(0,$B$2-AC75) -> 0.098825974
A76: Guinea-Bissau | B76: GNB | D76: 0.025235052 | E76: 0.025235052 | F76: 0.025235052 | G76: 0.025235052 | H76: 0.025235052 | I76: 0.025235052 | J76: 0.025235052 | K76: 0.025235052 | L76: 0.025235052 | M76: 0.025235052 | N76: 0.025235052 | O76: 0.025235052 | P76: 0.038881714 | Q76: 0.044427767 | R76: 0.025981064 | S76: 0.025010154 | T76: 0.023623126 | U76: 0.027522829 | V76: 0.025942979 | W76: 0.024407406 | X76: 0.047953672 | Y76: 0.045536914 | Z76: 0.048797121 | AA76: 0.042864313 | AC76: =LOOKUP(9.99E+307,D76:AB76) -> 0.042864313 | AD76: =LOOKUP(9.99E+307,D76:AB76,D$4:AB$4) -> 2023 | AE76: =IFERROR(AVERAGE(W76:AB76),"") -> 0.041911885 | AF76: =MAX(0,$B$2-AC76) -> 0.10713569
A77: Guyana | B77: GUY | D77: 0.078165045 | E77: 0.067953935 | F77: 0.075090137 | G77: 0.073576484 | H77: 0.073529549 | I77: 0.062754049 | J77: 0.05696579 | K77: 0.066087761 | L77: 0.070215044 | M77: 0.074141932 | N77: 0.076051526 | O77: 0.086206064 | P77: 0.082260752 | Q77: 0.088188906 | R77: 0.094168501 | S77: 0.10840705 | T77: 0.10054208 | U77: 0.10613539 | V77: 0.10711576 | W77: 0.1032425 | X77: 0.13011635 | Y77: 0.12894853 | Z77: 0.085649328 | AA77: 0.073120976 | AC77: =LOOKUP(9.99E+307,D77:AB77) -> 0.073120976 | AD77: =LOOKUP(9.99E+307,D77:AB77,D$4:AB$4) -> 2023 | AE77: =IFERROR(AVERAGE(W77:AB77),"") -> 0.10421554 | AF77: =MAX(0,$B$2-AC77) -> 0.076879024
A78: Haiti | B78: HTI | D78: 0.13943684 | E78: 0.11909204 | F78: 0.073620429 | G78: 0.066061697 | H78: 0.079492502 | I78: 0.066687546 | J78: 0.02994277 | K78: 0.07113584 | L78: 0.074259653 | M78: 0.067716474 | N78: 0.064308343 | O78: 0.029842613 | P78: 0.027839146 | Q78: 0.029984677 | R78: 0.032014871 | S78: 0.044000373 | T78: 0.050224214 | U78: 0.045437198 | V78: 0.046750169 | W78: 0.042496586 | X78: 0.048419085 | Y78: 0.043947258 | Z78: 0.041084309 | AA78: 0.045637708 | AC78: =LOOKUP(9.99E+307,D78:AB78) -> 0.045637708 | AD78: =LOOKUP(9.99E+307,D78:AB78,D$4:AB$4) -> 2023 | AE78: =IFERROR(AVERAGE(W78:AB78),"") -> 0.044316989 | AF78: =MAX(0,$B$2-AC78) -> 0.10436229
... A84: Iran (Islamic Republic of) | B84: IRN | D84: 0.10952403 | E84: 0.11870626 | F84: 0.0956565 | G84: 0.10212297 | H84: 0.10162407 | I84: 0.090055866 | J84: 0.096129694 | K84: 0.11534695 | L84: 0.094751682 | M84: 0.12377065 | N84: 0.12523605 | O84: 0.12023728 | P84: 0.15606089 | Q84: 0.16342754 | R84: 0.23143847 | S84: 0.2584054 | T84: 0.2421534 | U84: 0.24504799 | V84: 0.20785601 | W84: 0.19447935 | X84: 0.19029573 | Y84: 0.16051506 | Z84: 0.19111851 | AA84: 0.19061493 | AC84: =LOOKUP(9.99E+307,D84:AB84) -> 0.19061493 | AD84: =LOOKUP(9.99E+307,D84:AB84,D$4:AB$4) -> 2023 | AE84: =IFERROR(AVERAGE(W84:AB84),"") -> 0.18540472 | AF84: =MAX(0,$B$2-AC84) -> 0
A85: Iraq | B85: IRQ | G85: 0.03131005 | H85: 0.029806504 | I85: 0.031964197 | J85: 0.030470798 | K85: 0.046332202 | L85: 0.041442576 | M85: 0.04733726 | N85: 0.048027453 | O85: 0.04798624 | P85: 0.023523643 | Q85: 0.023758931 | R85: 0.023695984 | S85: 0.016812644 | T85: 0.059849253 | U85: 0.047749205 | V85: 0.064310226 | W85: 0.059936714 | X85: 0.061605988 | Y85: 0.069839292 | Z85: 0.05841526 | AA85: 0.06184782 | AC85: =LOOKUP(9.99E+307,D85:AB85) -> 0.06184782 | AD85: =LOOKUP(9.99E+307,D85:AB85,D$4:AB$4) -> 2023 | AE85: =IFERROR(AVERAGE(W85:AB85),"") -> 0.062329015 | AF85: =MAX(0,$B$2-AC85) -> 0.08815218
A86: Ireland | B86: IRL | D86: 0.14958854 | E86: 0.15585073 | F86: 0.16030506 | G86: 0.16897215 | H86: 0.17359148 | I86: 0.18252867 | J86: 0.1742926 | K86: 0.17357664 | L86: 0.17418354 | M86: 0.1730188 | N86: 0.12353869 | O86: 0.16179743 | P86: 0.17926008 | Q86: 0.17917908 | R86: 0.18022366 | S86: 0.1812147 | T86: 0.19262596 | U86: 0.19867968 | V86: 0.20052168 | W86: 0.20469543 | X86: 0.20296591 | Y86: 0.20970272 | Z86: 0.22366793 | AA86: 0.22157461 | AC86: =LOOKUP(9.99E+307,D86:AB86) -> 0.22157461 | AD86: =LOOKUP(9.99E+307,D86:AB86,D$4:AB$4) -> 2023 | AE86: =IFERROR(AVERAGE(W86:AB86),"") -> 0.21252132 | AF86: =MAX(0,$B$2-AC86) -> 0
A87: Israel | B87: ISR | D87: 0.094096451 | E87: 0.09333169 | F87: 0.086858454 | G87: 0.092341356 | H87: 0.095808048 | I87: 0.095716162 | J87: 0.09850812 | K87: 0.098824997 | L87: 0.099371214 | M87: 0.09999876 | N87: 0.10652871 | O87: 0.106494 | P87: 0.10802816 | Q87: 0.10911878 | R87: 0.11403407 | S87: 0.11648652 | T87: 0.11651914 | U87: 0.1176448 | V87: 0.11756129 | W87: 0.11899981 | X87: 0.11551647 | Y87: 0.13782756 | Z87: 0.11780927 | AA87: 0.11565848 | AC87: =LOOKUP(9.99E+307,D87:AB87) -> 0.11565848 | AD87: =LOOKUP(9.99E+307,D87:AB87,D$4:AB$4) -> 2023 | AE87: =IFERROR(AVERAGE(W87:AB87),"") -> 0.12116232 | AF87: =MAX(0,$B$2-AC87) -> 0.034341516
A88: Italy | B88: ITA | D88: 0.11822707 | E88: 0.12208769 | F88: 0.12634198 | G88: 0.12521319 | H88: 0.13294643 | I88: 0.13683554 | J88: 0.13728821 | K88: 0.13471567 | L88: 0.13829327 | M88: 0.13670728 | N88: 0.13988534 | O88: 0.1371105 | P88: 0.13134037 | Q88: 0.12982636 | R88: 0.130899 | S88: 0.13031324 | T88: 0.13164087 | U88: 0.13062402 | V88: 0.13140237 | W88: 0.13031165 | X88: 0.12771646 | Y88: 0.12345703 | Z88: 0.11886859 | AA88: 0.11435616 | AC88: =LOOKUP(9.99E+307,D88:AB88) -> 0.11435616 | AD88: =LOOKUP(9.99E+307,D88:AB88,D$4:AB$4) -> 2023 | AE88: =IFERROR(AVERAGE(W88:AB88),"") -> 0.12294198 | AF88: =MAX(0,$B$2-AC88) -> 0.035643835
A89: Jamaica | B89: JAM | D89: 0.11841487 | E89: 0.082009611 | F89: 0.086676102 | G89: 0.06137599 | H89: 0.076452746 | I89: 0.074342041 | J89: 0.062574463 | K89: 0.082274962 | L89: 0.083576364 | M89: 0.074510446 | N89: 0.090329323 | O89: 0.095287666 | P89: 0.091577921 | Q89: 0.10769291 | R89: 0.11251961 | S89: 0.1282022 | T89: 0.12683866 | U89: 0.13954786 | V89: 0.13039397 | W89: 0.13320455 | X89: 0.13988929 | Y89: 0.16177647 | Z89: 0.1896324 | AA89: 0.15855964 | AC89: =LOOKUP(9.99E+307,D89:AB89) -> 0.15855964 | AD89: =LOOKUP(9.99E+307,D89:AB89,D$4:AB$4) -> 2023 | AE89: =IFERROR(AVERAGE(W89:AB89),"") -> 0.15661247 | AF89: =MAX(0,$B$2-AC89) -> 0
A90: Japan | B90: JPN | D90: 0.15068058 | E90: 0.15945433 | F90: 0.16061543 | G90: 0.16358208 | H90: 0.17195955 | I90: 0.17754881 | J90: 0.17866653 | K90: 0.18227022 | L90: 0.18098146 | M90: 0.18057035 | N90: 0.18932966 | O90: 0.21692654 | P90: 0.22224499 | Q90: 0.2221854 | R90: 0.22571625 | S90: 0.23150288 | T90: 0.23176727 | U90: 0.2446199 | V90: 0.2448889 | W90: 0.2469809 | X90: 0.21954464 | Y90: 0.24535604 | Z90: 0.25365555 | AA90: 0.23300526 | AC90: =LOOKUP(9.99E+307,D90:AB90) -> 0.23300526 | AD90: =LOOKUP(9.99E+307,D90:AB90,D$4:AB$4) -> 2023 | AE90: =IFERROR(AVERAGE(W90:AB90),"") -> 0.23970848 | AF90: =MAX(0,$B$2-AC90) -> 0
A91: Jordan | B91: JOR | D91: 0.12689116 | E91: 0.136148 | F91: 0.133821 | G91: 0.1137037 | H91: 0.094005899 | I91: 0.11786743 | J91: 0.11360124 | K91: 0.12519184 | L91: 0.15125435 | M91: 0.17915905 | N91: 0.17020586 | O91: 0.15417559 | P91: 0.13670978 | Q91: 0.13126521 | R91: 0.13064031 | S91: 0.12219738 | T91: 0.1123799 | U91: 0.1109924 | V91: 0.099767199 | W91: 0.10080314 | X91: 0.10765898 | Y91: 0.10347293 | Z91: 0.10466299 | AA91: 0.10501314 | AC91: =LOOKUP(9.99E+307,D91:AB91) -> 0.10501314 | AD91: =LOOKUP(9.99E+307,D91:AB91,D$4:AB$4) -> 2023 | AE91: =IFERROR(AVERAGE(W91:AB91),"") -> 0.10432224 | AF91: =MAX(0,$B$2-AC91) -> 0.044986858
A92: Kazakhstan | B92: KAZ | D92: 0.092461405 | E92: 0.084094734 | F92: 0.09420599 | G92: 0.095652113 | H92: 0.10941607 | I92: 0.11530329 | J92: 0.11720528 | K92: 0.07576026 | L92: 0.084132977 | M92: 0.11363523 | N92: 0.082052278 | O92: 0.086768656 | P92: 0.094463635 | Q92: 0.09324193 | R92: 0.1003429 | S92: 0.08394762 | T92: 0.094843941 | U92: 0.078573442 | V92: 0.090960388 | W92: 0.082512455 | X92: 0.10061134 | Y92: 0.11617583 | Z92: 0.10601153 | AA92: 0.10700548 | AC92: =LOOKUP(9.99E+307,D92:AB92) -> 0.10700548 | AD92: =LOOKUP(9.99E+307,D92:AB92,D$4:AB$4) -> 2023 | AE92: =IFERROR(AVERAGE(W92:AB92),"") -> 0.10246333 | AF92: =MAX(0,$B$2-AC92) -> 0.042994518
A93: Kenya | B93: KEN | C93: yes | D93: 0.070889826 | E93: 0.070889826 | F93: 0.070889826 | G93: 0.070224299 | H93: 0.069893775 | I93: 0.068923879 | J93: 0.068128095 | K93: 0.070393863 | L93: 0.07170805 | M93: 0.072007761 | N93: 0.072441263 | O93: 0.07981091 | P93: 0.073592792 | Q93: 0.071497207 | R93: 0.078450079 | S93: 0.080744801 | T93: 0.080254345 | U93: 0.067924047 | V93: 0.072187452 | W93: 0.082272358 | X93: 0.089104605 | Y93: 0.092824087 | Z93: 0.086511555 | AA93: 0.086511555 | AC93: =LOOKUP(9.99E+307,D93:AB93) -> 0.086511555 | AD93: =LOOKUP(9.99E+307,D93:AB93,D$4:AB$4) -> 2023 | AE93: =IFERROR(AVERAGE(W93:AB93),"") -> 0.087444832 | AF93: =MAX(0,$B$2-AC93) -> 0.063488445
A94: Kiribati | B94: KIR | D94: 0.11406236 | E94: 0.1140622 | F94: 0.1140624 | G94: 0.1140624 | H94: 0.11406259 | I94: 0.11406224 | J94: 0.1140626 | K94: 0.11375 | L94: 0.12690647 | M94: 0.10902985 | N94: 0.10445255 | O94: 0.092922077 | P94: 0.083630953 | Q94: 0.091595097 | R94: 0.072800002 | S94: 0.066896553 | T94: 0.077818184 | U94: 0.09029851 | V94: 0.080882349 | W94: 0.0852071 | X94: 0.092987804 | Y94: 0.10564263 | Z94: 0.097087288 | AA94: 0.090027809 | AC94: =LOOKUP(9.99E+307,D94:AB94) -> 0.090027809 | AD94: =LOOKUP(9.99E+307,D94:AB94,D$4:AB$4) -> 2023 | AE94: =IFERROR(AVERAGE(W94:AB94),"") -> 0.094190527 | AF94: =MAX(0,$B$2-AC94) -> 0.059972191
A95: Kuwait | B95: KWT | D95: 0.054496169 | E95: 0.061746616 | F95: 0.056968455 | G95: 0.056350951 | H95: 0.051476212 | I95: 0.053828998 | J95: 0.043487558 | K95: 0.048705583 | L95: 0.03692637 | M95: 0.051779451 | N95: 0.049814396 | O95: 0.049837608 | P95: 0.051189165 | Q95: 0.054484105 | R95: 0.054922309 | S95: 0.064766784 | T95: 0.074780417 | U95: 0.077408123 | V95: 0.090121756 | W95: 0.091639633 | X95: 0.086557484 | Y95: 0.099418945 | Z95: 0.094005079 | AA95: 0.090218067 | AC95: =LOOKUP(9.99E+307,D95:AB95) -> 0.090218067 | AD95: =LOOKUP(9.99E+307,D95:AB95,D$4:AB$4) -> 2023 | AE95: =IFERROR(AVERAGE(W95:AB95),"") -> 0.092367842 | AF95: =MAX(0,$B$2-AC95) -> 0.059781933
A96: Kyrgyzstan | B96: KGZ | D96: 0.070640063 | E96: 0.071314993 | F96: 0.075632911 | G96: 0.080725298 | H96: 0.082125959 | I96: 0.13069867 | J96: 0.14458958 | K96: 0.10425051 | L96: 0.10385349 | M96: 0.10696233 | N96: 0.09203639 | O96: 0.098833132 | P96: 0.10400711 | Q96: 0.10346405 | R96: 0.071389055 | S96: 0.071201859 | T96: 0.064158077 | U96: 0.063416133 | V96: 0.073343763 | W96: 0.07093936 | X96: 0.069168787 | Y96: 0.09223444 | Z96: 0.075484381 | AA96: 0.073012633 | AC96: =LOOKUP(9.99E+307,D96:AB96) -> 0.073012633 | AD96: =LOOKUP(9.99E+307,D96:AB96,D$4:AB$4) -> 2023 | AE96: =IFERROR(AVERAGE(W96:AB96),"") -> 0.07616792 | AF96: =MAX(0,$B$2-AC96) -> 0.076987367
A97: Lao People's Democratic Republic | B97: LAO | D97: 0.061991444 | E97: 0.070550289 | F97: 0.061298442 | G97: 0.06834805 | H97: 0.05853271 | I97: 0.059141712 | J97: 0.043634644 | K97: 0.039029949 | L97: 0.031974592 | M97: 0.057037659 | N97: 0.026945555 | O97: 0.018174868 | P97: 0.017665906 | Q97: 0.029400711 | R97: 0.027363534 | S97: 0.033508019 | T97: 0.036279941 | U97: 0.040769591 | V97: 0.041973305 | W97: 0.05163249 | X97: 0.043148298 | Y97: 0.045797653 | Z97: 0.042535505 | AA97: 0.032051065 | AC97: =LOOKUP(9.99E+307,D97:AB97) -> 0.032051065 | AD97: =LOOKUP(9.99E+307,D97:AB97,D$4:AB$4) -> 2023 | AE97: =IFERROR(AVERAGE(W97:AB97),"") -> 0.043033002 | AF97: =MAX(0,$B$2-AC97) -> 0.11794893
A98: Latvia | B98: LVA | D98: 0.074288907 | E98: 0.081107721 | F98: 0.081623735 | G98: 0.080821371 | H98: 0.099400692 | I98: 0.093369303 | J98: 0.096225777 | K98: 0.097152071 | L98: 0.087995653 | M98: 0.080612297 | N98: 0.079929318 | O98: 0.085753937 | P98: 0.084060354 | Q98: 0.084206839 | R98: 0.083754768 | S98: 0.085845499 | T98: 0.091327562 | U98: 0.089402704 | V98: 0.094036093 | W98: 0.10359062 | X98: 0.10759473 | Y98: 0.14021643 | Z98: 0.11862193 | AA98: 0.099123182 | AC98: =LOOKUP(9.99E+307,D98:AB98) -> 0.099123182 | AD98: =LOOKUP(9.99E+307,D98:AB98,D$4:AB$4) -> 2023 | AE98: =IFERROR(AVERAGE(W98:AB98),"") -> 0.11382938 | AF98: =MAX(0,$B$2-AC98) -> 0.050876818
A99: Lebanon | B99: LBN | D99: 0.075372148 | E99: 0.088697367 | F99: 0.08291873 | G99: 0.080704136 | H99: 0.08917963 | I99: 0.092279873 | J99: 0.09829339 | K99: 0.099821758 | L99: 0.089598198 | M99: 0.083423948 | N99: 0.10285933 | O99: 0.12403281 | P99: 0.10079384 | Q99: 0.10792888 | R99: 0.1238764 | S99: 0.12660043 | T99: 0.13169962 | U99: 0.12027192 | V99: 0.11667254 | W99: 0.13683805 | X99: 0.14470898 | Y99: 0.11565791 | Z99: 0.12464161 | AA99: 0.15905529 | AC99: =LOOKUP(9.99E+307,D99:AB99) -> 0.15905529 | AD99: =LOOKUP(9.99E+307,D99:AB99,D$4:AB$4) -> 2023 | AE99: =IFERROR(AVERAGE(W99:AB99),"") -> 0.13618037 | AF99: =MAX(0,$B$2-AC99) -> 0
A100: Lesotho | B100: LSO | C100: yes | D100: 0.074074073 | E100: 0.087013416 | F100: 0.077236958 | G100: 0.079082699 | H100: 0.082549896 | I100: 0.059969253 | J100: 0.070538449 | K100: 0.096424684 | L100: 0.080810175 | M100: 0.073227449 | N100: 0.071979928 | O100: 0.081988745 | P100: 0.096743116 | Q100: 0.10487746 | R100: 0.11592402 | S100: 0.10860278 | T100: 0.10336077 | U100: 0.11972834 | V100: 0.1077791 | W100: 0.12610546 | X100: 0.089495935 | Y100: 0.081524248 | Z100: 0.12883148 | AA100: 0.11833222 | AC100: =LOOKUP(9.99E+307,D100:AB100) -> 0.11833222 | AD100: =LOOKUP(9.99E+307,D100:AB100,D$4:AB$4) -> 2023 | AE100: =IFERROR(AVERAGE(W100:AB100),"") -> 0.10885787 | AF100: =MAX(0,$B$2-AC100) -> 0.031667776
A101: Liberia | B101: LBR | C101: yes | D101: 0.042549176 | E101: 0.042549176 | F101: 0.042549176 | G101: 0.042549176 | H101: 0.042549176 | I101: 0.042549176 | J101: 0.042549176 | K101: 0.042549176 | L101: 0.042549176 | M101: 0.050466022 | N101: 0.050466022 | O101: 0.050466022 | P101: 0.050466022 | Q101: 0.011572529 | R101: 0.024611893 | S101: 0.032433903 | T101: 0.038970165 | U101: 0.039551458 | V101: 0.051662292 | W101: 0.041983461 | X101: 0.037481868 | Y101: 0.037302012 | Z101: 0.047911715 | AA101: 0.047911715 | AC101: =LOOKUP(9.99E+307,D101:AB101) -> 0.047911715 | AD101: =LOOKUP(9.99E+307,D101:AB101,D$4:AB$4) -> 2023 | AE101: =IFERROR(AVERAGE(W101:AB101),"") -> 0.042518155 | AF101: =MAX(0,$B$2-AC101) -> 0.10208828
A102: Libya | B102: LBY | D102: 0.060398207 | E102: 0.057829866 | F102: 0.077564321 | G102: 0.063085999 | H102: 0.054211988 | I102: 0.057806249 | J102: 0.05275487 | K102: 0.048129821 | L102: 0.037007906 | M102: 0.040890393 | N102: 0.043341274 | O102: 0.064195838 | P102: 0.074125748 | Q102: 0.04971242 | R102: 0.057134776 | S102: 0.075143166 | T102: 0.09908102 | U102: 0.088626747 | V102: 0.092703323 | W102: 0.083604937 | X102: 0.097431974 | Y102: 0.069114699 | Z102: 0.050627132 | AA102: 0.095714731 | AC102: =LOOKUP(9.99E+307,D102:AB102) -> 0.095714731 | AD102: =LOOKUP(9.99E+307,D102:AB102,D$4:AB$4) -> 2023 | AE102: =IFERROR(AVERAGE(W102:AB102),"") -> 0.079298695 | AF102: =MAX(0,$B$2-AC102) -> 0.054285269
A103: Liechtenstein | B103: LIE | Q103: 0.14194085 | R103: 0.15122819 | S103: 0.15558143 | T103: 0.15646569 | U103: 0.15017219 | V103: 0.14911199 | W103: 0.15295453 | X103: 0.13269869 | Y103: 0.15923554 | Z103: 0.15896936 | AA103: 0.15853006 | AC103: =LOOKUP(9.99E+307,D103:AB103) -> 0.15853006 | AD103: =LOOKUP(9.99E+307,D103:AB103,D$4:AB$4) -> 2023 | AE103: =IFERROR(AVERAGE(W103:AB103),"") -> 0.15247764 | AF103: =MAX(0,$B$2-AC103) -> 0
A104: Lithuania | B104: LTU | D104: 0.10571035 | E104: 0.11367867 | F104: 0.12712833 | G104: 0.13675911 | H104: 0.1013124 | I104: 0.10049972 | J104: 0.10622211 | K104: 0.10752552 | L104: 0.1167388 | M104: 0.11777744 | N104: 0.11411454 | O104: 0.11479018 | P104: 0.11480044 | Q104: 0.11297273 | R104: 0.1183361 | S104: 0.12154667 | T104: 0.12685909 | U104: 0.12643123 | V104: 0.1263407 | W104: 0.13048165 | X104: 0.12030653 | Y104: 0.13964344 | Z104: 0.13057192 | AA104: 0.12733354 | AC104: =LOOKUP(9.99E+307,D104:AB104) -> 0.12733354 | AD104: =LOOKUP(9.99E+307,D104:AB104,D$4:AB$4) -> 2023 | AE104: =IFERROR(AVERAGE(W104:AB104),"") -> 0.12966742 | AF104: =MAX(0,$B$2-AC104) -> 0.022666464
A105: Luxembourg | B105: LUX | D105: 0.12987872 | E105: 0.14059653 | F105: 0.13589751 | G105: 0.1346736 | H105: 0.14085335 | I105: 0.13798571 | J105: 0.1411739 | K105: 0.14061712 | L105: 0.14401401 | M105: 0.14116132 | N105: 0.13624106 | O105: 0.11964 | P105: 0.10589256 | Q105: 0.10647374 | R105: 0.10853743 | S105: 0.10634259 | T105: 0.10691935 | U105: 0.10547755 | V105: 0.10582692 | W105: 0.10898368 | X105: 0.10710371 | Y105: 0.11511127 | Z105: 0.11023471 | AA105: 0.10441708 | AB105: 0.10916821 | AC105: =LOOKUP(9.99E+307,D105:AB105) -> 0.10916821 | AD105: =LOOKUP(9.99E+307,D105:AB105,D$4:AB$4) -> 2024 | AE105: =IFERROR(AVERAGE(W105:AB105),"") -> 0.10916977 | AF105: =MAX(0,$B$2-AC105) -> 0.040831795
A106: Madagascar | B106: MDG | C106: yes | D106: 0.12027845 | E106: 0.11971967 | F106: 0.14041333 | G106: 0.13117822 | H106: 0.10014785 | I106: 0.10540405 | J106: 0.10247689 | K106: 0.11838323 | L106: 0.089767837 | M106: 0.10439493 | N106: 0.15209797 | O106: 0.13936786 | P106: 0.12936996 | Q106: 0.10268065 | R106: 0.1392415 | S106: 0.1527428 | T106: 0.17510868 | U106: 0.15032087 | V106: 0.10429566 | W106: 0.044441509 | X106: 0.042181768 | Y106: 0.053777943 | Z106: 0.055134177 | AA106: 0.055134177 | AC106: =LOOKUP(9.99E+307,D106:AB106) -> 0.055134177 | AD106: =LOOKUP(9.99E+307,D106:AB106,D$4:AB$4) -> 2023 | AE106: =IFERROR(AVERAGE(W106:AB106),"") -> 0.050133915 | AF106: =MAX(0,$B$2-AC106) -> 0.094865823
A107: Malawi | B107: MWI | C107: yes | D107: 0.070426035 | E107: 0.070426035 | F107: 0.070426035 | G107: 0.076335125 | H107: 0.04995151 | I107: 0.060378303 | J107: 0.052927179 | K107: 0.035445971 | L107: 0.066249685 | M107: 0.052324381 | N107: 0.057746429 | O107: 0.067799969 | P107: 0.050962386 | Q107: 0.071556726 | R107: 0.08580905 | S107: 0.0972892 | T107: 0.096779671 | U107: 0.081896133 | V107: 0.087133112 | W107: 0.079386005 | X107: 0.068733201 | Y107: 0.05756381 | Z107: 0.032871101 | AA107: 0.032871101 | AC107: =LOOKUP(9.99E+307,D107:AB107) -> 0.032871101 | AD107: =LOOKUP(9.99E+307,D107:AB107,D$4:AB$4) -> 2023 | AE107: =IFERROR(AVERAGE(W107:AB107),"") -> 0.054285044 | AF107: =MAX(0,$B$2-AC107) -> 0.1171289
A108: Malaysia | B108: MYS | D108: 0.045772691 | E108: 0.047883205 | F108: 0.050352817 | G108: 0.054110765 | H108: 0.056283822 | I108: 0.055539026 | J108: 0.065490737 | K108: 0.062760091 | L108: 0.059335213 | M108: 0.058650346 | N108: 0.063113642 | O108: 0.065151897 | P108: 0.065421767 | Q108: 0.068163185 | R108: 0.078240251 | S108: 0.082299528 | T108: 0.082628813 | U108: 0.087201471 | V108: 0.084516687 | W108: 0.085242796 | X108: 0.086899538 | Y108: 0.10056885 | Z108: 0.080028305 | AA108: 0.079430184 | AC108: =LOOKUP(9.99E+307,D108:AB108) -> 0.079430184 | AD108: =LOOKUP(9.99E+307,D108:AB108,D$4:AB$4) -> 2023 | AE108: =IFERROR(AVERAGE(W108:AB108),"") -> 0.086433934 | AF108: =MAX(0,$B$2-AC108) -> 0.070569816
A109: Maldives | B109: MDV | D109: 0.088284674 | E109: 0.090315933 | F109: 0.086192598 | G109: 0.081447077 | H109: 0.096030693 | I109: 0.07651948 | J109: 0.084460802 | K109: 0.11245549 | L109: 0.17986689 | M109: 0.15744858 | N109: 0.13543034 | O109: 0.11762476 | P109: 0.14140152 | Q109: 0.15930778 | R109: 0.1686293 | S109: 0.18454266 | T109: 0.19748093 | U109: 0.21471615 | V109: 0.17679087 | W109: 0.17853943 | X109: 0.18172747 | Y109: 0.14486053 | Z109: 0.13277081 | AA109: 0.15566577 | AC109: =LOOKUP(9.99E+307,D109:AB109) -> 0.15566577 | AD109: =LOOKUP(9.99E+307,D109:AB109,D$4:AB$4) -> 2023 | AE109: =IFERROR(AVERAGE(W109:AB109),"") -> 0.1587128 | AF109: =MAX(0,$B$2-AC109) -> 0
A110: Mali | B110: MLI | D110: 0.066688929 | E110: 0.057465625 | F110: 0.055660768 | G110: 0.06785975 | H110: 0.073005457 | I110: 0.064582086 | J110: 0.055458898 | K110: 0.046381097 | L110: 0.03794112 | M110: 0.029260635 | N110: 0.033015409 | O110: 0.029412172 | P110: 0.026625431 | Q110: 0.04128911 | R110: 0.044547329 | S110: 0.043903341 | T110: 0.054306331 | U110: 0.051372628 | V110: 0.056687856 | W110: 0.048350143 | X110: 0.053712625 | Y110: 0.050374312 | Z110: 0.056016617 | AA110: 0.054313564 | AC110: =LOOKUP(9.99E+307,D110:AB110) -> 0.054313564 | AD110: =LOOKUP(9.99E+307,D110:AB110,D$4:AB$4) -> 2023 | AE110: =IFERROR(AVERAGE(W110:AB110),"") -> 0.052553452 | AF110: =MAX(0,$B$2-AC110) -> 0.095686436
A111: Malta | B111: MLT | D111: 0.11782387 | E111: 0.11582794 | F111: 0.13113525 | G111: 0.1225456 | H111: 0.1336781 | I111: 0.14107656 | J111: 0.14261341 | K111: 0.13285126 | L111: 0.12028014 | M111: 0.12445888 | N111: 0.12730976 | O111: 0.12918922 | P111: 0.12989096 | Q111: 0.13995458 | R111: 0.13833277 | S111: 0.13986868 | T111: 0.15464032 | U111: 0.1598813 | V111: 0.14936394 | W111: 0.15936242 | X111: 0.15622097 | Y111: 0.16264776 | Z111: 0.16157269 | AA111: 0.15905086 | AC111: =LOOKUP(9.99E+307,D111:AB111) -> 0.15905086 | AD111: =LOOKUP(9.99E+307,D111:AB111,D$4:AB$4) -> 2023 | AE111: =IFERROR(AVERAGE(W111:AB111),"") -> 0.15977094 | AF111: =MAX(0,$B$2-AC111) -> 0
A112: Marshall Islands | B112: MHL | D112: 0.14493987 | E112: 0.10927813 | F112: 0.13726377 | G112: 0.15990213 | H112: 0.10680841 | I112: 0.064642143 | J112: 0.1061154 | K112: 0.095631189 | L112: 0.093922205 | M112: 0.098549681 | N112: 0.081760826 | O112: 0.093036795 | P112: 0.10019768 | Q112: 0.11063281 | R112: 0.10184946 | S112: 0.10757787 | T112: 0.1136909 | U112: 0.076857114 | V112: 0.10766292 | W112: 0.10150704 | X112: 0.077510929 | Y112: 0.074504628 | Z112: 0.086013136 | AA112: 0.15237169 | AC112: =LOOKUP(9.99E+307,D112:AB112) -> 0.15237169 | AD112: =LOOKUP(9.99E+307,D112:AB112,D$4:AB$4) -> 2023 | AE112: =IFERROR(AVERAGE(W112:AB112),"") -> 0.098381486 | AF112: =MAX(0,$B$2-AC112) -> 0
A113: Mauritania | B113: MRT | D113: 0.025142512 | E113: 0.024219305 | F113: 0.03582401 | G113: 0.02606683 | H113: 0.029611554 | I113: 0.038442106 | J113: 0.035596781 | K113: 0.038856704 | L113: 0.044803453 | M113: 0.044762416 | N113: 0.042230482 | O113: 0.04400929 | P113: 0.041669855 | Q113: 0.053850031 | R113: 0.052406993 | S113: 0.05530211 | T113: 0.057563295 | U113: 0.060655999 | V113: 0.047971277 | W113: 0.061779199 | X113: 0.05416491 | Y113: 0.072040954 | Z113: 0.059432788 | AA113: 0.059432788 | AC113: =LOOKUP(9.99E+307,D113:AB113) -> 0.059432788 | AD113: =LOOKUP(9.99E+307,D113:AB113,D$4:AB$4) -> 2023 | AE113: =IFERROR(AVERAGE(W113:AB113),"") -> 0.061370128 | AF113: =MAX(0,$B$2-AC113) -> 0.090567212
A114: Mauritius | B114: MUS | D114: 0.06879271 | E114: 0.07015892 | F114: 0.072455525 | G114: 0.071191735 | H114: 0.079944196 | I114: 0.073627076 | J114: 0.07302484 | K114: 0.068428731 | L114: 0.061225448 | M114: 0.062817368 | N114: 0.082958803 | O114: 0.073622041 | P114: 0.083190432 | Q114: 0.08007184 | R114: 0.10528387 | S114: 0.094584189 | T114: 0.10202269 | U114: 0.10204333 | V114: 0.1020625 | W114: 0.090032053 | X114: 0.089929619 | Y114: 0.10898217 | Z114: 0.086092091 | AA114: 0.082431126 | AC114: =LOOKUP(9.99E+307,D114:AB114) -> 0.082431126 | AD114: =LOOKUP(9.99E+307,D114:AB114,D$4:AB$4) -> 2023 | AE114: =IFERROR(AVERAGE(W114:AB114),"") -> 0.091493412 | AF114: =MAX(0,$B$2-AC114) -> 0.067568874
...

Sheet Spending by Category
A1: Government spending by category, % of total outlays (IMF Government Finance Statistics, COFOG), 46 countries, 2005-2025
A2: One row per country-year with data. Health = sum of its sub-items (formula). Total should be 100%. WHO Health Share = the GHED figure for the same year from the 'All GHED Countries' sheet, for comparison.
A4: Country | B4: ISO3 | C4: MOU 15 | D4: Year | E4: Coverage | F4: General Public Services (excl. Interest) | G4: Interest on Public Debt | H4: Defence | I4: Public Order and Safety | J4: Economic Affairs | K4: Environmental Protection | L4: Housing and Community Amenities | M4: Health | N4: Recreation, Culture and Religion | O4: Education | P4: Social Protection | Q4: Unclassified | R4: Total | S4: Medical Products | T4: Outpatient Services | U4: Hospital Services | V4: Public Health Services | W4: Health R&D | X4: Other Health | Y4: Health (No Breakdown) | Z4: WHO Health Share (GHED)
A5: Angola | B5: AGO | D5: 2014 | E5: Central government (budgetary) | F5: 0.21134662 | G5: 0.024892133 | H5: 0.11372186 | I5: 0.086392824 | J5: 0.19236299 | K5: 0.0062704669 | L5: 0.093350513 | M5: =SUM(S5:Y5) -> 0.046716281 | N5: 0.012095067 | O5: 0.068522597 | P5: 0.14432865 | R5: =SUM(F5:Q5) -> 1 | S5: 0.00073846322 | T5: 0.00087491207 | U5: 0.034201646 | V5: 0.01090126 | W5: 0 | X5: 0 | Z5: =IFERROR(IF(INDEX('All GHED Countries'!$D$5:$AB$199,MATCH($B5,'All GHED Countries'!$B$5:$B$199,0),MATCH($D5,'All GHED Countries'!$D$4:$AB$4,0))="","",INDEX('All GHED Countries'!$D$5:$AB$199,MATCH($B5,'All GHED Countries'!$B$5:$B$199,0),MATCH($D5,'All GHED Countries'!$D$4:$AB$4,0))),"") -> 0.036156802
A6: Angola | B6: AGO | D6: 2015 | E6: Central government (budgetary) | F6: 0.13209355 | G6: 0.071528649 | H6: 0.22712454 | I6: 0.04583937 | J6: 0.12396567 | K6: 0.0061437895 | L6: 0.050239753 | M6: =SUM(S6:Y6) -> 0.055617432 | N6: 0.0098367568 | O6: 0.12100889 | P6: 0.15660161 | R6: =SUM(F6:Q6) -> 1 | S6: 0.0010024234 | T6: 0.00074248199 | U6: 0.037021308 | V6: 0.016851218 | W6: 0 | X6: 0 | Z6: =IFERROR(IF(INDEX('All GHED Countries'!$D$5:$AB$199,MATCH($B6,'All GHED Countries'!$B$5:$B$199,0),MATCH($D6,'All GHED Countries'!$D$4:$AB$4,0))="","",INDEX('All GHED Countries'!$D$5:$AB$199,MATCH($B6,'All GHED Countries'!$B$5:$B$199,0),MATCH($D6,'All GHED Countries'!$D$4:$AB$4,0))),"") -> 0.045626254
A7: Angola | B7: AGO | D7: 2016 | E7: Central government (budgetary) | F7: 0.14559431 | G7: 0.10094723 | H7: 0.14380666 | I7: 0.13245054 | J7: 0.16789042 | K7: 0.00053985518 | L7: 0.034355169 | M7: =SUM(S7:Y7) -> 0.055828603 | N7: 0.0050662721 | O7: 0.10821701 | P7: 0.10530394 | R7: =SUM(F7:Q7) -> 1 | S7: 0.00085143784 | T7: 0.00090584734 | U7: 0.034584982 | V7: 0.019486336 | W7: 0 | X7: 0 | Z7: =IFERROR(IF(INDEX('All GHED Countries'!$D$5:$AB$199,MATCH($B7,'All GHED Countries'!$B$5:$B$199,0),MATCH($D7,'All GHED Countries'!$D$4:$AB$4,0))="","",INDEX('All GHED Countries'!$D$5:$AB$199,MATCH($B7,'All GHED Countries'!$B$5:$B$199,0),MATCH($D7,'All GHED Countries'!$D$4:$AB$4,0))),"") -> 0.054326968
A8: Angola | B8: AGO | D8: 2017 | E8: Central government (budgetary) | F8: 0.14598649 | G8: 0.11692908 | H8: 0.13153489 | I8: 0.10753201 | J8: 0.19782268 | K8: 0.005633868 | L8: 0.063749089 | M8: =SUM(S8:Y8) -> 0.044905958 | N8: 0.0078327547 | O8: 0.087602969 | P8: 0.09047021 | R8: =SUM(F8:Q8) -> 1 | S8: 0.0020233046 | T8: 5.2756844e-05 | U8: 0.029246367 | V8: 0.01358353 | W8: 0 | X8: 0 | Z8: =IFERROR(IF(INDEX('All GHED Countries'!$D$5:$AB$199,MATCH($B8,'All GHED Countries'!$B$5:$B$199,0),MATCH($D8,'All GHED Countries'!$D$4:$AB$4,0))="","",INDEX('All GHED Countries'!$D$5:$AB$199,MATCH($B8,'All GHED Countries'!$B$5:$B$199,0),MATCH($D8,'All GHED Countries'!$D$4:$AB$4,0))),"") -> 0.053643193
A9: Angola | B9: AGO | D9: 2021 | E9: Central government (budgetary) | F9: 0.10724204 | G9: 0.23824708 | H9: 0.079403848 | I9: 0.072294254 | J9: 0.2474218 | K9: 0.00036318822 | L9: 0.074011318 | M9: =SUM(S9:Y9) -> 0.078667505 | N9: 0.0052639513 | O9: 0.073520325 | P9: 0.023564694 | R9: =SUM(F9:Q9) -> 1 | S9: 0.00058143111 | T9: 3.4666817e-05 | U9: 0.040951099 | V9: 0.037100309 | W9: 0 | X9: 0 | Z9: =IFERROR(IF(INDEX('All GHED Countries'!$D$5:$AB$199,MATCH($B9,'All GHED Countries'!$B$5:$B$199,0),MATCH($D9,'All GHED Countries'!$D$4:$AB$4,0))="","",INDEX('All GHED Countries'!$D$5:$AB$199,MATCH($B9,'All GHED Countries'!$B$5:$B$199,0),MATCH($D9,'All GHED Countries'!$D$4:$AB$4,0))),"") -> 0.087773657
A10: Azerbaijan | B10: AZE | D10: 2008 | E10: General government | F10: 0.075420433 | G10: 0.00271703 | H10: 0.1099774 | I10: 0.045840534 | J10: 0.41322122 | K10: 0.00081427812 | L10: 0.015895041 | M10: =SUM(S10:Y10) -> 0.029771005 | N10: 0.012180936 | O10: 0.08504221 | P10: 0.18692668 | Q10: 0.022193233 | R10: =SUM(F10:Q10) -> 1 | T10: 0.0049022866 | U10: 0.01694197 | V10: 0 | Y10: 0.0079267482 | Z10: =IFERROR(IF(INDEX('All GHED Countries'!$D$5:$AB$199,MATCH($B10,'All GHED Countries'!$B$5:$B$199,0),MATCH($D10,'All GHED Countries'!$D$4:$AB$4,0))="","",INDEX('All GHED Countries'!$D$5:$AB$199,MATCH($B10,'All GHED Countries'!$B$5:$B$199,0),MATCH($D10,'All GHED Countries'!$D$4:$AB$4,0))),"") -> 0.027519121
A11: Azerbaijan | B11: AZE | D11: 2009 | E11: General government | F11: 0.058362049 | G11: 0.0065822488 | H11: 0.099252283 | I11: 0.056237664 | J11: 0.34660935 | K11: 0.00092000937 | L11: 0.018768191 | M11: =SUM(S11:Y11) -> 0.034600716 | N11: 0.013724867 | O11: 0.10045666 | P11: 0.22933324 | Q11: 0.035152722 | R11: =SUM(F11:Q11) -> 1 | T11: 0.0053695092 | U11: 0.019796929 | V11: 0.00070255261 | Y11: 0.0087317253 | Z11: =IFERROR(IF(INDEX('All GHED Countries'!$D$5:$AB$199,MATCH($B11,'All GHED Countries'!$B$5:$B$199,0),MATCH($D11,'All GHED Countries'!$D$4:$AB$4,0))="","",INDEX('All GHED Countries'!$D$5:$AB$199,MATCH($B11,'All GHED Countries'!$B$5:$B$199,0),MATCH($D11,'All GHED Countries'!$D$4:$AB$4,0))),"") -> 0.032848394
A12: Azerbaijan | B12: AZE | D12: 2010 | E12: General government | F12: 0.10024623 | G12: 0.0029473213 | H12: 0.088680794 | I12: 0.051805701 | J12: 0.35646172 | K12: 0.00085061931 | L12: 0.016094613 | M12: =SUM(S12:Y12) -> 0.032786151 | N12: 0.013072676 | O12: 0.091866886 | P12: 0.21695269 | Q12: 0.028234592 | R12: =SUM(F12:Q12) -> 1 | T12: 0.0058051037 | U12: 0.018079391 | V12: 0.00036561707 | Y12: 0.0085360394 | Z12: =IFERROR(IF(INDEX('All GHED Countries'!$D$5:$AB$199,MATCH($B12,'All GHED Countries'!$B$5:$B$199,0),MATCH($D12,'All GHED Countries'!$D$4:$AB$4,0))="","",INDEX('All GHED Countries'!$D$5:$AB$199,MATCH($B12,'All GHED Countries'!$B$5:$B$199,0),MATCH($D12,'All GHED Countries'!$D$4:$AB$4,0))),"") -> 0.031712611
A13: Azerbaijan | B13: AZE | D13: 2011 | E13: General government | F13: 0.096102761 | G13: 0.0099367353 | H13: 0.079025169 | I13: 0.043209566 | J13: 0.41962786 | K13: 0.00070892982 | L13: 0.0194985 | M13: =SUM(S13:Y13) -> 0.029698886 | N13: 0.011588952 | O13: 0.0777655 | P13: 0.21283714 | R13: =SUM(F13:Q13) -> 1 | T13: 0.0050445337 | U13: 0.016129618 | V13: 0.00028122836 | Y13: 0.0082435063 | Z13: =IFERROR(IF(INDEX('All GHED Countries'!$D$5:$AB$199,MATCH($B13,'All GHED Countries'!$B$5:$B$199,0),MATCH($D13,'All GHED Countries'!$D$4:$AB$4,0))="","",INDEX('All GHED Countries'!$D$5:$AB$199,MATCH($B13,'All GHED Countries'!$B$5:$B$199,0),MATCH($D13,'All GHED Countries'!$D$4:$AB$4,0))),"") -> 0.028160138
A14: Azerbaijan | B14: AZE | D14: 2012 | E14: General government | F14: 0.13359159 | G14: 0.0046097787 | H14: 0.071783759 | I14: 0.049322587 | J14: 0.37748057 | K14: 0.00064393804 | L14: 0.023631504 | M14: =SUM(S14:Y14) -> 0.031834048 | N14: 0.01271011 | O14: 0.077379888 | P14: 0.21701223 | R14: =SUM(F14:Q14) -> 1 | T14: 0.0048244247 | U14: 0.01658907 | V14: 0.00025042035 | Y14: 0.010170133 | Z14: =IFERROR(IF(INDEX('All GHED Countries'!$D$5:$AB$199,MATCH($B14,'All GHED Countries'!$B$5:$B$199,0),MATCH($D14,'All GHED Countries'!$D$4:$AB$4,0))="","",INDEX('All GHED Countries'!$D$5:$AB$199,MATCH($B14,'All GHED Countries'!$B$5:$B$199,0),MATCH($D14,'All GHED Countries'!$D$4:$AB$4,0))),"") -> 0.030453246
A15: Azerbaijan | B15: AZE | D15: 2013 | E15: General government | F15: 0.094873076 | G15: 0.0075036281 | H15: 0.070906193 | I15: 0.051692718 | J15: 0.43187496 | K15: 0.0006756596 | L15: 0.020545762 | M15: =SUM(S15:Y15) -> 0.030095401 | N15: 0.013479885 | O15: 0.071186925 | P15: 0.2071658 | R15: =SUM(F15:Q15) -> 1 | T15: 0.0046344539 | U15: 0.015640092 | V15: 0.00025694097 | Y15: 0.0095639141 | Z15: =IFERROR(IF(INDEX('All GHED Countries'!$D$5:$AB$199,MATCH($B15,'All GHED Countries'!$B$5:$B$199,0),MATCH($D15,'All GHED Countries'!$D$4:$AB$4,0))="","",INDEX('All GHED Countries'!$D$5:$AB$199,MATCH($B15,'All GHED Countries'!$B$5:$B$199,0),MATCH($D15,'All GHED Countries'!$D$4:$AB$4,0))),"") -> 0.028222861
A16: Azerbaijan | B16: AZE | D16: 2014 | E16: General government | F16: 0.16142488 | G16: 0.0040093138 | H16: 0.072472394 | I16: 0.054530477 | J16: 0.38445605 | K16: 0.0007142483 | L16: 0.021489351 | M16: =SUM(S16:Y16) -> 0.032603054 | N16: 0.014442101 | O16: 0.076995967 | P16: 0.17686216 | R16: =SUM(F16:Q16) -> 1 | T16: 0.0050711629 | U16: 0.017337187 | V16: 0.00031426925 | Y16: 0.0098804348 | Z16: =IFERROR(IF(INDEX('All GHED Countries'!$D$5:$AB$199,MATCH($B16,'All GHED Countries'!$B$5:$B$199,0),MATCH($D16,'All GHED Countries'!$D$4:$AB$4,0))="","",INDEX('All GHED Countries'!$D$5:$AB$199,MATCH($B16,'All GHED Countries'!$B$5:$B$199,0),MATCH($D16,'All GHED Countries'!$D$4:$AB$4,0))),"") -> 0.031070068
A17: Azerbaijan | B17: AZE | D17: 2015 | E17: General government | F17: 0.15601279 | G17: 0.010460893 | H17: 0.08446404 | I17: 0.056852033 | J17: 0.35511614 | K17: 0.00021772909 | L17: 0.020704057 | M17: =SUM(S17:Y17) -> 0.036029215 | N17: 0.013900023 | O17: 0.082662827 | P17: 0.18358026 | R17: =SUM(F17:Q17) -> 1 | S17: 0.010599448 | T17: 0.0049582851 | U17: 0.014716507 | V17: 0.00026721297 | W17: 0.00020783231 | X17: 0.0052799303 | Z17: =IFERROR(IF(INDEX('All GHED Countries'!$D$5:$AB$199,MATCH($B17,'All GHED Countries'!$B$5:$B$199,0),MATCH($D17,'All GHED Countries'!$D$4:$AB$4,0))="","",INDEX('All GHED Countries'!$D$5:$AB$199,MATCH($B17,'All GHED Countries'!$B$5:$B$199,0),MATCH($D17,'All GHED Countries'!$D$4:$AB$4,0))),"") -> 0.033728263
A18: Azerbaijan | B18: AZE | D18: 2016 | E18: General government | F18: 0.11894527 | G18: 0.013802902 | H18: 0.10522819 | I18: 0.064591927 | J18: 0.26852602 | K18: 0.0012015694 | L18: 0.024036436 | M18: =SUM(S18:Y18) -> 0.036805382 | N18: 0.035220119 | O18: 0.094459508 | P18: 0.23718268 | R18: =SUM(F18:Q18) -> 1 | S18: 0 | T18: 0.0055686177 | U18: 0.018371895 | V18: 0.00033320831 | W18: 0.00022213888 | X18: 0.012309523 | Z18: =IFERROR(IF(INDEX('All GHED Countries'!$D$5:$AB$199,MATCH($B18,'All GHED Countries'!$B$5:$B$199,0),MATCH($D18,'All GHED Countries'!$D$4:$AB$4,0))="","",INDEX('All GHED Countries'!$D$5:$AB$199,MATCH($B18,'All GHED Countries'!$B$5:$B$199,0),MATCH($D18,'All GHED Countries'!$D$4:$AB$4,0))),"") -> 0.03289871
A19: Azerbaijan | B19: AZE | D19: 2017 | E19: General government | F19: 0.098752309 | G19: 0.013239613 | H19: 0.10668758 | I19: 0.056720573 | J19: 0.39311161 | K19: 0.00064457126 | L19: 0.012776778 | M19: =SUM(S19:Y19) -> 0.03107912 | N19: 0.011203566 | O19: 0.078206281 | P19: 0.19757799 | R19: =SUM(F19:Q19) -> 1 | S19: 0 | T19: 0.0046100858 | U19: 0.014528755 | V19: 0.00029298694 | W19: 0.00018258606 | X19: 0.011464706 | Z19: =IFERROR(IF(INDEX('All GHED Countries'!$D$5:$AB$199,MATCH($B19,'All GHED Countries'!$B$5:$B$199,0),MATCH($D19,'All GHED Countries'!$D$4:$AB$4,0))="","",INDEX('All GHED Countries'!$D$5:$AB$199,MATCH($B19,'All GHED Countries'!$B$5:$B$199,0),MATCH($D19,'All GHED Countries'!$D$4:$AB$4,0))),"") -> 0.028237727
A20: Azerbaijan | B20: AZE | D20: 2018 | E20: General government | F20: 0.1348517 | G20: 0.025474609 | H20: 0.11111204 | I20: 0.062535338 | J20: 0.32182428 | K20: 0.00069504339 | L20: 0.018319933 | M20: =SUM(S20:Y20) -> 0.030326915 | N20: 0.012906475 | O20: 0.084542363 | P20: 0.1974113 | R20: =SUM(F20:Q20) -> 1 | S20: 0 | T20: 0.0043612993 | U20: 0.014462019 | V20: 0.00028470166 | W20: 0.0001898011 | X20: 0.011029095 | Z20: =IFERROR(IF(INDEX('All GHED Countries'!$D$5:$AB$199,MATCH($B20,'All GHED Countries'!$B$5:$B$199,0),MATCH($D20,'All GHED Countries'!$D$4:$AB$4,0))="","",INDEX('All GHED Countries'!$D$5:$AB$199,MATCH($B20,'All GHED Countries'!$B$5:$B$199,0),MATCH($D20,'All GHED Countries'!$D$4:$AB$4,0))),"") -> 0.026780353
A21: Azerbaijan | B21: AZE | D21: 2019 | E21: General government | F21: 0.1683575 | G21: 0.01515308 | H21: 0.113241 | I21: 0.064604139 | J21: 0.29327995 | K21: 0.00053148863 | L21: 0.013008278 | M21: =SUM(S21:Y21) -> 0.034094807 | N21: 0.013215597 | O21: 0.085931534 | P21: 0.19858262 | R21: =SUM(F21:Q21) -> 1 | S21: 0 | T21: 0.0044516884 | U21: 0.014478353 | V21: 0.00027516787 | W21: 0.00029778441 | X21: 0.014591813 | Z21: =IFERROR(IF(INDEX('All GHED Countries'!$D$5:$AB$199,MATCH($B21,'All GHED Countries'!$B$5:$B$199,0),MATCH($D21,'All GHED Countries'!$D$4:$AB$4,0))="","",INDEX('All GHED Countries'!$D$5:$AB$199,MATCH($B21,'All GHED Countries'!$B$5:$B$199,0),MATCH($D21,'All GHED Countries'!$D$4:$AB$4,0))),"") -> 0.032879271
A22: Azerbaijan | B22: AZE | D22: 2020 | E22: General government | F22: 0.1396493 | G22: 0.019984349 | H22: 0.11848301 | I22: 0.073511431 | J22: 0.22611456 | K22: 0.008141143 | L22: 0.0088747629 | M22: =SUM(S22:Y22) -> 0.057623126 | N22: 0.012176052 | O22: 0.098020109 | P22: 0.23742215 | R22: =SUM(F22:Q22) -> 1 | S22: 0 | T22: 2.037833e-05 | U22: 0.0052915732 | V22: 0 | W22: 5.7738603e-05 | X22: 0.052253436 | Z22: =IFERROR(IF(INDEX('All GHED Countries'!$D$5:$AB$199,MATCH($B22,'All GHED Countries'!$B$5:$B$199,0),MATCH($D22,'All GHED Countries'!$D$4:$AB$4,0))="","",INDEX('All GHED Countries'!$D$5:$AB$199,MATCH($B22,'All GHED Countries'!$B$5:$B$199,0),MATCH($D22,'All GHED Countries'!$D$4:$AB$4,0))),"") -> 0.057977181
A23: Azerbaijan | B23: AZE | D23: 2021 | E23: General government | F23: 0.086603686 | G23: 0.021050488 | H23: 0.14432266 | I23: 0.079324482 | J23: 0.20621473 | K23: 0.016048558 | L23: 0.0077837695 | M23: =SUM(S23:Y23) -> 0.046722799 | N23: 0.013081711 | O23: 0.10788627 | P23: 0.27096085 | R23: =SUM(F23:Q23) -> 1 | S23: 0 | T23: 4.7092814e-05 | U23: 0.0048505599 | V23: 0 | W23: 5.3820359e-05 | X23: 0.041771326 | Z23: =IFERROR(IF(INDEX('All GHED Countries'!$D$5:$AB$199,MATCH($B23,'All GHED Countries'!$B$5:$B$199,0),MATCH($D23,'All GHED Countries'!$D$4:$AB$4,0))="","",INDEX('All GHED Countries'!$D$5:$AB$199,MATCH($B23,'All GHED Countries'!$B$5:$B$199,0),MATCH($D23,'All GHED Countries'!$D$4:$AB$4,0))),"") -> 0.046051784
A24: Azerbaijan | B24: AZE | D24: 2022 | E24: General government | F24: 0.13037289 | G24: 0.017090577 | H24: 0.13243229 | I24: 0.066177995 | J24: 0.21779803 | K24: 0.0075407987 | L24: 0.0076011739 | M24: =SUM(S24:Y24) -> 0.038529155 | N24: 0.011409853 | O24: 0.10365036 | P24: 0.26739628 | R24: =SUM(F24:Q24) -> 0.99999941 | S24: 0 | T24: 4.376031e-05 | U24: 0.0043442176 | V24: 0 | W24: 5.3598946e-05 | X24: 0.034087578 | Z24: =IFERROR(IF(INDEX('All GHED Countries'!$D$5:$AB$199,MATCH($B24,'All GHED Countries'!$B$5:$B$199,0),MATCH($D24,'All GHED Countries'!$D$4:$AB$4,0))="","",INDEX('All GHED Countries'!$D$5:$AB$199,MATCH($B24,'All GHED Countries'!$B$5:$B$199,0),MATCH($D24,'All GHED Countries'!$D$4:$AB$4,0))),"") -> 0.036410747
A25: Azerbaijan | B25: AZE | D25: 2023 | E25: General government | F25: 0.12159898 | G25: 0.020629068 | H25: 0.11947851 | I25: 0.084753819 | J25: 0.24925484 | K25: 0.0083446132 | L25: 0.0082014482 | M25: =SUM(S25:Y25) -> 0.041143585 | N25: 0.011490084 | O25: 0.10151824 | P25: 0.23358681 | R25: =SUM(F25:Q25) -> 1 | S25: 0 | T25: 4.5677809e-05 | U25: 0.0042441862 | V25: 0 | W25: 5.2047035e-05 | X25: 0.036801674 | Z25: =IFERROR(IF(INDEX('All GHED Countries'!$D$5:$AB$199,MATCH($B25,'All GHED Countries'!$B$5:$B$199,0),MATCH($D25,'All GHED Countries'!$D$4:$AB$4,0))="","",INDEX('All GHED Countries'!$D$5:$AB$199,MATCH($B25,'All GHED Countries'!$B$5:$B$199,0),MATCH($D25,'All GHED Countries'!$D$4:$AB$4,0))),"") -> 0.042580843
A26: Azerbaijan | B26: AZE | D26: 2024 | E26: General government | F26: 0.11772124 | G26: 0.010000538 | H26: 0.1382346 | I26: 0.073798963 | J26: 0.24442 | K26: 0.0078692607 | L26: 0.0075353542 | M26: =SUM(S26:Y26) -> 0.041279279 | N26: 0.0116454 | O26: 0.10360371 | P26: 0.24389165 | R26: =SUM(F26:Q26) -> 1 | S26: 0 | T26: 4.505212e-05 | U26: 0.0050066665 | V26: 0 | W26: 0.00015816504 | X26: 0.036069396 | Z26: =IFERROR(IF(INDEX('All GHED Countries'!$D$5:$AB$199,MATCH($B26,'All GHED Countries'!$B$5:$B$199,0),MATCH($D26,'All GHED Countries'!$D$4:$AB$4,0))="","",INDEX('All GHED Countries'!$D$5:$AB$199,MATCH($B26,'All GHED Countries'!$B$5:$B$199,0),MATCH($D26,'All GHED Countries'!$D$4:$AB$4,0))),"")
A27: Bangladesh | B27: BGD | D27: 2005 | E27: Central government (budgetary) | F27: 0.23514123 | G27: 0.15307555 | H27: 0.097311189 | I27: 0.06415353 | J27: 0.11007514 | K27: 0.00097200427 | L27: 0.08721147 | M27: =SUM(S27:Y27) -> 0.063720871 | N27: 0.013016769 | O27: 0.15038369 | P27: 0.024938567 | R27: =SUM(F27:Q27) -> 1 | S27: 0 | T27: 0.040032637 | U27: 0.011592381 | V27: 0.012095853 | W27: 0 | X27: 0 | Z27: =IFERROR(IF(INDEX('All GHED Countries'!$D$5:$AB$199,MATCH($B27,'All GHED Countries'!$B$5:$B$199,0),MATCH($D27,'All GHED Countries'!$D$4:$AB$4,0))="","",INDEX('All GHED Countries'!$D$5:$AB$199,MATCH($B27,'All GHED Countries'!$B$5:$B$199,0),MATCH($D27,'All GHED Countries'!$D$4:$AB$4,0))),"") -> 0.043888373
A28: Bangladesh | B28: BGD | D28: 2006 | E28: Central government (budgetary) | F28: 0.21769056 | G28: 0.16793205 | H28: 0.097669031 | I28: 0.060084254 | J28: 0.10023035 | K28: 0.00083298061 | L28: 0.083542803 | M28: =SUM(S28:Y28) -> 0.073027851 | N28: 0.013274321 | O28: 0.1591692 | P28: 0.026546607 | R28: =SUM(F28:Q28) -> 1 | S28: 0 | T28: 0.048020564 | U28: 0.012440246 | V28: 0.012567041 | W28: 0 | X28: 0 | Z28: =IFERROR(IF(INDEX('All GHED Countries'!$D$5:$AB$199,MATCH($B28,'All GHED Countries'!$B$5:$B$199,0),MATCH($D28,'All GHED Countries'!$D$4:$AB$4,0))="","",INDEX('All GHED Countries'!$D$5:$AB$199,MATCH($B28,'All GHED Countries'!$B$5:$B$199,0),MATCH($D28,'All GHED Countries'!$D$4:$AB$4,0))),"") -> 0.047282033
... A30: Bangladesh | B30: BGD | D30: 2008 | E30: Central government (budgetary) | F30: 0.19731563 | G30: 0.20123754 | H30: 0.098327161 | I30: 0.066209344 | J30: 0.12041995 | K30: 0.00077175366 | L30: 0.060820966 | M30: =SUM(S30:Y30) -> 0.066473373 | N30: 0.010822871 | O30: 0.15049382 | P30: 0.027107586 | R30: =SUM(F30:Q30) -> 1 | S30: 0 | T30: 0.043475785 | U30: 0.01110979 | V30: 0.011887798 | W30: 0 | X30: 0 | Z30: =IFERROR(IF(INDEX('All GHED Countries'!$D$5:$AB$199,MATCH($B30,'All GHED Countries'!$B$5:$B$199,0),MATCH($D30,'All GHED Countries'!$D$4:$AB$4,0))="","",INDEX('All GHED Countries'!$D$5:$AB$199,MATCH($B30,'All GHED Countries'!$B$5:$B$199,0),MATCH($D30,'All GHED Countries'!$D$4:$AB$4,0))),"") -> 0.038409143
A31: Bangladesh | B31: BGD | D31: 2009 | E31: Central government (budgetary) | F31: 0.18884704 | G31: 0.18961957 | H31: 0.077708426 | I31: 0.065882999 | J31: 0.16641441 | K31: 0.00067958935 | L31: 0.065676858 | M31: =SUM(S31:Y31) -> 0.06337263 | N31: 0.010901517 | O31: 0.14114432 | P31: 0.029752647 | R31: =SUM(F31:Q31) -> 1 | T31: 0.011532479 | U31: 0.011563319 | V31: 0.010901517 | Y31: 0.029375315 | Z31: =IFERROR(IF(INDEX('All GHED Countries'!$D$5:$AB$199,MATCH($B31,'All GHED Countries'!$B$5:$B$199,0),MATCH($D31,'All GHED Countries'!$D$4:$AB$4,0))="","",INDEX('All GHED Countries'!$D$5:$AB$199,MATCH($B31,'All GHED Countries'!$B$5:$B$199,0),MATCH($D31,'All GHED Countries'!$D$4:$AB$4,0))),"") -> 0.041153383
A32: Bangladesh | B32: BGD | D32: 2010 | E32: Central government (budgetary) | F32: 0.19005536 | G32: 0.16946615 | H32: 0.098844123 | I32: 0.070427016 | J32: 0.071647548 | K32: 0.0072150064 | L32: 0.067342808 | M32: =SUM(S32:Y32) -> 0.070505586 | N32: 0.011203796 | O32: 0.16872004 | P32: 0.074572571 | R32: =SUM(F32:Q32) -> 1 | S32: 0 | T32: 0.045315688 | U32: 0.01228811 | V32: 0.012901788 | W32: 0 | X32: 0 | Z32: =IFERROR(IF(INDEX('All GHED Countries'!$D$5:$AB$199,MATCH($B32,'All GHED Countries'!$B$5:$B$199,0),MATCH($D32,'All GHED Countries'!$D$4:$AB$4,0))="","",INDEX('All GHED Countries'!$D$5:$AB$199,MATCH($B32,'All GHED Countries'!$B$5:$B$199,0),MATCH($D32,'All GHED Countries'!$D$4:$AB$4,0))),"") -> 0.044394164
A33: Bangladesh | B33: BGD | D33: 2011 | E33: Central government (budgetary) | F33: 0.068594841 | G33: 0.14732618 | H33: 0.10662414 | I33: 0.077550488 | J33: 0.26047006 | K33: 0.006887498 | L33: 0.020904544 | M33: =SUM(S33:Y33) -> 0.063785038 | N33: 0.0096137461 | O33: 0.16821608 | P33: 0.070027385 | R33: =SUM(F33:Q33) -> 1 | S33: 0 | T33: 0.0035107119 | U33: 0.011805803 | V33: 0.0087221982 | W33: 0.00025036683 | X33: 0.039495958 | Z33: =IFERROR(IF(INDEX('All GHED Countries'!$D$5:$AB$199,MATCH($B33,'All GHED Countries'!$B$5:$B$199,0),MATCH($D33,'All GHED Countries'!$D$4:$AB$4,0))="","",INDEX('All GHED Countries'!$D$5:$AB$199,MATCH($B33,'All GHED Countries'!$B$5:$B$199,0),MATCH($D33,'All GHED Countries'!$D$4:$AB$4,0))),"") -> 0.04181591
A34: Bangladesh | B34: BGD | D34: 2012 | E34: Central government (budgetary) | F34: 0.068725768 | G34: 0.16546543 | H34: 0.10821299 | I34: 0.075014711 | J34: 0.2618933 | K34: 0.0059220359 | L34: 0.019816137 | M34: =SUM(S34:Y34) -> 0.059955885 | N34: 0.0073244346 | O34: 0.16072247 | P34: 0.066946842 | R34: =SUM(F34:Q34) -> 1 | S34: 0 | T34: 0.003381493 | U34: 0.010799937 | V34: 0.0077344731 | W34: 0.00021916555 | X34: 0.037820816 | Z34: =IFERROR(IF(INDEX('All GHED Countries'!$D$5:$AB$199,MATCH($B34,'All GHED Countries'!$B$5:$B$199,0),MATCH($D34,'All GHED Countries'!$D$4:$AB$4,0))="","",INDEX('All GHED Countries'!$D$5:$AB$199,MATCH($B34,'All GHED Countries'!$B$5:$B$199,0),MATCH($D34,'All GHED Countries'!$D$4:$AB$4,0))),"") -> 0.040162044
A35: Bangladesh | B35: BGD | D35: 2013 | E35: Central government (budgetary) | F35: 0.068288581 | G35: 0.17277937 | H35: 0.093953751 | I35: 0.072688057 | J35: 0.2967269 | K35: 0.0031139328 | L35: 0.018043578 | M35: =SUM(S35:Y35) -> 0.058563816 | N35: 0.0074624272 | O35: 0.14441426 | P35: 0.063965327 | R35: =SUM(F35:Q35) -> 1 | S35: 0 | T35: 0.0031672736 | U35: 0.010285416 | V35: 0.0070395616 | W35: 0.00020356754 | X35: 0.037867996 | Z35: =IFERROR(IF(INDEX('All GHED Countries'!$D$5:$AB$199,MATCH($B35,'All GHED Countries'!$B$5:$B$199,0),MATCH($D35,'All GHED Countries'!$D$4:$AB$4,0))="","",INDEX('All GHED Countries'!$D$5:$AB$199,MATCH($B35,'All GHED Countries'!$B$5:$B$199,0),MATCH($D35,'All GHED Countries'!$D$4:$AB$4,0))),"") -> 0.036174552
A36: Bangladesh | B36: BGD | D36: 2014 | E36: Central government (budgetary) | F36: 0.074482218 | G36: 0.17262271 | H36: 0.1016138 | I36: 0.080069891 | J36: 0.26091288 | K36: 0.0014367863 | L36: 0.019622662 | M36: =SUM(S36:Y36) -> 0.057443281 | N36: 0.0077336681 | O36: 0.15945653 | P36: 0.064605576 | R36: =SUM(F36:Q36) -> 1 | S36: 0 | T36: 0.0029973527 | U36: 0.010216483 | V36: 0.0076770794 | W36: 0.0002194508 | X36: 0.036332915 | Z36: =IFERROR(IF(INDEX('All GHED Countries'!$D$5:$AB$199,MATCH($B36,'All GHED Countries'!$B$5:$B$199,0),MATCH($D36,'All GHED Countries'!$D$4:$AB$4,0))="","",INDEX('All GHED Countries'!$D$5:$AB$199,MATCH($B36,'All GHED Countries'!$B$5:$B$199,0),MATCH($D36,'All GHED Countries'!$D$4:$AB$4,0))),"") -> 0.035924532
A37: Bangladesh | B37: BGD | D37: 2015 | E37: Central government (budgetary) | F37: 0.063095208 | G37: 0.18016723 | H37: 0.10264623 | I37: 0.080566991 | J37: 0.26190896 | K37: 0.0013837277 | L37: 0.019706879 | M37: =SUM(S37:Y37) -> 0.05788093 | N37: 0.007915511 | O37: 0.1601341 | P37: 0.06459424 | R37: =SUM(F37:Q37) -> 1 | S37: 0 | T37: 0.0029739472 | U37: 0.010227975 | V37: 0.0071372289 | W37: 0.0002181833 | X37: 0.037323596 | Z37: =IFERROR(IF(INDEX('All GHED Countries'!$D$5:$AB$199,MATCH($B37,'All GHED Countries'!$B$5:$B$199,0),MATCH($D37,'All GHED Countries'!$D$4:$AB$4,0))="","",INDEX('All GHED Countries'!$D$5:$AB$199,MATCH($B37,'All GHED Countries'!$B$5:$B$199,0),MATCH($D37,'All GHED Countries'!$D$4:$AB$4,0))),"") -> 0.033768887
A38: Bangladesh | B38: BGD | D38: 2016 | E38: Central government (budgetary) | F38: 0.050183173 | G38: 0.16170134 | H38: 0.10010222 | I38: 0.093616563 | J38: 0.19136615 | K38: 0.0013841947 | L38: 0.080297969 | M38: =SUM(S38:Y38) -> 0.060948589 | N38: 0.010936606 | O38: 0.18625979 | P38: 0.063203408 | R38: =SUM(F38:Q38) -> 1 | S38: 0 | T38: 0.03601841 | U38: 0.01121051 | V38: 0.013719669 | W38: 0 | X38: 0 | Z38: =IFERROR(IF(INDEX('All GHED Countries'!$D$5:$AB$199,MATCH($B38,'All GHED Countries'!$B$5:$B$199,0),MATCH($D38,'All GHED Countries'!$D$4:$AB$4,0))="","",INDEX('All GHED Countries'!$D$5:$AB$199,MATCH($B38,'All GHED Countries'!$B$5:$B$199,0),MATCH($D38,'All GHED Countries'!$D$4:$AB$4,0))),"") -> 0.040993581
A39: Bolivia (Plurinational State of) | B39: BOL | D39: 2005 | E39: General government | F39: 0.10915667 | G39: 0.07800519 | H39: 0.043162427 | I39: 0.056933575 | J39: 0.21142055 | K39: 0.018018001 | L39: 0.036188368 | M39: =SUM(S39:Y39) -> 0.10861558 | N39: 0.012066841 | O39: 0.18950741 | P39: 0.1369254 | R39: =SUM(F39:Q39) -> 1 | T39: 0.034586931 | U39: 0.017200228 | V39: 0.0139397 | Y39: 0.042888716 | Z39: =IFERROR(IF(INDEX('All GHED Countries'!$D$5:$AB$199,MATCH($B39,'All GHED Countries'!$B$5:$B$199,0),MATCH($D39,'All GHED Countries'!$D$4:$AB$4,0))="","",INDEX('All GHED Countries'!$D$5:$AB$199,MATCH($B39,'All GHED Countries'!$B$5:$B$199,0),MATCH($D39,'All GHED Countries'!$D$4:$AB$4,0))),"") -> 0.082987986
A40: Bolivia (Plurinational State of) | B40: BOL | D40: 2006 | E40: General government | F40: 0.090965234 | G40: 0.09449111 | H40: 0.039484572 | I40: 0.050757992 | J40: 0.23443339 | K40: 0.017938392 | L40: 0.036595581 | M40: =SUM(S40:Y40) -> 0.095695793 | N40: 0.015249529 | O40: 0.19599041 | P40: 0.128398 | R40: =SUM(F40:Q40) -> 1 | T40: 0.032644138 | U40: 0.017583625 | V40: 0.0096836634 | Y40: 0.035784367 | Z40: =IFERROR(IF(INDEX('All GHED Countries'!$D$5:$AB$199,MATCH($B40,'All GHED Countries'!$B$5:$B$199,0),MATCH($D40,'All GHED Countries'!$D$4:$AB$4,0))="","",INDEX('All GHED Countries'!$D$5:$AB$199,MATCH($B40,'All GHED Countries'!$B$5:$B$199,0),MATCH($D40,'All GHED Countries'!$D$4:$AB$4,0))),"") -> 0.087520018
A41: Bolivia (Plurinational State of) | B41: BOL | D41: 2007 | E41: General government | F41: 0.088139541 | G41: 0.063925093 | H41: 0.043053077 | I41: 0.049999303 | J41: 0.24516532 | K41: 0.017413762 | L41: 0.047389744 | M41: =SUM(S41:Y41) -> 0.093964912 | N41: 0.021712827 | O41: 0.20374284 | P41: 0.12549358 | R41: =SUM(F41:Q41) -> 1 | T41: 0.036382462 | U41: 0.013584199 | V41: 0.0067695801 | Y41: 0.037228671 | Z41: =IFERROR(IF(INDEX('All GHED Countries'!$D$5:$AB$199,MATCH($B41,'All GHED Countries'!$B$5:$B$199,0),MATCH($D41,'All GHED Countries'!$D$4:$AB$4,0))="","",INDEX('All GHED Countries'!$D$5:$AB$199,MATCH($B41,'All GHED Countries'!$B$5:$B$199,0),MATCH($D41,'All GHED Countries'!$D$4:$AB$4,0))),"") -> 0.085002489
A42: Botswana | B42: BWA | C42: yes | D42: 2017 | E42: Central government (budgetary) | F42: 0.32558398 | G42: 0.059225243 | H42: 0.074832089 | I42: 0.041465716 | J42: 0.13579095 | K42: 0.006785428 | L42: 0.036857082 | M42: =SUM(S42:Y42) -> 0.091974114 | N42: 0.012054244 | O42: 0.16486112 | P42: 0.050570032 | R42: =SUM(F42:Q42) -> 1 | S42: 0 | T42: 0.0043755076 | U42: 0.071226879 | V42: 0.0029595988 | W42: 0 | X42: 0.013412129 | Z42: =IFERROR(IF(INDEX('All GHED Countries'!$D$5:$AB$199,MATCH($B42,'All GHED Countries'!$B$5:$B$199,0),MATCH($D42,'All GHED Countries'!$D$4:$AB$4,0))="","",INDEX('All GHED Countries'!$D$5:$AB$199,MATCH($B42,'All GHED Countries'!$B$5:$B$199,0),MATCH($D42,'All GHED Countries'!$D$4:$AB$4,0))),"") -> 0.14315475
A43: Botswana | B43: BWA | C43: yes | D43: 2018 | E43: Central government (budgetary) | F43: 0.18271607 | G43: 0.017496217 | H43: 0.087402659 | I43: 0.067858988 | J43: 0.12239798 | K43: 0 | L43: 0.10908376 | M43: =SUM(S43:Y43) -> 0.11930098 | N43: 0.03068085 | O43: 0.22378061 | P43: 0.039281887 | R43: =SUM(F43:Q43) -> 1 | S43: 0 | T43: 0 | U43: 0.10498933 | V43: 0 | W43: 0 | X43: 0.014311646 | Z43: =IFERROR(IF(INDEX('All GHED Countries'!$D$5:$AB$199,MATCH($B43,'All GHED Countries'!$B$5:$B$199,0),MATCH($D43,'All GHED Countries'!$D$4:$AB$4,0))="","",INDEX('All GHED Countries'!$D$5:$AB$199,MATCH($B43,'All GHED Countries'!$B$5:$B$199,0),MATCH($D43,'All GHED Countries'!$D$4:$AB$4,0))),"") -> 0.11542103
A44: Botswana | B44: BWA | C44: yes | D44: 2019 | E44: Central government (budgetary) | F44: 0.19066705 | G44: 0.018412196 | H44: 0.092127951 | I44: 0.072494963 | J44: 0.14245599 | K44: 0 | L44: 0.064739015 | M44: =SUM(S44:Y44) -> 0.12371168 | N44: 0.032911708 | O44: 0.21959941 | P44: 0.042880037 | R44: =SUM(F44:Q44) -> 1 | S44: 0 | T44: 0 | U44: 0.10707655 | V44: 0.0034105437 | W44: 0 | X44: 0.013224591 | Z44: =IFERROR(IF(INDEX('All GHED Countries'!$D$5:$AB$199,MATCH($B44,'All GHED Countries'!$B$5:$B$199,0),MATCH($D44,'All GHED Countries'!$D$4:$AB$4,0))="","",INDEX('All GHED Countries'!$D$5:$AB$199,MATCH($B44,'All GHED Countries'!$B$5:$B$199,0),MATCH($D44,'All GHED Countries'!$D$4:$AB$4,0))),"") -> 0.12006065
A45: Botswana | B45: BWA | C45: yes | D45: 2020 | E45: Central government (budgetary) | F45: 0.18735543 | G45: 0.018055097 | H45: 0.09219586 | I45: 0.077073008 | J45: 0.11277569 | K45: 0 | L45: 0.064971018 | M45: =SUM(S45:Y45) -> 0.15685634 | N45: 0.025094552 | O45: 0.22926034 | P45: 0.036362666 | R45: =SUM(F45:Q45) -> 1 | S45: 0 | T45: 0 | U45: 0.13913458 | V45: 0.0033456869 | W45: 0.014376072 | X45: 0 | Z45: =IFERROR(IF(INDEX('All GHED Countries'!$D$5:$AB$199,MATCH($B45,'All GHED Countries'!$B$5:$B$199,0),MATCH($D45,'All GHED Countries'!$D$4:$AB$4,0))="","",INDEX('All GHED Countries'!$D$5:$AB$199,MATCH($B45,'All GHED Countries'!$B$5:$B$199,0),MATCH($D45,'All GHED Countries'!$D$4:$AB$4,0))),"") -> 0.11661525
A46: Botswana | B46: BWA | C46: yes | D46: 2021 | E46: Central government (budgetary) | F46: 0.18465341 | G46: 0.017346845 | H46: 0.088095715 | I46: 0.077950724 | J46: 0.092032021 | K46: 0.0084831509 | L46: 0.10781704 | M46: =SUM(S46:Y46) -> 0.14915258 | N46: 0.01866958 | O46: 0.24260407 | P46: 0.013194853 | R46: =SUM(F46:Q46) -> 1 | S46: 0 | T46: 0 | U46: 0.13266579 | V46: 0.0030754999 | W46: 0.013411284 | X46: 0 | Z46: =IFERROR(IF(INDEX('All GHED Countries'!$D$5:$AB$199,MATCH($B46,'All GHED Countries'!$B$5:$B$199,0),MATCH($D46,'All GHED Countries'!$D$4:$AB$4,0))="","",INDEX('All GHED Countries'!$D$5:$AB$199,MATCH($B46,'All GHED Countries'!$B$5:$B$199,0),MATCH($D46,'All GHED Countries'!$D$4:$AB$4,0))),"") -> 0.14610139
A47: Botswana | B47: BWA | C47: yes | D47: 2022 | E47: Central government (budgetary) | F47: 0.1823525 | G47: 0.022454965 | H47: 0.089518871 | I47: 0.083084954 | J47: 0.098253921 | K47: 0.0077635471 | L47: 0.10937324 | M47: =SUM(S47:Y47) -> 0.1511326 | N47: 0.021273812 | O47: 0.22014618 | P47: 0.014645401 | R47: =SUM(F47:Q47) -> 1 | S47: 0 | T47: 0 | U47: 0.0016724651 | V47: 0.13270225 | W47: 0.016757878 | X47: 0 | Z47: =IFERROR(IF(INDEX('All GHED Countries'!$D$5:$AB$199,MATCH($B47,'All GHED Countries'!$B$5:$B$199,0),MATCH($D47,'All GHED Countries'!$D$4:$AB$4,0))="","",INDEX('All GHED Countries'!$D$5:$AB$199,MATCH($B47,'All GHED Countries'!$B$5:$B$199,0),MATCH($D47,'All GHED Countries'!$D$4:$AB$4,0))),"") -> 0.14610139
A48: Botswana | B48: BWA | C48: yes | D48: 2023 | E48: Central government (budgetary) | F48: 0.17297963 | G48: 0.029845837 | H48: 0.07712722 | I48: 0.079214753 | J48: 0.088288557 | K48: 0.0085160423 | L48: 0.1688198 | M48: =SUM(S48:Y48) -> 0.12171136 | N48: 0.015889476 | O48: 0.20014957 | P48: 0.037457759 | R48: =SUM(F48:Q48) -> 1 | S48: 0 | T48: 0 | U48: 0 | V48: 0.10762216 | W48: 0.014089207 | X48: 0 | Z48: =IFERROR(IF(INDEX('All GHED Countries'!$D$5:$AB$199,MATCH($B48,'All GHED Countries'!$B$5:$B$199,0),MATCH($D48,'All GHED Countries'!$D$4:$AB$4,0))="","",INDEX('All GHED Countries'!$D$5:$AB$199,MATCH($B48,'All GHED Countries'!$B$5:$B$199,0),MATCH($D48,'All GHED Countries'!$D$4:$AB$4,0))),"") -> 0.14610139
A49: Burkina Faso | B49: BFA | D49: 2017 | E49: Central government (budgetary) | F49: 0.58768749 | G49: 0.033313738 | H49: 0.009008959 | I49: 0.0075093016 | J49: 0.2093519 | K49: 0.0026647502 | L49: 0.026974789 | M49: =SUM(S49:Y49) -> 0.046390078 | N49: 0.0023102656 | O49: 0.071421452 | P49: 0.0033672815 | R49: =SUM(F49:Q49) -> 1 | S49: 0.00013681862 | T49: 0.027894338 | U49: 0.014470054 | V49: 0.00041885289 | W49: 0 | X49: 0.003470014 | Z49: =IFERROR(IF(INDEX('All GHED Countries'!$D$5:$AB$199,MATCH($B49,'All GHED Countries'!$B$5:$B$199,0),MATCH($D49,'All GHED Countries'!$D$4:$AB$4,0))="","",INDEX('All GHED Countries'!$D$5:$AB$199,MATCH($B49,'All GHED Countries'!$B$5:$B$199,0),MATCH($D49,'All GHED Countries'!$D$4:$AB$4,0))),"") -> 0.10235205
A50: Burkina Faso | B50: BFA | D50: 2018 | E50: Central government (budgetary) | F50: 0.50428413 | G50: 0.046831103 | H50: 0.068525515 | I50: 0.01635437 | J50: 0.15800812 | K50: 0.0028167421 | L50: 0.015886011 | M50: =SUM(S50:Y50) -> 0.062815966 | N50: 0.0093795875 | O50: 0.11009652 | P50: 0.0050019346 | R50: =SUM(F50:Q50) -> 1 | S50: 0.0084280181 | T50: 0 | U50: 0.037720899 | V50: 0.010338996 | W50: 0.00049735035 | X50: 0.0058307022 | Z50: =IFERROR(IF(INDEX('All GHED Countries'!$D$5:$AB$199,MATCH($B50,'All GHED Countries'!$B$5:$B$199,0),MATCH($D50,'All GHED Countries'!$D$4:$AB$4,0))="","",INDEX('All GHED Countries'!$D$5:$AB$199,MATCH($B50,'All GHED Countries'!$B$5:$B$199,0),MATCH($D50,'All GHED Countries'!$D$4:$AB$4,0))),"") -> 0.087850237
A51: Burkina Faso | B51: BFA | D51: 2019 | E51: Central government (budgetary) | F51: 0.59989836 | G51: 0.05308578 | H51: 0.052835989 | I51: 0.015766769 | J51: 0.14184334 | K51: 0.0035383799 | L51: 0.016277942 | M51: =SUM(S51:Y51) -> 0.039902347 | N51: 0.0047098755 | O51: 0.066005645 | P51: 0.0061355672 | R51: =SUM(F51:Q51) -> 1 | S51: 0.0001362736 | T51: 0 | U51: 0.027493414 | V51: 0.0062469928 | W51: 0.00041620784 | X51: 0.0056094588 | Z51: =IFERROR(IF(INDEX('All GHED Countries'!$D$5:$AB$199,MATCH($B51,'All GHED Countries'!$B$5:$B$199,0),MATCH($D51,'All GHED Countries'!$D$4:$AB$4,0))="","",INDEX('All GHED Countries'!$D$5:$AB$199,MATCH($B51,'All GHED Countries'!$B$5:$B$199,0),MATCH($D51,'All GHED Countries'!$D$4:$AB$4,0))),"") -> 0.09576911
A52: Burkina Faso | B52: BFA | D52: 2020 | E52: Central government (budgetary) | F52: 0.55672881 | G52: 0.054749545 | H52: 0.042909154 | I52: 0.013628834 | J52: 0.18728378 | K52: 0.0044568855 | L52: 0.010420872 | M52: =SUM(S52:Y52) -> 0.052415603 | N52: 0.0035159754 | O52: 0.069250538 | P52: 0.0046399974 | R52: =SUM(F52:Q52) -> 1 | S52: 0.00025177136 | T52: 3.2372511e-05 | U52: 0.015334683 | V52: 0.011637049 | W52: 0.00032963518 | X52: 0.024830093 | Z52: =IFERROR(IF(INDEX('All GHED Countries'!$D$5:$AB$199,MATCH($B52,'All GHED Countries'!$B$5:$B$199,0),MATCH($D52,'All GHED Countries'!$D$4:$AB$4,0))="","",INDEX('All GHED Countries'!$D$5:$AB$199,MATCH($B52,'All GHED Countries'!$B$5:$B$199,0),MATCH($D52,'All GHED Countries'!$D$4:$AB$4,0))),"") -> 0.116475
A53: Burkina Faso | B53: BFA | D53: 2021 | E53: Central government (budgetary) | F53: 0.47230655 | G53: 0.061579888 | H53: 0.046249956 | I53: 0.013743571 | J53: 0.14437518 | K53: 0.0045246241 | L53: 0.01303646 | M53: =SUM(S53:Y53) -> 0.14392853 | N53: 0.0052185617 | O53: 0.074199772 | P53: 0.020836909 | R53: =SUM(F53:Q53) -> 1 | S53: 6.7633508e-05 | T53: 2.5162646e-05 | U53: 0.018645718 | V53: 0.018308981 | W53: 0.10350365 | X53: 0.0033773878 | Z53: =IFERROR(IF(INDEX('All GHED Countries'!$D$5:$AB$199,MATCH($B53,'All GHED Countries'!$B$5:$B$199,0),MATCH($D53,'All GHED Countries'!$D$4:$AB$4,0))="","",INDEX('All GHED Countries'!$D$5:$AB$199,MATCH($B53,'All GHED Countries'!$B$5:$B$199,0),MATCH($D53,'All GHED Countries'!$D$4:$AB$4,0))),"") -> 0.098384151
A54: Burkina Faso | B54: BFA | D54: 2022 | E54: Central government (budgetary) | F54: 0.5331415 | G54: 0.057582857 | H54: 0.10695056 | I54: 0.017838964 | J54: 0.16500086 | K54: 0.0035482941 | L54: 0.01206739 | M54: =SUM(S54:Y54) -> 0.03893119 | N54: 0.0039342619 | O54: 0.054396249 | P54: 0.0066078703 | R54: =SUM(F54:Q54) -> 1 | S54: 4.562198e-05 | T54: 0.00049368423 | U54: 0.023499429 | V54: 0.011857072 | W54: 0 | X54: 0.0030353824 | Z54: =IFERROR(IF(INDEX('All GHED Countries'!$D$5:$AB$199,MATCH($B54,'All GHED Countries'!$B$5:$B$199,0),MATCH($D54,'All GHED Countries'!$D$4:$AB$4,0))="","",INDEX('All GHED Countries'!$D$5:$AB$199,MATCH($B54,'All GHED Countries'!$B$5:$B$199,0),MATCH($D54,'All GHED Countries'!$D$4:$AB$4,0))),"") -> 0.083968487
A55: Burkina Faso | B55: BFA | D55: 2023 | E55: Central government (budgetary) | F55: 0.11402108 | G55: 0.078095917 | H55: 0.17581056 | I55: 0.065993634 | J55: 0.23173521 | K55: 0.020171567 | L55: 0.0088415249 | M55: =SUM(S55:Y55) -> 0.084011051 | N55: 0.010310259 | O55: 0.18844758 | P55: 0.022561612 | R55: =SUM(F55:Q55) -> 1 | S55: 0 | T55: 0.0066172577 | U55: 0.068684149 | V55: 0.0043689247 | W55: 0.00092145881 | X55: 0.0034192611 | Z55: =IFERROR(IF(INDEX('All GHED Countries'!$D$5:$AB$199,MATCH($B55,'All GHED Countries'!$B$5:$B$199,0),MATCH($D55,'All GHED Countries'!$D$4:$AB$4,0))="","",INDEX('All GHED Countries'!$D$5:$AB$199,MATCH($B55,'All GHED Countries'!$B$5:$B$199,0),MATCH($D55,'All GHED Countries'!$D$4:$AB$4,0))),"") -> 0.08775362
A56: Burkina Faso | B56: BFA | D56: 2024 | E56: Central government (budgetary) | F56: 0.12078583 | G56: 0.077993811 | H56: 0.18263698 | I56: 0.06483796 | J56: 0.22267582 | K56: 0.015540085 | L56: 0.0036312623 | M56: =SUM(S56:Y56) -> 0.096326536 | N56: 0.0084477203 | O56: 0.19285088 | P56: 0.01427312 | R56: =SUM(F56:Q56) -> 1 | S56: 0.010208091 | T56: 0.0064438438 | U56: 0.061360633 | V56: 0.0011925882 | W56: 0.00023276311 | X56: 0.016888616 | Z56: =IFERROR(IF(INDEX('All GHED Countries'!$D$5:$AB$199,MATCH($B56,'All GHED Countries'!$B$5:$B$199,0),MATCH($D56,'All GHED Countries'!$D$4:$AB$4,0))="","",INDEX('All GHED Countries'!$D$5:$AB$199,MATCH($B56,'All GHED Countries'!$B$5:$B$199,0),MATCH($D56,'All GHED Countries'!$D$4:$AB$4,0))),"")
A57: Burundi | B57: BDI | C57: yes | D57: 2010 | E57: Central government (budgetary) | F57: 0.14899462 | G57: 0.02320601 | H57: 0.056307288 | I57: 0.035526071 | J57: 0.050973235 | K57: 0.0049546967 | L57: 0.0039227766 | M57: =SUM(S57:Y57) -> 0.061783078 | N57: 0.0017007925 | O57: 0.14961054 | P57: 0.0068114832 | Q57: 0.4562094 | R57: =SUM(F57:Q57) -> 1 | T57: 4.5500967e-05 | U57: 0.014835207 | V57: 0.0018954745 | Y57: 0.045006896 | Z57: =IFERROR(IF(INDEX('All GHED Countries'!$D$5:$AB$199,MATCH($B57,'All GHED Countries'!$B$5:$B$199,0),MATCH($D57,'All GHED Countries'!$D$4:$AB$4,0))="","",INDEX('All GHED Countries'!$D$5:$AB$199,MATCH($B57,'All GHED Countries'!$B$5:$B$199,0),MATCH($D57,'All GHED Countries'!$D$4:$AB$4,0))),"") -> 0.048606639
A58: Burundi | B58: BDI | C58: yes | D58: 2011 | E58: Central government (budgetary) | F58: 0.14397711 | G58: 0.028247467 | H58: 0.065724276 | I58: 0.043759063 | J58: 0.068024508 | K58: 0.0043232152 | L58: 0.003497345 | M58: =SUM(S58:Y58) -> 0.059117316 | N58: 0.0016423009 | O58: 0.14951016 | P58: 0.0066028007 | Q58: 0.42557444 | R58: =SUM(F58:Q58) -> 1 | T58: 2.865903e-05 | U58: 0.013149509 | V58: 0.0018258919 | Y58: 0.044113256 | Z58: =IFERROR(IF(INDEX('All GHED Countries'!$D$5:$AB$199,MATCH($B58,'All GHED Countries'!$B$5:$B$199,0),MATCH($D58,'All GHED Countries'!$D$4:$AB$4,0))="","",INDEX('All GHED Countries'!$D$5:$AB$199,MATCH($B58,'All GHED Countries'!$B$5:$B$199,0),MATCH($D58,'All GHED Countries'!$D$4:$AB$4,0))),"") -> 0.082279139
A59: Burundi | B59: BDI | C59: yes | D59: 2012 | E59: Central government (budgetary) | F59: 0.18190926 | G59: 0.03264468 | H59: 0.085438949 | I59: 0.049908343 | J59: 0.074448905 | K59: 0.0034699915 | L59: 0.0029051673 | M59: =SUM(S59:Y59) -> 0.086677945 | N59: 0.0021476261 | O59: 0.18136698 | P59: 0.0082051941 | Q59: 0.29087696 | R59: =SUM(F59:Q59) -> 1 | T59: 7.644356e-05 | U59: 0.029744687 | V59: 0.0025948561 | Y59: 0.054261958 | Z59: =IFERROR(IF(INDEX('All GHED Countries'!$D$5:$AB$199,MATCH($B59,'All GHED Countries'!$B$5:$B$199,0),MATCH($D59,'All GHED Countries'!$D$4:$AB$4,0))="","",INDEX('All GHED Countries'!$D$5:$AB$199,MATCH($B59,'All GHED Countries'!$B$5:$B$199,0),MATCH($D59,'All GHED Countries'!$D$4:$AB$4,0))),"") -> 0.071102819
A60: Burundi | B60: BDI | C60: yes | D60: 2013 | E60: Central government (budgetary) | F60: 0.13190589 | G60: 0.027663518 | H60: 0.088884802 | I60: 0.068415313 | J60: 0.080884668 | K60: 0.0046758252 | L60: 0.004336454 | M60: =SUM(S60:Y60) -> 0.084590011 | N60: 0.002337841 | O60: 0.1854479 | P60: 0.0090461744 | Q60: 0.3118116 | R60: =SUM(F60:Q60) -> 1 | S60: 0.051205856 | T60: 7.2260889e-05 | U60: 0.029990378 | V60: 0.0026051437 | W60: 0 | X60: 0.00071637295 | Z60: =IFERROR(IF(INDEX('All GHED Countries'!$D$5:$AB$199,MATCH($B60,'All GHED Countries'!$B$5:$B$199,0),MATCH($D60,'All GHED Countries'!$D$4:$AB$4,0))="","",INDEX('All GHED Countries'!$D$5:$AB$199,MATCH($B60,'All GHED Countries'!$B$5:$B$199,0),MATCH($D60,'All GHED Countries'!$D$4:$AB$4,0))),"") -> 0.044317017
A61: Cameroon | B61: CMR | C61: yes | D61: 2021 | E61: Central government (budgetary) | F61: 0.32703459 | G61: 0.064479223 | H61: 0.066754522 | I61: 0.042719605 | J61: 0.19060522 | K61: 0.0013486388 | L61: 0.039575063 | M61: =SUM(S61:Y61) -> 0.059021733 | N61: 0.020737853 | O61: 0.18217607 | P61: 0.0055474798 | R61: =SUM(F61:Q61) -> 1 | S61: 0.00016101552 | T61: 0 | U61: 0.0027836461 | V61: 0.004879253 | W61: 0.00030157915 | X61: 0.050896239 | Z61: =IFERROR(IF(INDEX('All GHED Countries'!$D$5:$AB$199,MATCH($B61,'All GHED Countries'!$B$5:$B$199,0),MATCH($D61,'All GHED Countries'!$D$4:$AB$4,0))="","",INDEX('All GHED Countries'!$D$5:$AB$199,MATCH($B61,'All GHED Countries'!$B$5:$B$199,0),MATCH($D61,'All GHED Countries'!$D$4:$AB$4,0))),"") -> 0.028629239
A62: Central African Republic | B62: CAF | D62: 2008 | E62: Central government (budgetary) | F62: 0.387288 | G62: 0.079068068 | H62: 0.14028041 | I62: 0.057168468 | J62: 0.040175099 | K62: 0 | L62: 0.03368442 | M62: =SUM(S62:Y62) -> 0.047621826 | N62: 0.0045014787 | O62: 0.083217449 | P62: 0.0048071946 | Q62: 0.12218759 | R62: =SUM(F62:Q62) -> 1 | Y62: 0.047621826 | Z62: =IFERROR(IF(INDEX('All GHED Countries'!$D$5:$AB$199,MATCH($B62,'All GHED Countries'!$B$5:$B$199,0),MATCH($D62,'All GHED Countries'!$D$4:$AB$4,0))="","",INDEX('All GHED Countries'!$D$5:$AB$199,MATCH($B62,'All GHED Countries'!$B$5:$B$199,0),MATCH($D62,'All GHED Countries'!$D$4:$AB$4,0))),"") -> 0.05283493
A63: Central African Republic | B63: CAF | D63: 2009 | E63: Central government (budgetary) | F63: 0.38155311 | G63: 0.055409634 | H63: 0.10123261 | I63: 0.019214 | J63: 0.054616209 | K63: 0 | L63: 0.025626852 | M63: =SUM(S63:Y63) -> 0.034508915 | N63: 0.0058181169 | O63: 0.067768849 | P63: 0.0044167995 | Q63: 0.2498349 | R63: =SUM(F63:Q63) -> 1 | Y63: 0.034508915 | Z63: =IFERROR(IF(INDEX('All GHED Countries'!$D$5:$AB$199,MATCH($B63,'All GHED Countries'!$B$5:$B$199,0),MATCH($D63,'All GHED Countries'!$D$4:$AB$4,0))="","",INDEX('All GHED Countries'!$D$5:$AB$199,MATCH($B63,'All GHED Countries'!$B$5:$B$199,0),MATCH($D63,'All GHED Countries'!$D$4:$AB$4,0))),"") -> 0.04575438
A64: Central African Republic | B64: CAF | D64: 2010 | E64: Central government (budgetary) | F64: 0.232482 | G64: 0.038260755 | H64: 0.096954964 | I64: 0.012793917 | J64: 0.058058463 | K64: 0 | L64: 0.021627694 | M64: =SUM(S64:Y64) -> 0.026153187 | N64: 0.0073733662 | O64: 0.046292448 | P64: 0.0026189802 | Q64: 0.45738422 | R64: =SUM(F64:Q64) -> 1 | Y64: 0.026153187 | Z64: =IFERROR(IF(INDEX('All GHED Countries'!$D$5:$AB$199,MATCH($B64,'All GHED Countries'!$B$5:$B$199,0),MATCH($D64,'All GHED Countries'!$D$4:$AB$4,0))="","",INDEX('All GHED Countries'!$D$5:$AB$199,MATCH($B64,'All GHED Countries'!$B$5:$B$199,0),MATCH($D64,'All GHED Countries'!$D$4:$AB$4,0))),"") -> 0.033414733
A65: Dominican Republic | B65: DOM | D65: 2014 | E65: Central government (budgetary) | F65: 0.13276392 | G65: 0.14058527 | H65: 0.027205334 | I65: 0.043725309 | J65: 0.19694004 | K65: 0.004801196 | L65: 0.016288725 | M65: =SUM(S65:Y65) -> 0.10394916 | N65: 0.0094376639 | O65: 0.22576798 | P65: 0.085200573 | Q65: 0.013334821 | R65: =SUM(F65:Q65) -> 1 | T65: 0.0034278326 | U65: 0.010233424 | V65: 0.0059531345 | W65: 1.0300151e-05 | X65: 0.084324467 | Z65: =IFERROR(IF(INDEX('All GHED Countries'!$D$5:$AB$199,MATCH($B65,'All GHED Countries'!$B$5:$B$199,0),MATCH($D65,'All GHED Countries'!$D$4:$AB$4,0))="","",INDEX('All GHED Countries'!$D$5:$AB$199,MATCH($B65,'All GHED Countries'!$B$5:$B$199,0),MATCH($D65,'All GHED Countries'!$D$4:$AB$4,0))),"") -> 0.14475961
A66: Dominican Republic | B66: DOM | D66: 2015 | E66: General government | F66: 0.09761685 | G66: 0.13286014 | H66: 0.026395317 | I66: 0.041590043 | J66: 0.19693717 | K66: 0.019496303 | L66: 0.023055937 | M66: =SUM(S66:Y66) -> 0.082323853 | N66: 0.0099956829 | O66: 0.2280391 | P66: 0.1416896 | R66: =SUM(F66:Q66) -> 1 | S66: 0 | T66: 0.0044395596 | U66: 0.0087097895 | V66: 0.011415617 | W66: 9.1663797e-06 | X66: 0.057749721 | Z66: =IFERROR(IF(INDEX('All GHED Countries'!$D$5:$AB$199,MATCH($B66,'All GHED Countries'!$B$5:$B$199,0),MATCH($D66,'All GHED Countries'!$D$4:$AB$4,0))="","",INDEX('All GHED Countries'!$D$5:$AB$199,MATCH($B66,'All GHED Countries'!$B$5:$B$199,0),MATCH($D66,'All GHED Countries'!$D$4:$AB$4,0))),"") -> 0.14195518
A67: Dominican Republic | B67: DOM | D67: 2016 | E67: General government | F67: 0.12100331 | G67: 0.14235285 | H67: 0.02688253 | I67: 0.040829548 | J67: 0.17949961 | K67: 0.019760677 | L67: 0.02838493 | M67: =SUM(S67:Y67) -> 0.070458871 | N67: 0.0095199314 | O67: 0.22261269 | P67: 0.13869505 | R67: =SUM(F67:Q67) -> 1 | S67: 0 | T67: 0 | U67: 0.0027994645 | V67: 0.048246913 | W67: 8.2555443e-06 | X67: 0.019404238 | Z67: =IFERROR(IF(INDEX('All GHED Countries'!$D$5:$AB$199,MATCH($B67,'All GHED Countries'!$B$5:$B$199,0),MATCH($D67,'All GHED Countries'!$D$4:$AB$4,0))="","",INDEX('All GHED Countries'!$D$5:$AB$199,MATCH($B67,'All GHED Countries'!$B$5:$B$199,0),MATCH($D67,'All GHED Countries'!$D$4:$AB$4,0))),"") -> 0.15698118
A68: Dominican Republic | B68: DOM | D68: 2017 | E68: General government | F68: 0.10956088 | G68: 0.13982671 | H68: 0.029102478 | I68: 0.043187345 | J68: 0.18848651 | K68: 0.017638405 | L68: 0.022856311 | M68: =SUM(S68:Y68) -> 0.082072437 | N68: 0.0088202808 | O68: 0.22438192 | P68: 0.13406672 | R68: =SUM(F68:Q68) -> 1 | S68: 0 | T68: 0 | U68: 0.002084486 | V68: 0.058958648 | W68: 0.00056428745 | X68: 0.020465016 | Z68: =IFERROR(IF(INDEX('All GHED Countries'!$D$5:$AB$199,MATCH($B68,'All GHED Countries'!$B$5:$B$199,0),MATCH($D68,'All GHED Countries'!$D$4:$AB$4,0))="","",INDEX('All GHED Countries'!$D$5:$AB$199,MATCH($B68,'All GHED Countries'!$B$5:$B$199,0),MATCH($D68,'All GHED Countries'!$D$4:$AB$4,0))),"") -> 0.15108495
A69: Dominican Republic | B69: DOM | D69: 2018 | E69: General government | F69: 0.12923248 | G69: 0.14690032 | H69: 0.031954995 | I69: 0.043700335 | J69: 0.16178895 | K69: 0.010322489 | L69: 0.028454713 | M69: =SUM(S69:Y69) -> 0.080346028 | N69: 0.010548978 | O69: 0.23016161 | P69: 0.12658911 | R69: =SUM(F69:Q69) -> 1 | S69: 0 | T69: 0 | U69: 0.0081238621 | V69: 0.051069464 | W69: 8.3589523e-06 | X69: 0.021144343 | Z69: =IFERROR(IF(INDEX('All GHED Countries'!$D$5:$AB$199,MATCH($B69,'All GHED Countries'!$B$5:$B$199,0),MATCH($D69,'All GHED Countries'!$D$4:$AB$4,0))="","",INDEX('All GHED Countries'!$D$5:$AB$199,MATCH($B69,'All GHED Countries'!$B$5:$B$199,0),MATCH($D69,'All GHED Countries'!$D$4:$AB$4,0))),"") -> 0.15667871
A70: Dominican Republic | B70: DOM | D70: 2019 | E70: General government | F70: 0.18730719 | G70: 0.14302735 | H70: 0.029464911 | I70: 0.046013828 | J70: 0.13592707 | K70: 0.011198986 | L70: 0.025713671 | M70: =SUM(S70:Y70) -> 0.072839334 | N70: 0.0095254982 | O70: 0.21582166 | P70: 0.1231605 | R70: =SUM(F70:Q70) -> 1 | S70: 0 | T70: 4.3942283e-05 | U70: 0.0073963405 | V70: 0.047885278 | W70: 5.8500952e-06 | X70: 0.017507923 | Z70: =IFERROR(IF(INDEX('All GHED Countries'!$D$5:$AB$199,MATCH($B70,'All GHED Countries'!$B$5:$B$199,0),MATCH($D70,'All GHED Countries'!$D$4:$AB$4,0))="","",INDEX('All GHED Countries'!$D$5:$AB$199,MATCH($B70,'All GHED Countries'!$B$5:$B$199,0),MATCH($D70,'All GHED Countries'!$D$4:$AB$4,0))),"") -> 0.14952268
A71: Dominican Republic | B71: DOM | D71: 2020 | E71: General government | F71: 0.11726981 | G71: 0.14016011 | H71: 0.027480484 | I71: 0.041231552 | J71: 0.11813478 | K71: 0.010082889 | L71: 0.023594055 | M71: =SUM(S71:Y71) -> 0.072721874 | N71: 0.0062329097 | O71: 0.20295688 | P71: 0.24013466 | R71: =SUM(F71:Q71) -> 1 | S71: 0 | T71: 3.4122014e-05 | U71: 0.0070898455 | V71: 0.045898671 | W71: 4.9748297e-06 | X71: 0.019694262 | Z71: =IFERROR(IF(INDEX('All GHED Countries'!$D$5:$AB$199,MATCH($B71,'All GHED Countries'!$B$5:$B$199,0),MATCH($D71,'All GHED Countries'!$D$4:$AB$4,0))="","",INDEX('All GHED Countries'!$D$5:$AB$199,MATCH($B71,'All GHED Countries'!$B$5:$B$199,0),MATCH($D71,'All GHED Countries'!$D$4:$AB$4,0))),"") -> 0.14678337
A72: Dominican Republic | B72: DOM | D72: 2021 | E72: General government | F72: 0.085135078 | G72: 0.16373685 | H72: 0.028947716 | I72: 0.04703694 | J72: 0.17997012 | K72: 0.01426695 | L72: 0.020551616 | M72: =SUM(S72:Y72) -> 0.1031584 | N72: 0.0077431944 | O72: 0.19069459 | P72: 0.15875855 | R72: =SUM(F72:Q72) -> 1 | S72: 0 | T72: 3.6365079e-05 | U72: 0.0092400085 | V72: 0.049103757 | W72: 4.9820724e-06 | X72: 0.044773282 | Z72: =IFERROR(IF(INDEX('All GHED Countries'!$D$5:$AB$199,MATCH($B72,'All GHED Countries'!$B$5:$B$199,0),MATCH($D72,'All GHED Countries'!$D$4:$AB$4,0))="","",INDEX('All GHED Countries'!$D$5:$AB$199,MATCH($B72,'All GHED Countries'!$B$5:$B$199,0),MATCH($D72,'All GHED Countries'!$D$4:$AB$4,0))),"") -> 0.18260876
A73: Dominican Republic | B73: DOM | D73: 2022 | E73: General government | F73: 0.098071122 | G73: 0.1451675 | H73: 0.028946384 | I73: 0.040442259 | J73: 0.21846819 | K73: 0.014759531 | L73: 0.025296964 | M73: =SUM(S73:Y73) -> 0.077361778 | N73: 0.0080405214 | O73: 0.19367552 | P73: 0.14977024 | R73: =SUM(F73:Q73) -> 1 | S73: 0 | T73: 3.7974511e-05 | U73: 0.010134884 | V73: 0.042182487 | W73: 6.2945935e-06 | X73: 0.025000138 | Z73: =IFERROR(IF(INDEX('All GHED Countries'!$D$5:$AB$199,MATCH($B73,'All GHED Countries'!$B$5:$B$199,0),MATCH($D73,'All GHED Countries'!$D$4:$AB$4,0))="","",INDEX('All GHED Countries'!$D$5:$AB$199,MATCH($B73,'All GHED Countries'!$B$5:$B$199,0),MATCH($D73,'All GHED Countries'!$D$4:$AB$4,0))),"") -> 0.15200764
A74: Dominican Republic | B74: DOM | D74: 2023 | E74: General government | F74: 0.093728357 | G74: 0.1540978 | H74: 0.032674987 | I74: 0.044305471 | J74: 0.19432711 | K74: 0.014728748 | L74: 0.024603015 | M74: =SUM(S74:Y74) -> 0.081547385 | N74: 0.0095740854 | O74: 0.18988547 | P74: 0.16052757 | R74: =SUM(F74:Q74) -> 1 | S74: 0 | T74: 4.5013132e-05 | U74: 0.011305254 | V74: 0.04798972 | W74: 5.7461872e-06 | X74: 0.022201652 | Z74: =IFERROR(IF(INDEX('All GHED Countries'!$D$5:$AB$199,MATCH($B74,'All GHED Countries'!$B$5:$B$199,0),MATCH($D74,'All GHED Countries'!$D$4:$AB$4,0))="","",INDEX('All GHED Countries'!$D$5:$AB$199,MATCH($B74,'All GHED Countries'!$B$5:$B$199,0),MATCH($D74,'All GHED Countries'!$D$4:$AB$4,0))),"") -> 0.15411339
A75: Dominican Republic | B75: DOM | D75: 2024 | E75: General government | F75: 0.092848887 | G75: 0.16533635 | H75: 0.034017333 | I75: 0.045579022 | J75: 0.1957237 | K75: 0.013458904 | L75: 0.023389792 | M75: =SUM(S75:Y75) -> 0.067427204 | N75: 0.0091553184 | O75: 0.19878968 | P75: 0.15427381 | R75: =SUM(F75:Q75) -> 1 | S75: 0 | T75: 0.00013137259 | U75: 0.0089900813 | V75: 0.037084119 | W75: 5.5631515e-06 | X75: 0.021216067 | Z75: =IFERROR(IF(INDEX('All GHED Countries'!$D$5:$AB$199,MATCH($B75,'All GHED Countries'!$B$5:$B$199,0),MATCH($D75,'All GHED Countries'!$D$4:$AB$4,0))="","",INDEX('All GHED Countries'!$D$5:$AB$199,MATCH($B75,'All GHED Countries'!$B$5:$B$199,0),MATCH($D75,'All GHED Countries'!$D$4:$AB$4,0))),"")
A76: Egypt | B76: EGY | D76: 2005 | E76: General government | F76: 0.11523269 | G76: 0.1738529 | H76: 0.088724433 | I76: 0.053346135 | J76: 0.070492893 | K76: 0.0029546843 | L76: 0.035977626 | M76: =SUM(S76:Y76) -> 0.043499185 | N76: 0.043786862 | O76: 0.15473436 | P76: 0.24097158 | R76: =SUM(F76:Q76) -> 1.0235733 | T76: 0 | U76: 0.025902932 | V76: 0.017596253 | Z76: =IFERROR(IF(INDEX('All GHED Countries'!$D$5:$AB$199,MATCH($B76,'All GHED Countries'!$B$5:$B$199,0),MATCH($D76,'All GHED Countries'!$D$4:$AB$4,0))="","",INDEX('All GHED Countries'!$D$5:$AB$199,MATCH($B76,'All GHED Countries'!$B$5:$B$199,0),MATCH($D76,'All GHED Countries'!$D$4:$AB$4,0))),"") -> 0.052435308
A77: Egypt | B77: EGY | D77: 2006 | E77: General government | F77: 0.080277936 | G77: 0.15587215 | H77: 0.072544133 | I77: 0.047913521 | J77: 0.051613326 | K77: 0.0018767654 | L77: 0.025560343 | M77: =SUM(S77:Y77) -> 0.044006097 | N77: 0.034762504 | O77: 0.1167237 | P77: 0.38439544 | R77: =SUM(F77:Q77) -> 1.0155459 | T77: 0 | U77: 0.030135699 | V77: 0.013870398 | Z77: =IFERROR(IF(INDEX('All GHED Countries'!$D$5:$AB$199,MATCH($B77,'All GHED Countries'!$B$5:$B$199,0),MATCH($D77,'All GHED Countries'!$D$4:$AB$4,0))="","",INDEX('All GHED Countries'!$D$5:$AB$199,MATCH($B77,'All GHED Countries'!$B$5:$B$199,0),MATCH($D77,'All GHED Countries'!$D$4:$AB$4,0))),"") -> 0.050499468
A78: Egypt | B78: EGY | D78: 2007 | E78: General government | F78: 0.083562696 | G78: 0.15863671 | H78: 0.07493186 | I78: 0.046530335 | J78: 0.058174417 | K78: 0.003461867 | L78: 0.038665877 | M78: =SUM(S78:Y78) -> 0.043624541 | N78: 0.036495938 | O78: 0.11606871 | P78: 0.35831427 | R78: =SUM(F78:Q78) -> 1.0184672 | T78: 0.00010870597 | U78: 0.028259371 | V78: 0.015256465 | Z78: =IFERROR(IF(INDEX('All GHED Countries'!$D$5:$AB$199,MATCH($B78,'All GHED Countries'!$B$5:$B$199,0),MATCH($D78,'All GHED Countries'!$D$4:$AB$4,0))="","",INDEX('All GHED Countries'!$D$5:$AB$199,MATCH($B78,'All GHED Countries'!$B$5:$B$199,0),MATCH($D78,'All GHED Countries'!$D$4:$AB$4,0))),"") -> 0.050176458
A79: Egypt | B79: EGY | D79: 2008 | E79: General government | F79: 0.069766654 | G79: 0.13393416 | H79: 0.065566475 | I79: 0.04296648 | J79: 0.060796964 | K79: 0.0029817213 | L79: 0.045340608 | M79: =SUM(S79:Y79) -> 0.043041693 | N79: 0.035886609 | O79: 0.11013206 | P79: 0.38958259 | R79: =SUM(F79:Q79) -> 0.99999601 | T79: 0.0004120387 | U79: 0.02555948 | V79: 0.017070175 | Z79: =IFERROR(IF(INDEX('All GHED Countries'!$D$5:$AB$199,MATCH($B79,'All GHED Countries'!$B$5:$B$199,0),MATCH($D79,'All GHED Countries'!$D$4:$AB$4,0))="","",INDEX('All GHED Countries'!$D$5:$AB$199,MATCH($B79,'All GHED Countries'!$B$5:$B$199,0),MATCH($D79,'All GHED Countries'!$D$4:$AB$4,0))),"") -> 0.046992469
A80: Egypt | B80: EGY | D80: 2009 | E80: General government | F80: 0.084643226 | G80: 0.1225825 | H80: 0.063121929 | I80: 0.045301211 | J80: 0.064441463 | K80: 0.0035271629 | L80: 0.050988376 | M80: =SUM(S80:Y80) -> 0.044217008 | N80: 0.038681407 | O80: 0.11172618 | P80: 0.37076954 | R80: =SUM(F80:Q80) -> 1 | T80: 0.0003812922 | U80: 0.027462003 | V80: 0.016373712 | Z80: =IFERROR(IF(INDEX('All GHED Countries'!$D$5:$AB$199,MATCH($B80,'All GHED Countries'!$B$5:$B$199,0),MATCH($D80,'All GHED Countries'!$D$4:$AB$4,0))="","",INDEX('All GHED Countries'!$D$5:$AB$199,MATCH($B80,'All GHED Countries'!$B$5:$B$199,0),MATCH($D80,'All GHED Countries'!$D$4:$AB$4,0))),"") -> 0.047180848
A81: Egypt | B81: EGY | D81: 2010 | E81: General government | F81: 0.082845171 | G81: 0.15679427 | H81: 0.059993678 | I81: 0.046108843 | J81: 0.066489905 | K81: 0.003448521 | L81: 0.051279104 | M81: =SUM(S81:Y81) -> 0.043716558 | N81: 0.037409394 | O81: 0.11330206 | P81: 0.33860796 | R81: =SUM(F81:Q81) -> 0.99999546 | T81: 0.00042602343 | U81: 0.025818532 | V81: 0.017472002 | Z81: =IFERROR(IF(INDEX('All GHED Countries'!$D$5:$AB$199,MATCH($B81,'All GHED Countries'!$B$5:$B$199,0),MATCH($D81,'All GHED Countries'!$D$4:$AB$4,0))="","",INDEX('All GHED Countries'!$D$5:$AB$199,MATCH($B81,'All GHED Countries'!$B$5:$B$199,0),MATCH($D81,'All GHED Countries'!$D$4:$AB$4,0))),"") -> 0.043615632
A82: Egypt | B82: EGY | D82: 2011 | E82: General government | F82: 0.07524422 | G82: 0.17345135 | H82: 0.060701998 | I82: 0.047071079 | J82: 0.057360708 | K82: 0.0026303291 | L82: 0.029078992 | M82: =SUM(S82:Y82) -> 0.046060287 | N82: 0.034021648 | O82: 0.10951527 | P82: 0.36522959 | R82: =SUM(F82:Q82) -> 1.0003655 | T82: 0.00099943418 | U82: 0.027068766 | V82: 0.017992087 | Z82: =IFERROR(IF(INDEX('All GHED Countries'!$D$5:$AB$199,MATCH($B82,'All GHED Countries'!$B$5:$B$199,0),MATCH($D82,'All GHED Countries'!$D$4:$AB$4,0))="","",INDEX('All GHED Countries'!$D$5:$AB$199,MATCH($B82,'All GHED Countries'!$B$5:$B$199,0),MATCH($D82,'All GHED Countries'!$D$4:$AB$4,0))),"") -> 0.048270822
A83: Egypt | B83: EGY | D83: 2012 | E83: General government | F83: 0.11001081 | G83: 0.18086178 | H83: 0.050816968 | I83: 0.053413681 | J83: 0.052211176 | K83: 0.0027961628 | L83: 0.022260864 | M83: =SUM(S83:Y83) -> 0.043553528 | N83: 0.033879269 | O83: 0.10923044 | P83: 0.34165469 | R83: =SUM(F83:Q83) -> 1.0006894 | Y83: 0.043553528 | Z83: =IFERROR(IF(INDEX('All GHED Countries'!$D$5:$AB$199,MATCH($B83,'All GHED Countries'!$B$5:$B$199,0),MATCH($D83,'All GHED Countries'!$D$4:$AB$4,0))="","",INDEX('All GHED Countries'!$D$5:$AB$199,MATCH($B83,'All GHED Countries'!$B$5:$B$199,0),MATCH($D83,'All GHED Countries'!$D$4:$AB$4,0))),"") -> 0.043854094
A84: Egypt | B84: EGY | D84: 2013 | E84: General government | F84: 0.078257144 | G84: 0.21174286 | H84: 0.06 | I84: 0.06 | J84: 0.06 | K84: 0.003 | L84: 0.03 | M84: =SUM(S84:Y84) -> 0.05 | N84: 0.04 | O84: 0.12 | P84: 0.29 | R84: =SUM(F84:Q84) -> 1.003 | Y84: 0.05 | Z84: =IFERROR(IF(INDEX('All GHED Countries'!$D$5:$AB$199,MATCH($B84,'All GHED Countries'!$B$5:$B$199,0),MATCH($D84,'All GHED Countries'!$D$4:$AB$4,0))="","",INDEX('All GHED Countries'!$D$5:$AB$199,MATCH($B84,'All GHED Countries'!$B$5:$B$199,0),MATCH($D84,'All GHED Countries'!$D$4:$AB$4,0))),"") -> 0.041566329
A85: Egypt | B85: EGY | D85: 2014 | E85: General government | F85: 0.078860898 | G85: 0.2111391 | H85: 0.06 | I85: 0.06 | J85: 0.06 | K85: 0.003 | L85: 0.03 | M85: =SUM(S85:Y85) -> 0.05 | N85: 0.04 | O85: 0.12 | P85: 0.29 | R85: =SUM(F85:Q85) -> 1.003 | Y85: 0.05 | Z85: =IFERROR(IF(INDEX('All GHED Countries'!$D$5:$AB$199,MATCH($B85,'All GHED Countries'!$B$5:$B$199,0),MATCH($D85,'All GHED Countries'!$D$4:$AB$4,0))="","",INDEX('All GHED Countries'!$D$5:$AB$199,MATCH($B85,'All GHED Countries'!$B$5:$B$199,0),MATCH($D85,'All GHED Countries'!$D$4:$AB$4,0))),"") -> 0.041614847
A86: Egypt | B86: EGY | D86: 2015 | E86: General government | F86: 0.066360002 | G86: 0.22364 | H86: 0.06 | I86: 0.06 | J86: 0.06 | K86: 0.003 | L86: 0.03 | M86: =SUM(S86:Y86) -> 0.05 | N86: 0.04 | O86: 0.12 | P86: 0.29 | R86: =SUM(F86:Q86) -> 1.003 | Y86: 0.05 | Z86: =IFERROR(IF(INDEX('All GHED Countries'!$D$5:$AB$199,MATCH($B86,'All GHED Countries'!$B$5:$B$199,0),MATCH($D86,'All GHED Countries'!$D$4:$AB$4,0))="","",INDEX('All GHED Countries'!$D$5:$AB$199,MATCH($B86,'All GHED Countries'!$B$5:$B$199,0),MATCH($D86,'All GHED Countries'!$D$4:$AB$4,0))),"") -> 0.050579767
A87: El Salvador | B87: SLV | D87: 2005 | E87: General government | H87: 0.030988781 | I87: 0.11042675 | J87: 0.12285526 | K87: 0.0060217774 | L87: 0.098630665 | M87: =SUM(S87:Y87) -> 0.15189177 | N87: 0.0069841619 | O87: 0.1408381 | P87: 0.10841949 | Q87: 0.22294324 | R87: =SUM(F87:Q87) -> 1 | T87: 0.0010448746 | U87: 0.129207 | Y87: 0.021639903 | Z87: =IFERROR(IF(INDEX('All GHED Countries'!$D$5:$AB$199,MATCH($B87,'All GHED Countries'!$B$5:$B$199,0),MATCH($D87,'All GHED Countries'!$D$4:$AB$4,0))="","",INDEX('All GHED Countries'!$D$5:$AB$199,MATCH($B87,'All GHED Countries'!$B$5:$B$199,0),MATCH($D87,'All GHED Countries'!$D$4:$AB$4,0))),"") -> 0.18938656
A88: El Salvador | B88: SLV | D88: 2006 | E88: Central government (budgetary) | F88: 0.13772658 | G88: 0.15075811 | H88: 0.035141895 | I88: 0.12441713 | J88: 0.13655313 | K88: 0.0078745021 | L88: 0.014575549 | M88: =SUM(S88:Y88) -> 0.095018991 | N88: 0.0072260136 | O88: 0.16601303 | P88: 0.12469506 | R88: =SUM(F88:Q88) -> 1 | T88: 0.0004014452 | U88: 0.066763425 | V88: 0.005249668 | Y88: 0.022604453 | Z88: =IFERROR(IF(INDEX('All GHED Countries'!$D$5:$AB$199,MATCH($B88,'All GHED Countries'!$B$5:$B$199,0),MATCH($D88,'All GHED Countries'!$D$4:$AB$4,0))="","",INDEX('All GHED Countries'!$D$5:$AB$199,MATCH($B88,'All GHED Countries'!$B$5:$B$199,0),MATCH($D88,'All GHED Countries'!$D$4:$AB$4,0))),"") -> 0.19308365
A89: El Salvador | B89: SLV | D89: 2007 | E89: General government | F89: 0.14288075 | G89: 0.11136107 | H89: 0.030147049 | I89: 0.10653144 | J89: 0.070792186 | K89: 0.0016014031 | L89: 0.047533712 | M89: =SUM(S89:Y89) -> 0.13942375 | N89: 0.0074732146 | O89: 0.13754274 | P89: 0.20032791 | R89: =SUM(F89:Q89) -> 0.99561521 | T89: 0.00012709549 | U89: 0.095499549 | V89: 0.020665726 | Y89: 0.023131379 | Z89: =IFERROR(IF(INDEX('All GHED Countries'!$D$5:$AB$199,MATCH($B89,'All GHED Countries'!$B$5:$B$199,0),MATCH($D89,'All GHED Countries'!$D$4:$AB$4,0))="","",INDEX('All GHED Countries'!$D$5:$AB$199,MATCH($B89,'All GHED Countries'!$B$5:$B$199,0),MATCH($D89,'All GHED Countries'!$D$4:$AB$4,0))),"") -> 0.17984247
A90: El Salvador | B90: SLV | D90: 2008 | E90: General government | F90: 0.16909761 | G90: 0.09778272 | H90: 0.025770162 | I90: 0.10011555 | J90: 0.069897748 | K90: 0.0013517344 | L90: 0.053676935 | M90: =SUM(S90:Y90) -> 0.1498681 | N90: 0.0066714631 | O90: 0.13090021 | P90: 0.21285456 | R90: =SUM(F90:Q90) -> 1.0179868 | T90: 0.00054505418 | U90: 0.1036257 | V90: 0.028713454 | Y90: 0.016983888 | Z90: =IFERROR(IF(INDEX('All GHED Countries'!$D$5:$AB$199,MATCH($B90,'All GHED Countries'!$B$5:$B$199,0),MATCH($D90,'All GHED Countries'!$D$4:$AB$4,0))="","",INDEX('All GHED Countries'!$D$5:$AB$199,MATCH($B90,'All GHED Countries'!$B$5:$B$199,0),MATCH($D90,'All GHED Countries'!$D$4:$AB$4,0))),"") -> 0.16658825
A91: El Salvador | B91: SLV | D91: 2009 | E91: General government | F91: 0.13120254 | G91: 0.096006268 | H91: 0.026758809 | I91: 0.10504641 | J91: 0.087046486 | K91: 0.0054039937 | L91: 0.014303508 | M91: =SUM(S91:Y91) -> 0.14916228 | N91: 0.0065490779 | O91: 0.16905058 | P91: 0.20947005 | R91: =SUM(F91:Q91) -> 1 | Y91: 0.14916228 | Z91: =IFERROR(IF(INDEX('All GHED Countries'!$D$5:$AB$199,MATCH($B91,'All GHED Countries'!$B$5:$B$199,0),MATCH($D91,'All GHED Countries'!$D$4:$AB$4,0))="","",INDEX('All GHED Countries'!$D$5:$AB$199,MATCH($B91,'All GHED Countries'!$B$5:$B$199,0),MATCH($D91,'All GHED Countries'!$D$4:$AB$4,0))),"") -> 0.15814736
A92: El Salvador | B92: SLV | D92: 2010 | E92: General government | F92: 0.15440299 | G92: 0.10288734 | H92: 0.029428701 | I92: 0.11654259 | J92: 0.079628182 | K92: 0.0074240118 | L92: 0.010693867 | M92: =SUM(S92:Y92) -> 0.13595607 | N92: 0.0064368856 | O92: 0.15471147 | P92: 0.20188788 | R92: =SUM(F92:Q92) -> 1 | T92: 0 | U92: 0.073273557 | V92: 0.038292272 | Y92: 0.024390244 | Z92: =IFERROR(IF(INDEX('All GHED Countries'!$D$5:$AB$199,MATCH($B92,'All GHED Countries'!$B$5:$B$199,0),MATCH($D92,'All GHED Countries'!$D$4:$AB$4,0))="","",INDEX('All GHED Countries'!$D$5:$AB$199,MATCH($B92,'All GHED Countries'!$B$5:$B$199,0),MATCH($D92,'All GHED Countries'!$D$4:$AB$4,0))),"") -> 0.17085518
A93: El Salvador | B93: SLV | D93: 2011 | E93: General government | F93: 0.21974803 | G93: 0.09389121 | H93: 0.028078619 | I93: 0.10331583 | J93: 0.067658467 | K93: 0.0031770372 | L93: 0.030421462 | M93: =SUM(S93:Y93) -> 0.15565707 | N93: 0.009016396 | O93: 0.1253421 | P93: 0.1626501 | R93: =SUM(F93:Q93) -> 0.99895633 | Y93: 0.15565707 | Z93: =IFERROR(IF(INDEX('All GHED Countries'!$D$5:$AB$199,MATCH($B93,'All GHED Countries'!$B$5:$B$199,0),MATCH($D93,'All GHED Countries'!$D$4:$AB$4,0))="","",INDEX('All GHED Countries'!$D$5:$AB$199,MATCH($B93,'All GHED Countries'!$B$5:$B$199,0),MATCH($D93,'All GHED Countries'!$D$4:$AB$4,0))),"") -> 0.18986029
A94: El Salvador | B94: SLV | D94: 2012 | E94: General government | F94: 0.36405865 | G94: 0.097277893 | H94: 0.030222128 | I94: 0.098808746 | J94: 0.11831593 | K94: 0.0055558745 | M94: =SUM(S94:Y94) -> 0.13005585 | N94: 0.0055176337 | O94: 0.16004871 | R94: =SUM(F94:Q94) -> 1.0098614 | T94: 0.0017185 | U94: 0.064349678 | V94: 0.063105507 | W94: 0 | X94: 0 | Y94: 0.00088216978 | Z94: =IFERROR(IF(INDEX('All GHED Countries'!$D$5:$AB$199,MATCH($B94,'All GHED Countries'!$B$5:$B$199,0),MATCH($D94,'All GHED Countries'!$D$4:$AB$4,0))="","",INDEX('All GHED Countries'!$D$5:$AB$199,MATCH($B94,'All GHED Countries'!$B$5:$B$199,0),MATCH($D94,'All GHED Countries'!$D$4:$AB$4,0))),"") -> 0.162677
A95: El Salvador | B95: SLV | D95: 2013 | E95: General government | F95: 0.34142515 | G95: 0.093369664 | H95: 0.026868136 | I95: 0.091404508 | J95: 0.10659731 | K95: 0.0048881182 | M95: =SUM(S95:Y95) -> 0.11792585 | N95: 0.0050037156 | O95: 0.1403022 | Q95: 0.072215341 | R95: =SUM(F95:Q95) -> 1 | T95: 0.0067046487 | U95: 0.072347453 | V95: 0.033605813 | Y95: 0.0052679382 | Z95: =IFERROR(IF(INDEX('All GHED Countries'!$D$5:$AB$199,MATCH($B95,'All GHED Countries'!$B$5:$B$199,0),MATCH($D95,'All GHED Countries'!$D$4:$AB$4,0))="","",INDEX('All GHED Countries'!$D$5:$AB$199,MATCH($B95,'All GHED Countries'!$B$5:$B$199,0),MATCH($D95,'All GHED Countries'!$D$4:$AB$4,0))),"") -> 0.16716999
A96: El Salvador | B96: SLV | D96: 2014 | E96: General government | F96: 0.24541774 | G96: 0.11088644 | H96: 0.02856226 | I96: 0.10970346 | J96: 0.087080062 | K96: 0.0059911083 | L96: 0.012713689 | M96: =SUM(S96:Y96) -> 0.092513858 | N96: 0.0028736421 | O96: 0.15580365 | P96: 0.14845409 | R96: =SUM(F96:Q96) -> 1 | S96: 0.0022118336 | T96: 0.0093523987 | U96: 0.02467849 | V96: 0.053310414 | W96: 0.00033090424 | X96: 0.0026298179 | Z96: =IFERROR(IF(INDEX('All GHED Countries'!$D$5:$AB$199,MATCH($B96,'All GHED Countries'!$B$5:$B$199,0),MATCH($D96,'All GHED Countries'!$D$4:$AB$4,0))="","",INDEX('All GHED Countries'!$D$5:$AB$199,MATCH($B96,'All GHED Countries'!$B$5:$B$199,0),MATCH($D96,'All GHED Countries'!$D$4:$AB$4,0))),"") -> 0.16978041
A97: El Salvador | B97: SLV | D97: 2015 | E97: General government | F97: 0.12250477 | G97: 0.10934072 | H97: 0.02949322 | I97: 0.12266662 | J97: 0.15046937 | K97: 0.0061324318 | L97: 0.025213106 | M97: =SUM(S97:Y97) -> 0.16327375 | N97: 0.0040463259 | O97: 0.1721397 | P97: 0.094719994 | R97: =SUM(F97:Q97) -> 1 | S97: 0.0047297054 | T97: 0.03639895 | U97: 0.062079632 | V97: 0.059004424 | W97: 0 | X97: 0.0010610366 | Z97: =IFERROR(IF(INDEX('All GHED Countries'!$D$5:$AB$199,MATCH($B97,'All GHED Countries'!$B$5:$B$199,0),MATCH($D97,'All GHED Countries'!$D$4:$AB$4,0))="","",INDEX('All GHED Countries'!$D$5:$AB$199,MATCH($B97,'All GHED Countries'!$B$5:$B$199,0),MATCH($D97,'All GHED Countries'!$D$4:$AB$4,0))),"") -> 0.17738533
A98: El Salvador | B98: SLV | D98: 2016 | E98: General government | F98: 0.1162236 | G98: 0.10745542 | H98: 0.021846417 | I98: 0.11832928 | J98: 0.11969468 | K98: 0.0066131473 | L98: 0.0084391656 | M98: =SUM(S98:Y98) -> 0.15164177 | N98: 0.0052477463 | O98: 0.16162729 | P98: 0.18288149 | R98: =SUM(F98:Q98) -> 1 | S98: 0.0023030861 | T98: 0.030104626 | U98: 0.065522801 | V98: 0.053102586 | W98: 0 | X98: 0.00060867276 | Z98: =IFERROR(IF(INDEX('All GHED Countries'!$D$5:$AB$199,MATCH($B98,'All GHED Countries'!$B$5:$B$199,0),MATCH($D98,'All GHED Countries'!$D$4:$AB$4,0))="","",INDEX('All GHED Countries'!$D$5:$AB$199,MATCH($B98,'All GHED Countries'!$B$5:$B$199,0),MATCH($D98,'All GHED Countries'!$D$4:$AB$4,0))),"") -> 0.17652054
A99: El Salvador | B99: SLV | D99: 2017 | E99: General government | F99: 0.17563117 | G99: 0.10930964 | H99: 0.024890972 | I99: 0.12187379 | J99: 0.13593616 | K99: 0.0054736405 | L99: 0.012934999 | M99: =SUM(S99:Y99) -> 0.1414988 | N99: 0.0049841279 | O99: 0.085976207 | P99: 0.18149049 | R99: =SUM(F99:Q99) -> 1 | S99: 0.0020618863 | T99: 0.028807073 | U99: 0.055492924 | V99: 0.053846382 | W99: 1.4833714e-05 | X99: 0.0012756994 | Z99: =IFERROR(IF(INDEX('All GHED Countries'!$D$5:$AB$199,MATCH($B99,'All GHED Countries'!$B$5:$B$199,0),MATCH($D99,'All GHED Countries'!$D$4:$AB$4,0))="","",INDEX('All GHED Countries'!$D$5:$AB$199,MATCH($B99,'All GHED Countries'!$B$5:$B$199,0),MATCH($D99,'All GHED Countries'!$D$4:$AB$4,0))),"") -> 0.16314199
A100: El Salvador | B100: SLV | D100: 2018 | E100: General government | F100: 0.16289502 | G100: 0.11177356 | H100: 0.022816195 | I100: 0.11496954 | J100: 0.10677177 | K100: 0.0033249731 | L100: 0.010447868 | M100: =SUM(S100:Y100) -> 0.15018273 | N100: 0.0057900394 | O100: 0.14784665 | P100: 0.16318166 | R100: =SUM(F100:Q100) -> 1 | S100: 0.0010892153 | T100: 0.031701899 | U100: 0.055850949 | V100: 0.046893587 | W100: 0 | X100: 0.01464708 | Z100: =IFERROR(IF(INDEX('All GHED Countries'!$D$5:$AB$199,MATCH($B100,'All GHED Countries'!$B$5:$B$199,0),MATCH($D100,'All GHED Countries'!$D$4:$AB$4,0))="","",INDEX('All GHED Countries'!$D$5:$AB$199,MATCH($B100,'All GHED Countries'!$B$5:$B$199,0),MATCH($D100,'All GHED Countries'!$D$4:$AB$4,0))),"") -> 0.16460562
A101: El Salvador | B101: SLV | D101: 2019 | E101: General government | F101: 0.14940418 | G101: 0.11617477 | H101: 0.025043067 | I101: 0.11677273 | J101: 0.11069349 | K101: 0.0038582554 | L101: 0.0080297271 | M101: =SUM(S101:Y101) -> 0.15356141 | N101: 0.0053246772 | O101: 0.1433107 | P101: 0.16782699 | R101: =SUM(F101:Q101) -> 1 | S101: 0.00108202 | T101: 0.033756175 | U101: 0.059781603 | V101: 0.046555333 | W101: 0 | X101: 0.012386281 | Z101: =IFERROR(IF(INDEX('All GHED Countries'!$D$5:$AB$199,MATCH($B101,'All GHED Countries'!$B$5:$B$199,0),MATCH($D101,'All GHED Countries'!$D$4:$AB$4,0))="","",INDEX('All GHED Countries'!$D$5:$AB$199,MATCH($B101,'All GHED Countries'!$B$5:$B$199,0),MATCH($D101,'All GHED Countries'!$D$4:$AB$4,0))),"") -> 0.16971138
A102: El Salvador | B102: SLV | D102: 2020 | E102: General government | F102: 0.25053673 | G102: 0.092522383 | H102: 0.024221177 | I102: 0.093527316 | J102: 0.10943495 | K102: 0.0047391741 | L102: 0.01881966 | M102: =SUM(S102:Y102) -> 0.1399598 | N102: 0.004179609 | O102: 0.11868491 | P102: 0.14337429 | R102: =SUM(F102:Q102) -> 1 | S102: 0.00078795907 | T102: 0.022234149 | U102: 0.052507765 | V102: 0.05459757 | W102: 0 | X102: 0.0098323589 | Z102: =IFERROR(IF(INDEX('All GHED Countries'!$D$5:$AB$199,MATCH($B102,'All GHED Countries'!$B$5:$B$199,0),MATCH($D102,'All GHED Countries'!$D$4:$AB$4,0))="","",INDEX('All GHED Countries'!$D$5:$AB$199,MATCH($B102,'All GHED Countries'!$B$5:$B$199,0),MATCH($D102,'All GHED Countries'!$D$4:$AB$4,0))),"") -> 0.1772464
...

Sheet Latest Year by Category
A1: Government spending by category, latest year with COFOG data for each country (% of total outlays)
A2: Each value is looked up from 'Spending by Category' for the country's latest year (formulas).
A4: Country | B4: ISO3 | C4: MOU 15 | D4: Latest Year | E4: Coverage | F4: General Public Services (excl. Interest) | G4: Interest on Public Debt | H4: Defence | I4: Public Order and Safety | J4: Economic Affairs | K4: Environmental Protection | L4: Housing and Community Amenities | M4: Health | N4: Recreation, Culture and Religion | O4: Education | P4: Social Protection | Q4: Unclassified | R4: Total | S4: WHO Health Share (GHED)
A5: Angola | B5: AGO | D5: =TEXT(SUMPRODUCT(MAX(('Spending by Category'!$B$5:$B$505=$B5)*('Spending by Category'!$D$5:$D$505+0))),"0") -> 2021 | E5: =INDEX('Spending by Category'!$E$5:$E$505,MATCH(1,INDEX(('Spending by Category'!$B$5:$B$505=$B5)*('Spending by Category'!$D$5:$D$505=$D5),0),0)) -> Central government (budgetary) | F5: =IFERROR(IF(INDEX('Spending by Category'!$F$5:$F$505,MATCH(1,INDEX(('Spending by Category'!$B$5:$B$505=$B5)*('Spending by Category'!$D$5:$D$505=$D5),0),0))="","",INDEX('Spending by Category'!$F$5:$F$505,MATCH(1,INDEX(('Spending by Category'!$B$5:$B$505=$B5)*('Spending by Category'!$D$5:$D$505=$D5),0),0))),"") -> 0.10724204 | G5: =IFERROR(IF(INDEX('Spending by Category'!$G$5:$G$505,MATCH(1,INDEX(('Spending by Category'!$B$5:$B$505=$B5)*('Spending by Category'!$D$5:$D$505=$D5),0),0))="","",INDEX('Spending by Category'!$G$5:$G$505,MATCH(1,INDEX(('Spending by Category'!$B$5:$B$505=$B5)*('Spending by Category'!$D$5:$D$505=$D5),0),0))),"") -> 0.23824708 | H5: =IFERROR(IF(INDEX('Spending by Category'!$H$5:$H$505,MATCH(1,INDEX(('Spending by Category'!$B$5:$B$505=$B5)*('Spending by Category'!$D$5:$D$505=$D5),0),0))="","",INDEX('Spending by Category'!$H$5:$H$505,MATCH(1,INDEX(('Spending by Category'!$B$5:$B$505=$B5)*('Spending by Category'!$D$5:$D$505=$D5),0),0))),"") -> 0.079403848 | I5: =IFERROR(IF(INDEX('Spending by Category'!$I$5:$I$505,MATCH(1,INDEX(('Spending by Category'!$B$5:$B$505=$B5)*('Spending by Category'!$D$5:$D$505=$D5),0),0))="","",INDEX('Spending by Category'!$I$5:$I$505,MATCH(1,INDEX(('Spending by Category'!$B$5:$B$505=$B5)*('Spending by Category'!$D$5:$D$505=$D5),0),0))),"") -> 0.072294254 | J5: =IFERROR(IF(INDEX('Spending by Category'!$J$5:$J$505,MATCH(1,INDEX(('Spending by Category'!$B$5:$B$505=$B5)*('Spending by Category'!$D$5:$D$505=$D5),0),0))="","",INDEX('Spending by Category'!$J$5:$J$505,MATCH(1,INDEX(('Spending by Category'!$B$5:$B$505=$B5)*('Spending by Category'!$D$5:$D$505=$D5),0),0))),"") -> 0.2474218 | K5: =IFERROR(IF(INDEX('Spending by Category'!$K$5:$K$505,MATCH(1,INDEX(('Spending by Category'!$B$5:$B$505=$B5)*('Spending by Category'!$D$5:$D$505=$D5),0),0))="","",INDEX('Spending by Category'!$K$5:$K$505,MATCH(1,INDEX(('Spending by Category'!$B$5:$B$505=$B5)*('Spending by Category'!$D$5:$D$505=$D5),0),0))),"") -> 0.00036318822 | L5: =IFERROR(IF(INDEX('Spending by Category'!$L$5:$L$505,MATCH(1,INDEX(('Spending by Category'!$B$5:$B$505=$B5)*('Spending by Category'!$D$5:$D$505=$D5),0),0))="","",INDEX('Spending by Category'!$L$5:$L$505,MATCH(1,INDEX(('Spending by Category'!$B$5:$B$505=$B5)*('Spending by Category'!$D$5:$D$505=$D5),0),0))),"") -> 0.074011318 | M5: =IFERROR(IF(INDEX('Spending by Category'!$M$5:$M$505,MATCH(1,INDEX(('Spending by Category'!$B$5:$B$505=$B5)*('Spending by Category'!$D$5:$D$505=$D5),0),0))="","",INDEX('Spending by Category'!$M$5:$M$505,MATCH(1,INDEX(('Spending by Category'!$B$5:$B$505=$B5)*('Spending by Category'!$D$5:$D$505=$D5),0),0))),"") -> 0.078667505 | N5: =IFERROR(IF(INDEX('Spending by Category'!$N$5:$N$505,MATCH(1,INDEX(('Spending by Category'!$B$5:$B$505=$B5)*('Spending by Category'!$D$5:$D$505=$D5),0),0))="","",INDEX('Spending by Category'!$N$5:$N$505,MATCH(1,INDEX(('Spending by Category'!$B$5:$B$505=$B5)*('Spending by Category'!$D$5:$D$505=$D5),0),0))),"") -> 0.0052639513 | O5: =IFERROR(IF(INDEX('Spending by Category'!$O$5:$O$505,MATCH(1,INDEX(('Spending by Category'!$B$5:$B$505=$B5)*('Spending by Category'!$D$5:$D$505=$D5),0),0))="","",INDEX('Spending by Category'!$O$5:$O$505,MATCH(1,INDEX(('Spending by Category'!$B$5:$B$505=$B5)*('Spending by Category'!$D$5:$D$505=$D5),0),0))),"") -> 0.073520325 | P5: =IFERROR(IF(INDEX('Spending by Category'!$P$5:$P$505,MATCH(1,INDEX(('Spending by Category'!$B$5:$B$505=$B5)*('Spending by Category'!$D$5:$D$505=$D5),0),0))="","",INDEX('Spending by Category'!$P$5:$P$505,MATCH(1,INDEX(('Spending by Category'!$B$5:$B$505=$B5)*('Spending by Category'!$D$5:$D$505=$D5),0),0))),"") -> 0.023564694 | Q5: =IFERROR(IF(INDEX('Spending by Category'!$Q$5:$Q$505,MATCH(1,INDEX(('Spending by Category'!$B$5:$B$505=$B5)*('Spending by Category'!$D$5:$D$505=$D5),0),0))="","",INDEX('Spending by Category'!$Q$5:$Q$505,MATCH(1,INDEX(('Spending by Category'!$B$5:$B$505=$B5)*('Spending by Category'!$D$5:$D$505=$D5),0),0))),"") | R5: =IFERROR(IF(INDEX('Spending by Category'!$R$5:$R$505,MATCH(1,INDEX(('Spending by Category'!$B$5:$B$505=$B5)*('Spending by Category'!$D$5:$D$505=$D5),0),0))="","",INDEX('Spending by Category'!$R$5:$R$505,MATCH(1,INDEX(('Spending by Category'!$B$5:$B$505=$B5)*('Spending by Category'!$D$5:$D$505=$D5),0),0))),"") -> 1 | S5: =IFERROR(IF(INDEX('Spending by Category'!$Z$5:$Z$505,MATCH(1,INDEX(('Spending by Category'!$B$5:$B$505=$B5)*('Spending by Category'!$D$5:$D$505=$D5),0),0))="","",INDEX('Spending by Category'!$Z$5:$Z$505,MATCH(1,INDEX(('Spending by Category'!$B$5:$B$505=$B5)*('Spending by Category'!$D$5:$D$505=$D5),0),0))),"") -> 0.087773657
A6: Azerbaijan | B6: AZE | D6: =TEXT(SUMPRODUCT(MAX(('Spending by Category'!$B$5:$B$505=$B6)*('Spending by Category'!$D$5:$D$505+0))),"0") -> 2024 | E6: =INDEX('Spending by Category'!$E$5:$E$505,MATCH(1,INDEX(('Spending by Category'!$B$5:$B$505=$B6)*('Spending by Category'!$D$5:$D$505=$D6),0),0)) -> General government | F6: =IFERROR(IF(INDEX('Spending by Category'!$F$5:$F$505,MATCH(1,INDEX(('Spending by Category'!$B$5:$B$505=$B6)*('Spending by Category'!$D$5:$D$505=$D6),0),0))="","",INDEX('Spending by Category'!$F$5:$F$505,MATCH(1,INDEX(('Spending by Category'!$B$5:$B$505=$B6)*('Spending by Category'!$D$5:$D$505=$D6),0),0))),"") -> 0.11772124 | G6: =IFERROR(IF(INDEX('Spending by Category'!$G$5:$G$505,MATCH(1,INDEX(('Spending by Category'!$B$5:$B$505=$B6)*('Spending by Category'!$D$5:$D$505=$D6),0),0))="","",INDEX('Spending by Category'!$G$5:$G$505,MATCH(1,INDEX(('Spending by Category'!$B$5:$B$505=$B6)*('Spending by Category'!$D$5:$D$505=$D6),0),0))),"") -> 0.010000538 | H6: =IFERROR(IF(INDEX('Spending by Category'!$H$5:$H$505,MATCH(1,INDEX(('Spending by Category'!$B$5:$B$505=$B6)*('Spending by Category'!$D$5:$D$505=$D6),0),0))="","",INDEX('Spending by Category'!$H$5:$H$505,MATCH(1,INDEX(('Spending by Category'!$B$5:$B$505=$B6)*('Spending by Category'!$D$5:$D$505=$D6),0),0))),"") -> 0.1382346 | I6: =IFERROR(IF(INDEX('Spending by Category'!$I$5:$I$505,MATCH(1,INDEX(('Spending by Category'!$B$5:$B$505=$B6)*('Spending by Category'!$D$5:$D$505=$D6),0),0))="","",INDEX('Spending by Category'!$I$5:$I$505,MATCH(1,INDEX(('Spending by Category'!$B$5:$B$505=$B6)*('Spending by Category'!$D$5:$D$505=$D6),0),0))),"") -> 0.073798963 | J6: =IFERROR(IF(INDEX('Spending by Category'!$J$5:$J$505,MATCH(1,INDEX(('Spending by Category'!$B$5:$B$505=$B6)*('Spending by Category'!$D$5:$D$505=$D6),0),0))="","",INDEX('Spending by Category'!$J$5:$J$505,MATCH(1,INDEX(('Spending by Category'!$B$5:$B$505=$B6)*('Spending by Category'!$D$5:$D$505=$D6),0),0))),"") -> 0.24442 | K6: =IFERROR(IF(INDEX('Spending by Category'!$K$5:$K$505,MATCH(1,INDEX(('Spending by Category'!$B$5:$B$505=$B6)*('Spending by Category'!$D$5:$D$505=$D6),0),0))="","",INDEX('Spending by Category'!$K$5:$K$505,MATCH(1,INDEX(('Spending by Category'!$B$5:$B$505=$B6)*('Spending by Category'!$D$5:$D$505=$D6),0),0))),"") -> 0.0078692607 | L6: =IFERROR(IF(INDEX('Spending by Category'!$L$5:$L$505,MATCH(1,INDEX(('Spending by Category'!$B$5:$B$505=$B6)*('Spending by Category'!$D$5:$D$505=$D6),0),0))="","",INDEX('Spending by Category'!$L$5:$L$505,MATCH(1,INDEX(('Spending by Category'!$B$5:$B$505=$B6)*('Spending by Category'!$D$5:$D$505=$D6),0),0))),"") -> 0.0075353542 | M6: =IFERROR(IF(INDEX('Spending by Category'!$M$5:$M$505,MATCH(1,INDEX(('Spending by Category'!$B$5:$B$505=$B6)*('Spending by Category'!$D$5:$D$505=$D6),0),0))="","",INDEX('Spending by Category'!$M$5:$M$505,MATCH(1,INDEX(('Spending by Category'!$B$5:$B$505=$B6)*('Spending by Category'!$D$5:$D$505=$D6),0),0))),"") -> 0.041279279 | N6: =IFERROR(IF(INDEX('Spending by Category'!$N$5:$N$505,MATCH(1,INDEX(('Spending by Category'!$B$5:$B$505=$B6)*('Spending by Category'!$D$5:$D$505=$D6),0),0))="","",INDEX('Spending by Category'!$N$5:$N$505,MATCH(1,INDEX(('Spending by Category'!$B$5:$B$505=$B6)*('Spending by Category'!$D$5:$D$505=$D6),0),0))),"") -> 0.0116454 | O6: =IFERROR(IF(INDEX('Spending by Category'!$O$5:$O$505,MATCH(1,INDEX(('Spending by Category'!$B$5:$B$505=$B6)*('Spending by Category'!$D$5:$D$505=$D6),0),0))="","",INDEX('Spending by Category'!$O$5:$O$505,MATCH(1,INDEX(('Spending by Category'!$B$5:$B$505=$B6)*('Spending by Category'!$D$5:$D$505=$D6),0),0))),"") -> 0.10360371 | P6: =IFERROR(IF(INDEX('Spending by Category'!$P$5:$P$505,MATCH(1,INDEX(('Spending by Category'!$B$5:$B$505=$B6)*('Spending by Category'!$D$5:$D$505=$D6),0),0))="","",INDEX('Spending by Category'!$P$5:$P$505,MATCH(1,INDEX(('Spending by Category'!$B$5:$B$505=$B6)*('Spending by Category'!$D$5:$D$505=$D6),0),0))),"") -> 0.24389165 | Q6: =IFERROR(IF(INDEX('Spending by Category'!$Q$5:$Q$505,MATCH(1,INDEX(('Spending by Category'!$B$5:$B$505=$B6)*('Spending by Category'!$D$5:$D$505=$D6),0),0))="","",INDEX('Spending by Category'!$Q$5:$Q$505,MATCH(1,INDEX(('Spending by Category'!$B$5:$B$505=$B6)*('Spending by Category'!$D$5:$D$505=$D6),0),0))),"") | R6: =IFERROR(IF(INDEX('Spending by Category'!$R$5:$R$505,MATCH(1,INDEX(('Spending by Category'!$B$5:$B$505=$B6)*('Spending by Category'!$D$5:$D$505=$D6),0),0))="","",INDEX('Spending by Category'!$R$5:$R$505,MATCH(1,INDEX(('Spending by Category'!$B$5:$B$505=$B6)*('Spending by Category'!$D$5:$D$505=$D6),0),0))),"") -> 1 | S6: =IFERROR(IF(INDEX('Spending by Category'!$Z$5:$Z$505,MATCH(1,INDEX(('Spending by Category'!$B$5:$B$505=$B6)*('Spending by Category'!$D$5:$D$505=$D6),0),0))="","",INDEX('Spending by Category'!$Z$5:$Z$505,MATCH(1,INDEX(('Spending by Category'!$B$5:$B$505=$B6)*('Spending by Category'!$D$5:$D$505=$D6),0),0))),"")
A7: Bangladesh | B7: BGD | D7: =TEXT(SUMPRODUCT(MAX(('Spending by Category'!$B$5:$B$505=$B7)*('Spending by Category'!$D$5:$D$505+0))),"0") -> 2016 | E7: =INDEX('Spending by Category'!$E$5:$E$505,MATCH(1,INDEX(('Spending by Category'!$B$5:$B$505=$B7)*('Spending by Category'!$D$5:$D$505=$D7),0),0)) -> Central government (budgetary) | F7: =IFERROR(IF(INDEX('Spending by Category'!$F$5:$F$505,MATCH(1,INDEX(('Spending by Category'!$B$5:$B$505=$B7)*('Spending by Category'!$D$5:$D$505=$D7),0),0))="","",INDEX('Spending by Category'!$F$5:$F$505,MATCH(1,INDEX(('Spending by Category'!$B$5:$B$505=$B7)*('Spending by Category'!$D$5:$D$505=$D7),0),0))),"") -> 0.050183173 | G7: =IFERROR(IF(INDEX('Spending by Category'!$G$5:$G$505,MATCH(1,INDEX(('Spending by Category'!$B$5:$B$505=$B7)*('Spending by Category'!$D$5:$D$505=$D7),0),0))="","",INDEX('Spending by Category'!$G$5:$G$505,MATCH(1,INDEX(('Spending by Category'!$B$5:$B$505=$B7)*('Spending by Category'!$D$5:$D$505=$D7),0),0))),"") -> 0.16170134 | H7: =IFERROR(IF(INDEX('Spending by Category'!$H$5:$H$505,MATCH(1,INDEX(('Spending by Category'!$B$5:$B$505=$B7)*('Spending by Category'!$D$5:$D$505=$D7),0),0))="","",INDEX('Spending by Category'!$H$5:$H$505,MATCH(1,INDEX(('Spending by Category'!$B$5:$B$505=$B7)*('Spending by Category'!$D$5:$D$505=$D7),0),0))),"") -> 0.10010222 | I7: =IFERROR(IF(INDEX('Spending by Category'!$I$5:$I$505,MATCH(1,INDEX(('Spending by Category'!$B$5:$B$505=$B7)*('Spending by Category'!$D$5:$D$505=$D7),0),0))="","",INDEX('Spending by Category'!$I$5:$I$505,MATCH(1,INDEX(('Spending by Category'!$B$5:$B$505=$B7)*('Spending by Category'!$D$5:$D$505=$D7),0),0))),"") -> 0.093616563 | J7: =IFERROR(IF(INDEX('Spending by Category'!$J$5:$J$505,MATCH(1,INDEX(('Spending by Category'!$B$5:$B$505=$B7)*('Spending by Category'!$D$5:$D$505=$D7),0),0))="","",INDEX('Spending by Category'!$J$5:$J$505,MATCH(1,INDEX(('Spending by Category'!$B$5:$B$505=$B7)*('Spending by Category'!$D$5:$D$505=$D7),0),0))),"") -> 0.19136615 | K7: =IFERROR(IF(INDEX('Spending by Category'!$K$5:$K$505,MATCH(1,INDEX(('Spending by Category'!$B$5:$B$505=$B7)*('Spending by Category'!$D$5:$D$505=$D7),0),0))="","",INDEX('Spending by Category'!$K$5:$K$505,MATCH(1,INDEX(('Spending by Category'!$B$5:$B$505=$B7)*('Spending by Category'!$D$5:$D$505=$D7),0),0))),"") -> 0.0013841947 | L7: =IFERROR(IF(INDEX('Spending by Category'!$L$5:$L$505,MATCH(1,INDEX(('Spending by Category'!$B$5:$B$505=$B7)*('Spending by Category'!$D$5:$D$505=$D7),0),0))="","",INDEX('Spending by Category'!$L$5:$L$505,MATCH(1,INDEX(('Spending by Category'!$B$5:$B$505=$B7)*('Spending by Category'!$D$5:$D$505=$D7),0),0))),"") -> 0.080297969 | M7: =IFERROR(IF(INDEX('Spending by Category'!$M$5:$M$505,MATCH(1,INDEX(('Spending by Category'!$B$5:$B$505=$B7)*('Spending by Category'!$D$5:$D$505=$D7),0),0))="","",INDEX('Spending by Category'!$M$5:$M$505,MATCH(1,INDEX(('Spending by Category'!$B$5:$B$505=$B7)*('Spending by Category'!$D$5:$D$505=$D7),0),0))),"") -> 0.060948589 | N7: =IFERROR(IF(INDEX('Spending by Category'!$N$5:$N$505,MATCH(1,INDEX(('Spending by Category'!$B$5:$B$505=$B7)*('Spending by Category'!$D$5:$D$505=$D7),0),0))="","",INDEX('Spending by Category'!$N$5:$N$505,MATCH(1,INDEX(('Spending by Category'!$B$5:$B$505=$B7)*('Spending by Category'!$D$5:$D$505=$D7),0),0))),"") -> 0.010936606 | O7: =IFERROR(IF(INDEX('Spending by Category'!$O$5:$O$505,MATCH(1,INDEX(('Spending by Category'!$B$5:$B$505=$B7)*('Spending by Category'!$D$5:$D$505=$D7),0),0))="","",INDEX('Spending by Category'!$O$5:$O$505,MATCH(1,INDEX(('Spending by Category'!$B$5:$B$505=$B7)*('Spending by Category'!$D$5:$D$505=$D7),0),0))),"") -> 0.18625979 | P7: =IFERROR(IF(INDEX('Spending by Category'!$P$5:$P$505,MATCH(1,INDEX(('Spending by Category'!$B$5:$B$505=$B7)*('Spending by Category'!$D$5:$D$505=$D7),0),0))="","",INDEX('Spending by Category'!$P$5:$P$505,MATCH(1,INDEX(('Spending by Category'!$B$5:$B$505=$B7)*('Spending by Category'!$D$5:$D$505=$D7),0),0))),"") -> 0.063203408 | Q7: =IFERROR(IF(INDEX('Spending by Category'!$Q$5:$Q$505,MATCH(1,INDEX(('Spending by Category'!$B$5:$B$505=$B7)*('Spending by Category'!$D$5:$D$505=$D7),0),0))="","",INDEX('Spending by Category'!$Q$5:$Q$505,MATCH(1,INDEX(('Spending by Category'!$B$5:$B$505=$B7)*('Spending by Category'!$D$5:$D$505=$D7),0),0))),"") | R7: =IFERROR(IF(INDEX('Spending by Category'!$R$5:$R$505,MATCH(1,INDEX(('Spending by Category'!$B$5:$B$505=$B7)*('Spending by Category'!$D$5:$D$505=$D7),0),0))="","",INDEX('Spending by Category'!$R$5:$R$505,MATCH(1,INDEX(('Spending by Category'!$B$5:$B$505=$B7)*('Spending by Category'!$D$5:$D$505=$D7),0),0))),"") -> 1 | S7: =IFERROR(IF(INDEX('Spending by Category'!$Z$5:$Z$505,MATCH(1,INDEX(('Spending by Category'!$B$5:$B$505=$B7)*('Spending by Category'!$D$5:$D$505=$D7),0),0))="","",INDEX('Spending by Category'!$Z$5:$Z$505,MATCH(1,INDEX(('Spending by Category'!$B$5:$B$505=$B7)*('Spending by Category'!$D$5:$D$505=$D7),0),0))),"") -> 0.040993581
